Workbook

Sheet shadow
A1: Shadow Empresa: | AN1: Sim
B3: ANTERIOR | C3: Memoria Anteior | E3: ANO 1 | F3: ANO 2 | G3: ANO 3 | H3: Memoria Atual | I3: Memoria Atual Ajustada | J3: Retirar | K3: Retirar | L3: Retirar | M3: Retirar | N3: Adicionar | O3: Adicionar | P3: Adicionar | Q3: Adicionar | T3: ANTERIOR | U3: Memoria Anteior | W3: ATUAL 1 | X3: ATUAL 2 | Y3: ATUAL 3 | Z3: Memoria Atual | AA3: Memoria Atual Ajustada | AB3: Inversor de Sinal | AC3: Retirar | AD3: Retirar | AE3: Retirar | AF3: Retirar | AG3: Adicionar | AH3: Adicionar | AI3: Adicionar | AJ3: Adicionar
A4: ATIVO | B4: =B2 -> 0 | E4: =E2 -> 0 | F4: =F2 -> 0 | G4: =G2 -> 0 | S4: DEMONSTRAÇÃO DE RESULTADOS | T4: =+B4 -> 0 | W4: =+E4 -> 0 | X4: =+F4 -> 0 | Y4: =+G4 -> 0
A5: Caixa | B5: =IFERROR(SUMIFS(INDEX(rastreabilidade!$F:$H,0,MATCH($B$2,rastreabilidade!$F$1:$H$1,0)),rastreabilidade!$K:$K,$A5,rastreabilidade!$D:$D,"Sim"),0) -> 0 | E5: =IFERROR(SUMIFS(INDEX(rastreabilidade!$F:$H,0,MATCH(E$3,rastreabilidade!$F$1:$H$1,0)),rastreabilidade!$N:$N,$AM5),0) +IF($N5="",0,IFERROR(SUMIFS(INDEX(rastreabilidade!$F:$H,0,MATCH(E$3,rastreabilidade!$F$1:$H$1,0)),rastreabilidade!$M:$M,$N5),0)) +IF($O5="",0,IFERROR(SUMIFS(INDEX(rastreabilidade!$F:$H,0,MATCH(E$3,rastreabilidade!$F$1:$H$1,0)),rastreabilidade!$M:$M,$O5),0)) +IF($P5="",0,IFERROR(SUMIFS(INDEX(rastreabilidade!$F:$H,0,MATCH(E$3,rastreabilidade!$F$1:$H$1,0)),rastreabilidade!$M:$M,$P5),0)) +IF($Q5="",0,IFERROR(SUMIFS(INDEX(rastreabilidade!$F:$H,0,MATCH(E$3,rastreabilidade!$F$1:$H$1,0)),rastreabilidade!$M:$M,$Q5),0)) -IF($J5="",0,IFERROR(SUMIFS(INDEX(rastreabilidade!$F:$H,0,MATCH(E$3,rastreabilidade!$F$1:$H$1,0)),rastreabilidade!$M:$M,$J5,rastreabilidade!$N:$N,$AM5),0)) -IF($K5="",0,IFERROR(SUMIFS(INDEX(rastreabilidade!$F:$H,0,MATCH(E$3,rastreabilidade!$F$1:$H$1,0)),rastreabilidade!$M:$M,$K5,rastreabilidade!$N:$N,$AM5),0)) -IF($L5="",0,IFERROR(SUMIFS(INDEX(rastreabilidade!$F:$H,0,MATCH(E$3,rastreabilidade!$F$1:$H$1,0)),rastreabilidade!$M:$M,$L5,rastreabilidade!$N:$N,$AM5),0)) -IF($M5="",0,IFERROR(SUMIFS(INDEX(rastreabilidade!$F:$H,0,MATCH(E$3,rastreabilidade!$F$1:$H$1,0)),rastreabilidade!$M:$M,$M5,rastreabilidade!$N:$N,$AM5),0)) -> 0 | F5: =IFERROR(SUMIFS(INDEX(rastreabilidade!$F:$H,0,MATCH(F$3,rastreabilidade!$F$1:$H$1,0)),rastreabilidade!$N:$N,$AM5),0) +IF($N5="",0,IFERROR(SUMIFS(INDEX(rastreabilidade!$F:$H,0,MATCH(F$3,rastreabilidade!$F$1:$H$1,0)),rastreabilidade!$M:$M,$N5),0)) +IF($O5="",0,IFERROR(SUMIFS(INDEX(rastreabilidade!$F:$H,0,MATCH(F$3,rastreabilidade!$F$1:$H$1,0)),rastreabilidade!$M:$M,$O5),0)) +IF($P5="",0,IFERROR(SUMIFS(INDEX(rastreabilidade!$F:$H,0,MATCH(F$3,rastreabilidade!$F$1:$H$1,0)),rastreabilidade!$M:$M,$P5),0)) +IF($Q5="",0,IFERROR(SUMIFS(INDEX(rastreabilidade!$F:$H,0,MATCH(F$3,rastreabilidade!$F$1:$H$1,0)),rastreabilidade!$M:$M,$Q5),0)) -IF($J5="",0,IFERROR(SUMIFS(INDEX(rastreabilidade!$F:$H,0,MATCH(F$3,rastreabilidade!$F$1:$H$1,0)),rastreabilidade!$M:$M,$J5,rastreabilidade!$N:$N,$AM5),0)) -IF($K5="",0,IFERROR(SUMIFS(INDEX(rastreabilidade!$F:$H,0,MATCH(F$3,rastreabilidade!$F$1:$H$1,0)),rastreabilidade!$M:$M,$K5,rastreabilidade!$N:$N,$AM5),0)) -IF($L5="",0,IFERROR(SUMIFS(INDEX(rastreabilidade!$F:$H,0,MATCH(F$3,rastreabilidade!$F$1:$H$1,0)),rastreabilidade!$M:$M,$L5,rastreabilidade!$N:$N,$AM5),0)) -IF($M5="",0,IFERROR(SUMIFS(INDEX(rastreabilidade!$F:$H,0,MATCH(F$3,rastreabilidade!$F$1:$H$1,0)),rastreabilidade!$M:$M,$M5,rastreabilidade!$N:$N,$AM5),0)) -> 0 | G5: =IFERROR(SUMIFS(INDEX(rastreabilidade!$F:$H,0,MATCH(G$3,rastreabilidade!$F$1:$H$1,0)),rastreabilidade!$N:$N,$AM5),0) +IF($N5="",0,IFERROR(SUMIFS(INDEX(rastreabilidade!$F:$H,0,MATCH(G$3,rastreabilidade!$F$1:$H$1,0)),rastreabilidade!$M:$M,$N5),0)) +IF($O5="",0,IFERROR(SUMIFS(INDEX(rastreabilidade!$F:$H,0,MATCH(G$3,rastreabilidade!$F$1:$H$1,0)),rastreabilidade!$M:$M,$O5),0)) +IF($P5="",0,IFERROR(SUMIFS(INDEX(rastreabilidade!$F:$H,0,MATCH(G$3,rastreabilidade!$F$1:$H$1,0)),rastreabilidade!$M:$M,$P5),0)) +IF($Q5="",0,IFERROR(SUMIFS(INDEX(rastreabilidade!$F:$H,0,MATCH(G$3,rastreabilidade!$F$1:$H$1,0)),rastreabilidade!$M:$M,$Q5),0)) -IF($J5="",0,IFERROR(SUMIFS(INDEX(rastreabilidade!$F:$H,0,MATCH(G$3,rastreabilidade!$F$1:$H$1,0)),rastreabilidade!$M:$M,$J5,rastreabilidade!$N:$N,$AM5),0)) -IF($K5="",0,IFERROR(SUMIFS(INDEX(rastreabilidade!$F:$H,0,MATCH(G$3,rastreabilidade!$F$1:$H$1,0)),rastreabilidade!$M:$M,$K5,rastreabilidade!$N:$N,$AM5),0)) -IF($L5="",0,IFERROR(SUMIFS(INDEX(rastreabilidade!$F:$H,0,MATCH(G$3,rastreabilidade!$F$1:$H$1,0)),rastreabilidade!$M:$M,$L5,rastreabilidade!$N:$N,$AM5),0)) -IF($M5="",0,IFERROR(SUMIFS(INDEX(rastreabilidade!$F:$H,0,MATCH(G$3,rastreabilidade!$F$1:$H$1,0)),rastreabilidade!$M:$M,$M5,rastreabilidade!$N:$N,$AM5),0)) -> 0 | I5: {=_xlfn.LET( _xlpm.mem,H5, _xlpm.retiradas,J5:M5, _xlpm.adicoes,N5:Q5, _xlpm.memAjustada,_xlfn.REDUCE(_xlpm.mem,_xlpm.retiradas,_xlfn.LAMBDA(_xlpm.x,_xlpm.y,IF(_xlpm.y<>"",SUBSTITUTE(_xlpm.x," + ("&_xlpm.y&")",""),_xlpm.x))), _xlpm.memRemovida,_xlfn.REDUCE(_xlpm.memAjustada,_xlpm.retiradas,_xlfn.LAMBDA(_xlpm.x,_xlpm.y,IF(_xlpm.y<>"",SUBSTITUTE(_xlpm.x,"("&_xlpm.y&")",""),_xlpm.x))), _xlpm.memSemSinal,IF(OR(LEFT(_xlpm.memRemovida,3)=" + ",LEFT(_xlpm.memRemovida,3)=" - "),MID(_xlpm.memRemovida,4,LEN(_xlpm.memRemovida)),_xlpm.memRemovida), _xlpm.memFinal,IF(OR(RIGHT(_xlpm.memSemSinal,3)=" + ",RIGHT(_xlpm.memSemSinal,3)=" - "),LEFT(_xlpm.memSemSinal,LEN(_xlpm.memSemSinal)-3),_xlpm.memSemSinal), _xlpm.adicoesTxt,_xlfn.TEXTJOIN(" + ",TRUE,IF(_xlpm.adicoes<>"","("&_xlpm.adicoes&")","")), IF(_xlpm.memFinal="",_xlpm.adicoesTxt,IF(_xlpm.adicoesTxt="",_xlpm.memFinal,_xlpm.memFinal&" + "&_xlpm.adicoesTxt)) )} | S5: Vendas Totais | T5: =IFERROR(SUMIFS(INDEX(rastreabilidade!$F:$H,0,MATCH($T$2,rastreabilidade!$F$1:$H$1,0)),rastreabilidade!$K:$K,$S5,rastreabilidade!$D:$D,"Sim"),0) -> 0 | W5: =IFERROR(SUMIFS(INDEX(rastreabilidade!$F:$H,0,MATCH(W$3,rastreabilidade!$F$1:$H$1,0)),rastreabilidade!$N:$N,$AN5),0)*IF($AB5="sim",-1,1) +IF($AG5="",0,IFERROR(SUMIFS(INDEX(rastreabilidade!$F:$H,0,MATCH(W$3,rastreabilidade!$F$1:$H$1,0)),rastreabilidade!$M:$M,$AG5),0)) +IF($AH5="",0,IFERROR(SUMIFS(INDEX(rastreabilidade!$F:$H,0,MATCH(W$3,rastreabilidade!$F$1:$H$1,0)),rastreabilidade!$M:$M,$AH5),0)) +IF($AI5="",0,IFERROR(SUMIFS(INDEX(rastreabilidade!$F:$H,0,MATCH(W$3,rastreabilidade!$F$1:$H$1,0)),rastreabilidade!$M:$M,$AI5),0)) +IF($AJ5="",0,IFERROR(SUMIFS(INDEX(rastreabilidade!$F:$H,0,MATCH(W$3,rastreabilidade!$F$1:$H$1,0)),rastreabilidade!$M:$M,$AJ5),0)) -IF($AC5="",0,IFERROR(SUMIFS(INDEX(rastreabilidade!$F:$H,0,MATCH(W$3,rastreabilidade!$F$1:$H$1,0)),rastreabilidade!$M:$M,$AC5,rastreabilidade!$N:$N,$AN5),0)) -IF($AD5="",0,IFERROR(SUMIFS(INDEX(rastreabilidade!$F:$H,0,MATCH(W$3,rastreabilidade!$F$1:$H$1,0)),rastreabilidade!$M:$M,$AD5,rastreabilidade!$N:$N,$AN5),0)) -IF($AE5="",0,IFERROR(SUMIFS(INDEX(rastreabilidade!$F:$H,0,MATCH(W$3,rastreabilidade!$F$1:$H$1,0)),rastreabilidade!$M:$M,$AE5,rastreabilidade!$N:$N,$AN5),0)) -IF($AF5="",0,IFERROR(SUMIFS(INDEX(rastreabilidade!$F:$H,0,MATCH(W$3,rastreabilidade!$F$1:$H$1,0)),rastreabilidade!$M:$M,$AF5,rastreabilidade!$N:$N,$AN5),0)) -> 0 | X5: =IFERROR(SUMIFS(INDEX(rastreabilidade!$F:$H,0,MATCH(X$3,rastreabilidade!$F$1:$H$1,0)),rastreabilidade!$N:$N,$AN5),0)*IF($AB5="sim",-1,1) +IF($AG5="",0,IFERROR(SUMIFS(INDEX(rastreabilidade!$F:$H,0,MATCH(X$3,rastreabilidade!$F$1:$H$1,0)),rastreabilidade!$M:$M,$AG5),0)) +IF($AH5="",0,IFERROR(SUMIFS(INDEX(rastreabilidade!$F:$H,0,MATCH(X$3,rastreabilidade!$F$1:$H$1,0)),rastreabilidade!$M:$M,$AH5),0)) +IF($AI5="",0,IFERROR(SUMIFS(INDEX(rastreabilidade!$F:$H,0,MATCH(X$3,rastreabilidade!$F$1:$H$1,0)),rastreabilidade!$M:$M,$AI5),0)) +IF($AJ5="",0,IFERROR(SUMIFS(INDEX(rastreabilidade!$F:$H,0,MATCH(X$3,rastreabilidade!$F$1:$H$1,0)),rastreabilidade!$M:$M,$AJ5),0)) -IF($AC5="",0,IFERROR(SUMIFS(INDEX(rastreabilidade!$F:$H,0,MATCH(X$3,rastreabilidade!$F$1:$H$1,0)),rastreabilidade!$M:$M,$AC5,rastreabilidade!$N:$N,$AN5),0)) -IF($AD5="",0,IFERROR(SUMIFS(INDEX(rastreabilidade!$F:$H,0,MATCH(X$3,rastreabilidade!$F$1:$H$1,0)),rastreabilidade!$M:$M,$AD5,rastreabilidade!$N:$N,$AN5),0)) -IF($AE5="",0,IFERROR(SUMIFS(INDEX(rastreabilidade!$F:$H,0,MATCH(X$3,rastreabilidade!$F$1:$H$1,0)),rastreabilidade!$M:$M,$AE5,rastreabilidade!$N:$N,$AN5),0)) -IF($AF5="",0,IFERROR(SUMIFS(INDEX(rastreabilidade!$F:$H,0,MATCH(X$3,rastreabilidade!$F$1:$H$1,0)),rastreabilidade!$M:$M,$AF5,rastreabilidade!$N:$N,$AN5),0)) -> 0 | Y5: =IFERROR(SUMIFS(INDEX(rastreabilidade!$F:$H,0,MATCH(Y$3,rastreabilidade!$F$1:$H$1,0)),rastreabilidade!$N:$N,$AN5),0)*IF($AB5="sim",-1,1) +IF($AG5="",0,IFERROR(SUMIFS(INDEX(rastreabilidade!$F:$H,0,MATCH(Y$3,rastreabilidade!$F$1:$H$1,0)),rastreabilidade!$M:$M,$AG5),0)) +IF($AH5="",0,IFERROR(SUMIFS(INDEX(rastreabilidade!$F:$H,0,MATCH(Y$3,rastreabilidade!$F$1:$H$1,0)),rastreabilidade!$M:$M,$AH5),0)) +IF($AI5="",0,IFERROR(SUMIFS(INDEX(rastreabilidade!$F:$H,0,MATCH(Y$3,rastreabilidade!$F$1:$H$1,0)),rastreabilidade!$M:$M,$AI5),0)) +IF($AJ5="",0,IFERROR(SUMIFS(INDEX(rastreabilidade!$F:$H,0,MATCH(Y$3,rastreabilidade!$F$1:$H$1,0)),rastreabilidade!$M:$M,$AJ5),0)) -IF($AC5="",0,IFERROR(SUMIFS(INDEX(rastreabilidade!$F:$H,0,MATCH(Y$3,rastreabilidade!$F$1:$H$1,0)),rastreabilidade!$M:$M,$AC5,rastreabilidade!$N:$N,$AN5),0)) -IF($AD5="",0,IFERROR(SUMIFS(INDEX(rastreabilidade!$F:$H,0,MATCH(Y$3,rastreabilidade!$F$1:$H$1,0)),rastreabilidade!$M:$M,$AD5,rastreabilidade!$N:$N,$AN5),0)) -IF($AE5="",0,IFERROR(SUMIFS(INDEX(rastreabilidade!$F:$H,0,MATCH(Y$3,rastreabilidade!$F$1:$H$1,0)),rastreabilidade!$M:$M,$AE5,rastreabilidade!$N:$N,$AN5),0)) -IF($AF5="",0,IFERROR(SUMIFS(INDEX(rastreabilidade!$F:$H,0,MATCH(Y$3,rastreabilidade!$F$1:$H$1,0)),rastreabilidade!$M:$M,$AF5,rastreabilidade!$N:$N,$AN5),0)) -> 0 | AA5: {=_xlfn.LET( _xlpm.mem,Z5, _xlpm.retiradas,AC5:AF5, _xlpm.adicoes,AG5:AJ5, _xlpm.memAjustada,_xlfn.REDUCE(_xlpm.mem,_xlpm.retiradas,_xlfn.LAMBDA(_xlpm.x,_xlpm.y,IF(_xlpm.y<>"",SUBSTITUTE(_xlpm.x," + ("&_xlpm.y&")",""),_xlpm.x))), _xlpm.memRemovida,_xlfn.REDUCE(_xlpm.memAjustada,_xlpm.retiradas,_xlfn.LAMBDA(_xlpm.x,_xlpm.y,IF(_xlpm.y<>"",SUBSTITUTE(_xlpm.x,"("&_xlpm.y&")",""),_xlpm.x))), _xlpm.memSemSinal,IF(OR(LEFT(_xlpm.memRemovida,3)=" + ",LEFT(_xlpm.memRemovida,3)=" - "),MID(_xlpm.memRemovida,4,LEN(_xlpm.memRemovida)),_xlpm.memRemovida), _xlpm.memFinal,IF(OR(RIGHT(_xlpm.memSemSinal,3)=" + ",RIGHT(_xlpm.memSemSinal,3)=" - "),LEFT(_xlpm.memSemSinal,LEN(_xlpm.memSemSinal)-3),_xlpm.memSemSinal), _xlpm.adicoesTxt,_xlfn.TEXTJOIN(" + ",TRUE,IF(_xlpm.adicoes<>"","("&_xlpm.adicoes&")","")), IF(_xlpm.memFinal="",_xlpm.adicoesTxt,IF(_xlpm.adicoesTxt="",_xlpm.memFinal,_xlpm.memFinal&" + "&_xlpm.adicoesTxt)) )} | AM5: =_xlfn.TEXTJOIN("|",TRUE,A5,"Ativo","Circulante") -> Caixa|Ativo|Circulante | AN5: =_xlfn.CONCAT(S5,"|","DRE","|","DRE",) -> Vendas Totais|DRE|DRE
A6: Aplicações Financeiras | B6: =IFERROR(SUMIFS(INDEX(rastreabilidade!$F:$H,0,MATCH($B$2,rastreabilidade!$F$1:$H$1,0)),rastreabilidade!$K:$K,$A6,rastreabilidade!$D:$D,"Sim"),0) -> 0 | E6: =IFERROR(SUMIFS(INDEX(rastreabilidade!$F:$H,0,MATCH(E$3,rastreabilidade!$F$1:$H$1,0)),rastreabilidade!$N:$N,$AM6),0) +IF($N6="",0,IFERROR(SUMIFS(INDEX(rastreabilidade!$F:$H,0,MATCH(E$3,rastreabilidade!$F$1:$H$1,0)),rastreabilidade!$M:$M,$N6),0)) +IF($O6="",0,IFERROR(SUMIFS(INDEX(rastreabilidade!$F:$H,0,MATCH(E$3,rastreabilidade!$F$1:$H$1,0)),rastreabilidade!$M:$M,$O6),0)) +IF($P6="",0,IFERROR(SUMIFS(INDEX(rastreabilidade!$F:$H,0,MATCH(E$3,rastreabilidade!$F$1:$H$1,0)),rastreabilidade!$M:$M,$P6),0)) +IF($Q6="",0,IFERROR(SUMIFS(INDEX(rastreabilidade!$F:$H,0,MATCH(E$3,rastreabilidade!$F$1:$H$1,0)),rastreabilidade!$M:$M,$Q6),0)) -IF($J6="",0,IFERROR(SUMIFS(INDEX(rastreabilidade!$F:$H,0,MATCH(E$3,rastreabilidade!$F$1:$H$1,0)),rastreabilidade!$M:$M,$J6,rastreabilidade!$N:$N,$AM6),0)) -IF($K6="",0,IFERROR(SUMIFS(INDEX(rastreabilidade!$F:$H,0,MATCH(E$3,rastreabilidade!$F$1:$H$1,0)),rastreabilidade!$M:$M,$K6,rastreabilidade!$N:$N,$AM6),0)) -IF($L6="",0,IFERROR(SUMIFS(INDEX(rastreabilidade!$F:$H,0,MATCH(E$3,rastreabilidade!$F$1:$H$1,0)),rastreabilidade!$M:$M,$L6,rastreabilidade!$N:$N,$AM6),0)) -IF($M6="",0,IFERROR(SUMIFS(INDEX(rastreabilidade!$F:$H,0,MATCH(E$3,rastreabilidade!$F$1:$H$1,0)),rastreabilidade!$M:$M,$M6,rastreabilidade!$N:$N,$AM6),0)) -> 0 | F6: =IFERROR(SUMIFS(INDEX(rastreabilidade!$F:$H,0,MATCH(F$3,rastreabilidade!$F$1:$H$1,0)),rastreabilidade!$N:$N,$AM6),0) +IF($N6="",0,IFERROR(SUMIFS(INDEX(rastreabilidade!$F:$H,0,MATCH(F$3,rastreabilidade!$F$1:$H$1,0)),rastreabilidade!$M:$M,$N6),0)) +IF($O6="",0,IFERROR(SUMIFS(INDEX(rastreabilidade!$F:$H,0,MATCH(F$3,rastreabilidade!$F$1:$H$1,0)),rastreabilidade!$M:$M,$O6),0)) +IF($P6="",0,IFERROR(SUMIFS(INDEX(rastreabilidade!$F:$H,0,MATCH(F$3,rastreabilidade!$F$1:$H$1,0)),rastreabilidade!$M:$M,$P6),0)) +IF($Q6="",0,IFERROR(SUMIFS(INDEX(rastreabilidade!$F:$H,0,MATCH(F$3,rastreabilidade!$F$1:$H$1,0)),rastreabilidade!$M:$M,$Q6),0)) -IF($J6="",0,IFERROR(SUMIFS(INDEX(rastreabilidade!$F:$H,0,MATCH(F$3,rastreabilidade!$F$1:$H$1,0)),rastreabilidade!$M:$M,$J6,rastreabilidade!$N:$N,$AM6),0)) -IF($K6="",0,IFERROR(SUMIFS(INDEX(rastreabilidade!$F:$H,0,MATCH(F$3,rastreabilidade!$F$1:$H$1,0)),rastreabilidade!$M:$M,$K6,rastreabilidade!$N:$N,$AM6),0)) -IF($L6="",0,IFERROR(SUMIFS(INDEX(rastreabilidade!$F:$H,0,MATCH(F$3,rastreabilidade!$F$1:$H$1,0)),rastreabilidade!$M:$M,$L6,rastreabilidade!$N:$N,$AM6),0)) -IF($M6="",0,IFERROR(SUMIFS(INDEX(rastreabilidade!$F:$H,0,MATCH(F$3,rastreabilidade!$F$1:$H$1,0)),rastreabilidade!$M:$M,$M6,rastreabilidade!$N:$N,$AM6),0)) -> 0 | G6: =IFERROR(SUMIFS(INDEX(rastreabilidade!$F:$H,0,MATCH(G$3,rastreabilidade!$F$1:$H$1,0)),rastreabilidade!$N:$N,$AM6),0) +IF($N6="",0,IFERROR(SUMIFS(INDEX(rastreabilidade!$F:$H,0,MATCH(G$3,rastreabilidade!$F$1:$H$1,0)),rastreabilidade!$M:$M,$N6),0)) +IF($O6="",0,IFERROR(SUMIFS(INDEX(rastreabilidade!$F:$H,0,MATCH(G$3,rastreabilidade!$F$1:$H$1,0)),rastreabilidade!$M:$M,$O6),0)) +IF($P6="",0,IFERROR(SUMIFS(INDEX(rastreabilidade!$F:$H,0,MATCH(G$3,rastreabilidade!$F$1:$H$1,0)),rastreabilidade!$M:$M,$P6),0)) +IF($Q6="",0,IFERROR(SUMIFS(INDEX(rastreabilidade!$F:$H,0,MATCH(G$3,rastreabilidade!$F$1:$H$1,0)),rastreabilidade!$M:$M,$Q6),0)) -IF($J6="",0,IFERROR(SUMIFS(INDEX(rastreabilidade!$F:$H,0,MATCH(G$3,rastreabilidade!$F$1:$H$1,0)),rastreabilidade!$M:$M,$J6,rastreabilidade!$N:$N,$AM6),0)) -IF($K6="",0,IFERROR(SUMIFS(INDEX(rastreabilidade!$F:$H,0,MATCH(G$3,rastreabilidade!$F$1:$H$1,0)),rastreabilidade!$M:$M,$K6,rastreabilidade!$N:$N,$AM6),0)) -IF($L6="",0,IFERROR(SUMIFS(INDEX(rastreabilidade!$F:$H,0,MATCH(G$3,rastreabilidade!$F$1:$H$1,0)),rastreabilidade!$M:$M,$L6,rastreabilidade!$N:$N,$AM6),0)) -IF($M6="",0,IFERROR(SUMIFS(INDEX(rastreabilidade!$F:$H,0,MATCH(G$3,rastreabilidade!$F$1:$H$1,0)),rastreabilidade!$M:$M,$M6,rastreabilidade!$N:$N,$AM6),0)) -> 0 | I6: {=_xlfn.LET( _xlpm.mem,H6, _xlpm.retiradas,J6:M6, _xlpm.adicoes,N6:Q6, _xlpm.memAjustada,_xlfn.REDUCE(_xlpm.mem,_xlpm.retiradas,_xlfn.LAMBDA(_xlpm.x,_xlpm.y,IF(_xlpm.y<>"",SUBSTITUTE(_xlpm.x," + ("&_xlpm.y&")",""),_xlpm.x))), _xlpm.memRemovida,_xlfn.REDUCE(_xlpm.memAjustada,_xlpm.retiradas,_xlfn.LAMBDA(_xlpm.x,_xlpm.y,IF(_xlpm.y<>"",SUBSTITUTE(_xlpm.x,"("&_xlpm.y&")",""),_xlpm.x))), _xlpm.memSemSinal,IF(OR(LEFT(_xlpm.memRemovida,3)=" + ",LEFT(_xlpm.memRemovida,3)=" - "),MID(_xlpm.memRemovida,4,LEN(_xlpm.memRemovida)),_xlpm.memRemovida), _xlpm.memFinal,IF(OR(RIGHT(_xlpm.memSemSinal,3)=" + ",RIGHT(_xlpm.memSemSinal,3)=" - "),LEFT(_xlpm.memSemSinal,LEN(_xlpm.memSemSinal)-3),_xlpm.memSemSinal), _xlpm.adicoesTxt,_xlfn.TEXTJOIN(" + ",TRUE,IF(_xlpm.adicoes<>"","("&_xlpm.adicoes&")","")), IF(_xlpm.memFinal="",_xlpm.adicoesTxt,IF(_xlpm.adicoesTxt="",_xlpm.memFinal,_xlpm.memFinal&" + "&_xlpm.adicoesTxt)) )} | S6: -Impostos | T6: =IFERROR(SUMIFS(INDEX(rastreabilidade!$F:$H,0,MATCH($T$2,rastreabilidade!$F$1:$H$1,0)),rastreabilidade!$K:$K,$S6,rastreabilidade!$D:$D,"Sim"),0) -> 0 | W6: =IFERROR(SUMIFS(INDEX(rastreabilidade!$F:$H,0,MATCH(W$3,rastreabilidade!$F$1:$H$1,0)),rastreabilidade!$N:$N,$AN6),0)*IF($AB6="sim",-1,1) +IF($AG6="",0,IFERROR(SUMIFS(INDEX(rastreabilidade!$F:$H,0,MATCH(W$3,rastreabilidade!$F$1:$H$1,0)),rastreabilidade!$M:$M,$AG6),0)) +IF($AH6="",0,IFERROR(SUMIFS(INDEX(rastreabilidade!$F:$H,0,MATCH(W$3,rastreabilidade!$F$1:$H$1,0)),rastreabilidade!$M:$M,$AH6),0)) +IF($AI6="",0,IFERROR(SUMIFS(INDEX(rastreabilidade!$F:$H,0,MATCH(W$3,rastreabilidade!$F$1:$H$1,0)),rastreabilidade!$M:$M,$AI6),0)) +IF($AJ6="",0,IFERROR(SUMIFS(INDEX(rastreabilidade!$F:$H,0,MATCH(W$3,rastreabilidade!$F$1:$H$1,0)),rastreabilidade!$M:$M,$AJ6),0)) -IF($AC6="",0,IFERROR(SUMIFS(INDEX(rastreabilidade!$F:$H,0,MATCH(W$3,rastreabilidade!$F$1:$H$1,0)),rastreabilidade!$M:$M,$AC6,rastreabilidade!$N:$N,$AN6),0)) -IF($AD6="",0,IFERROR(SUMIFS(INDEX(rastreabilidade!$F:$H,0,MATCH(W$3,rastreabilidade!$F$1:$H$1,0)),rastreabilidade!$M:$M,$AD6,rastreabilidade!$N:$N,$AN6),0)) -IF($AE6="",0,IFERROR(SUMIFS(INDEX(rastreabilidade!$F:$H,0,MATCH(W$3,rastreabilidade!$F$1:$H$1,0)),rastreabilidade!$M:$M,$AE6,rastreabilidade!$N:$N,$AN6),0)) -IF($AF6="",0,IFERROR(SUMIFS(INDEX(rastreabilidade!$F:$H,0,MATCH(W$3,rastreabilidade!$F$1:$H$1,0)),rastreabilidade!$M:$M,$AF6,rastreabilidade!$N:$N,$AN6),0)) -> 0 | X6: =IFERROR(SUMIFS(INDEX(rastreabilidade!$F:$H,0,MATCH(X$3,rastreabilidade!$F$1:$H$1,0)),rastreabilidade!$N:$N,$AN6),0)*IF($AB6="sim",-1,1) +IF($AG6="",0,IFERROR(SUMIFS(INDEX(rastreabilidade!$F:$H,0,MATCH(X$3,rastreabilidade!$F$1:$H$1,0)),rastreabilidade!$M:$M,$AG6),0)) +IF($AH6="",0,IFERROR(SUMIFS(INDEX(rastreabilidade!$F:$H,0,MATCH(X$3,rastreabilidade!$F$1:$H$1,0)),rastreabilidade!$M:$M,$AH6),0)) +IF($AI6="",0,IFERROR(SUMIFS(INDEX(rastreabilidade!$F:$H,0,MATCH(X$3,rastreabilidade!$F$1:$H$1,0)),rastreabilidade!$M:$M,$AI6),0)) +IF($AJ6="",0,IFERROR(SUMIFS(INDEX(rastreabilidade!$F:$H,0,MATCH(X$3,rastreabilidade!$F$1:$H$1,0)),rastreabilidade!$M:$M,$AJ6),0)) -IF($AC6="",0,IFERROR(SUMIFS(INDEX(rastreabilidade!$F:$H,0,MATCH(X$3,rastreabilidade!$F$1:$H$1,0)),rastreabilidade!$M:$M,$AC6,rastreabilidade!$N:$N,$AN6),0)) -IF($AD6="",0,IFERROR(SUMIFS(INDEX(rastreabilidade!$F:$H,0,MATCH(X$3,rastreabilidade!$F$1:$H$1,0)),rastreabilidade!$M:$M,$AD6,rastreabilidade!$N:$N,$AN6),0)) -IF($AE6="",0,IFERROR(SUMIFS(INDEX(rastreabilidade!$F:$H,0,MATCH(X$3,rastreabilidade!$F$1:$H$1,0)),rastreabilidade!$M:$M,$AE6,rastreabilidade!$N:$N,$AN6),0)) -IF($AF6="",0,IFERROR(SUMIFS(INDEX(rastreabilidade!$F:$H,0,MATCH(X$3,rastreabilidade!$F$1:$H$1,0)),rastreabilidade!$M:$M,$AF6,rastreabilidade!$N:$N,$AN6),0)) -> 0 | Y6: =IFERROR(SUMIFS(INDEX(rastreabilidade!$F:$H,0,MATCH(Y$3,rastreabilidade!$F$1:$H$1,0)),rastreabilidade!$N:$N,$AN6),0)*IF($AB6="sim",-1,1) +IF($AG6="",0,IFERROR(SUMIFS(INDEX(rastreabilidade!$F:$H,0,MATCH(Y$3,rastreabilidade!$F$1:$H$1,0)),rastreabilidade!$M:$M,$AG6),0)) +IF($AH6="",0,IFERROR(SUMIFS(INDEX(rastreabilidade!$F:$H,0,MATCH(Y$3,rastreabilidade!$F$1:$H$1,0)),rastreabilidade!$M:$M,$AH6),0)) +IF($AI6="",0,IFERROR(SUMIFS(INDEX(rastreabilidade!$F:$H,0,MATCH(Y$3,rastreabilidade!$F$1:$H$1,0)),rastreabilidade!$M:$M,$AI6),0)) +IF($AJ6="",0,IFERROR(SUMIFS(INDEX(rastreabilidade!$F:$H,0,MATCH(Y$3,rastreabilidade!$F$1:$H$1,0)),rastreabilidade!$M:$M,$AJ6),0)) -IF($AC6="",0,IFERROR(SUMIFS(INDEX(rastreabilidade!$F:$H,0,MATCH(Y$3,rastreabilidade!$F$1:$H$1,0)),rastreabilidade!$M:$M,$AC6,rastreabilidade!$N:$N,$AN6),0)) -IF($AD6="",0,IFERROR(SUMIFS(INDEX(rastreabilidade!$F:$H,0,MATCH(Y$3,rastreabilidade!$F$1:$H$1,0)),rastreabilidade!$M:$M,$AD6,rastreabilidade!$N:$N,$AN6),0)) -IF($AE6="",0,IFERROR(SUMIFS(INDEX(rastreabilidade!$F:$H,0,MATCH(Y$3,rastreabilidade!$F$1:$H$1,0)),rastreabilidade!$M:$M,$AE6,rastreabilidade!$N:$N,$AN6),0)) -IF($AF6="",0,IFERROR(SUMIFS(INDEX(rastreabilidade!$F:$H,0,MATCH(Y$3,rastreabilidade!$F$1:$H$1,0)),rastreabilidade!$M:$M,$AF6,rastreabilidade!$N:$N,$AN6),0)) -> 0 | AA6: {=_xlfn.LET( _xlpm.mem,Z6, _xlpm.retiradas,AC6:AF6, _xlpm.adicoes,AG6:AJ6, _xlpm.memAjustada,_xlfn.REDUCE(_xlpm.mem,_xlpm.retiradas,_xlfn.LAMBDA(_xlpm.x,_xlpm.y,IF(_xlpm.y<>"",SUBSTITUTE(_xlpm.x," + ("&_xlpm.y&")",""),_xlpm.x))), _xlpm.memRemovida,_xlfn.REDUCE(_xlpm.memAjustada,_xlpm.retiradas,_xlfn.LAMBDA(_xlpm.x,_xlpm.y,IF(_xlpm.y<>"",SUBSTITUTE(_xlpm.x,"("&_xlpm.y&")",""),_xlpm.x))), _xlpm.memSemSinal,IF(OR(LEFT(_xlpm.memRemovida,3)=" + ",LEFT(_xlpm.memRemovida,3)=" - "),MID(_xlpm.memRemovida,4,LEN(_xlpm.memRemovida)),_xlpm.memRemovida), _xlpm.memFinal,IF(OR(RIGHT(_xlpm.memSemSinal,3)=" + ",RIGHT(_xlpm.memSemSinal,3)=" - "),LEFT(_xlpm.memSemSinal,LEN(_xlpm.memSemSinal)-3),_xlpm.memSemSinal), _xlpm.adicoesTxt,_xlfn.TEXTJOIN(" + ",TRUE,IF(_xlpm.adicoes<>"","("&_xlpm.adicoes&")","")), IF(_xlpm.memFinal="",_xlpm.adicoesTxt,IF(_xlpm.adicoesTxt="",_xlpm.memFinal,_xlpm.memFinal&" + "&_xlpm.adicoesTxt)) )} | AM6: =_xlfn.TEXTJOIN("|",TRUE,A6,"Ativo","Circulante") -> Aplicações Financeiras|Ativo|Circulante | AN6: =_xlfn.CONCAT(S6,"|","DRE","|","DRE",) -> -Impostos|DRE|DRE
A7: Disponibilidades | B7: =+B6+B5 -> 0 | E7: =+E6+E5 -> 0 | F7: =+F6+F5 -> 0 | G7: =+G6+G5 -> 0 | S7: Vendas Líquidas | T7: =+T5-T6 -> 0 | W7: =+W5-W6 -> 0 | X7: =+X5-X6 -> 0 | Y7: =+Y5-Y6 -> 0 | AM7: =_xlfn.TEXTJOIN("|",TRUE,A7,"Ativo","Circulante") -> Disponibilidades|Ativo|Circulante | AN7: =_xlfn.CONCAT(S7,"|","DRE","|","DRE",) -> Vendas Líquidas|DRE|DRE
A8: Clientes | B8: =IFERROR(SUMIFS(INDEX(rastreabilidade!$F:$H,0,MATCH($B$2,rastreabilidade!$F$1:$H$1,0)),rastreabilidade!$K:$K,$A8,rastreabilidade!$D:$D,"Sim"),0) -> 0 | E8: =IFERROR(SUMIFS(INDEX(rastreabilidade!$F:$H,0,MATCH(E$3,rastreabilidade!$F$1:$H$1,0)),rastreabilidade!$N:$N,$AM8),0) +IF($N8="",0,IFERROR(SUMIFS(INDEX(rastreabilidade!$F:$H,0,MATCH(E$3,rastreabilidade!$F$1:$H$1,0)),rastreabilidade!$M:$M,$N8),0)) +IF($O8="",0,IFERROR(SUMIFS(INDEX(rastreabilidade!$F:$H,0,MATCH(E$3,rastreabilidade!$F$1:$H$1,0)),rastreabilidade!$M:$M,$O8),0)) +IF($P8="",0,IFERROR(SUMIFS(INDEX(rastreabilidade!$F:$H,0,MATCH(E$3,rastreabilidade!$F$1:$H$1,0)),rastreabilidade!$M:$M,$P8),0)) +IF($Q8="",0,IFERROR(SUMIFS(INDEX(rastreabilidade!$F:$H,0,MATCH(E$3,rastreabilidade!$F$1:$H$1,0)),rastreabilidade!$M:$M,$Q8),0)) -IF($J8="",0,IFERROR(SUMIFS(INDEX(rastreabilidade!$F:$H,0,MATCH(E$3,rastreabilidade!$F$1:$H$1,0)),rastreabilidade!$M:$M,$J8,rastreabilidade!$N:$N,$AM8),0)) -IF($K8="",0,IFERROR(SUMIFS(INDEX(rastreabilidade!$F:$H,0,MATCH(E$3,rastreabilidade!$F$1:$H$1,0)),rastreabilidade!$M:$M,$K8,rastreabilidade!$N:$N,$AM8),0)) -IF($L8="",0,IFERROR(SUMIFS(INDEX(rastreabilidade!$F:$H,0,MATCH(E$3,rastreabilidade!$F$1:$H$1,0)),rastreabilidade!$M:$M,$L8,rastreabilidade!$N:$N,$AM8),0)) -IF($M8="",0,IFERROR(SUMIFS(INDEX(rastreabilidade!$F:$H,0,MATCH(E$3,rastreabilidade!$F$1:$H$1,0)),rastreabilidade!$M:$M,$M8,rastreabilidade!$N:$N,$AM8),0)) -> 0 | F8: =IFERROR(SUMIFS(INDEX(rastreabilidade!$F:$H,0,MATCH(F$3,rastreabilidade!$F$1:$H$1,0)),rastreabilidade!$N:$N,$AM8),0) +IF($N8="",0,IFERROR(SUMIFS(INDEX(rastreabilidade!$F:$H,0,MATCH(F$3,rastreabilidade!$F$1:$H$1,0)),rastreabilidade!$M:$M,$N8),0)) +IF($O8="",0,IFERROR(SUMIFS(INDEX(rastreabilidade!$F:$H,0,MATCH(F$3,rastreabilidade!$F$1:$H$1,0)),rastreabilidade!$M:$M,$O8),0)) +IF($P8="",0,IFERROR(SUMIFS(INDEX(rastreabilidade!$F:$H,0,MATCH(F$3,rastreabilidade!$F$1:$H$1,0)),rastreabilidade!$M:$M,$P8),0)) +IF($Q8="",0,IFERROR(SUMIFS(INDEX(rastreabilidade!$F:$H,0,MATCH(F$3,rastreabilidade!$F$1:$H$1,0)),rastreabilidade!$M:$M,$Q8),0)) -IF($J8="",0,IFERROR(SUMIFS(INDEX(rastreabilidade!$F:$H,0,MATCH(F$3,rastreabilidade!$F$1:$H$1,0)),rastreabilidade!$M:$M,$J8,rastreabilidade!$N:$N,$AM8),0)) -IF($K8="",0,IFERROR(SUMIFS(INDEX(rastreabilidade!$F:$H,0,MATCH(F$3,rastreabilidade!$F$1:$H$1,0)),rastreabilidade!$M:$M,$K8,rastreabilidade!$N:$N,$AM8),0)) -IF($L8="",0,IFERROR(SUMIFS(INDEX(rastreabilidade!$F:$H,0,MATCH(F$3,rastreabilidade!$F$1:$H$1,0)),rastreabilidade!$M:$M,$L8,rastreabilidade!$N:$N,$AM8),0)) -IF($M8="",0,IFERROR(SUMIFS(INDEX(rastreabilidade!$F:$H,0,MATCH(F$3,rastreabilidade!$F$1:$H$1,0)),rastreabilidade!$M:$M,$M8,rastreabilidade!$N:$N,$AM8),0)) -> 0 | G8: =IFERROR(SUMIFS(INDEX(rastreabilidade!$F:$H,0,MATCH(G$3,rastreabilidade!$F$1:$H$1,0)),rastreabilidade!$N:$N,$AM8),0) +IF($N8="",0,IFERROR(SUMIFS(INDEX(rastreabilidade!$F:$H,0,MATCH(G$3,rastreabilidade!$F$1:$H$1,0)),rastreabilidade!$M:$M,$N8),0)) +IF($O8="",0,IFERROR(SUMIFS(INDEX(rastreabilidade!$F:$H,0,MATCH(G$3,rastreabilidade!$F$1:$H$1,0)),rastreabilidade!$M:$M,$O8),0)) +IF($P8="",0,IFERROR(SUMIFS(INDEX(rastreabilidade!$F:$H,0,MATCH(G$3,rastreabilidade!$F$1:$H$1,0)),rastreabilidade!$M:$M,$P8),0)) +IF($Q8="",0,IFERROR(SUMIFS(INDEX(rastreabilidade!$F:$H,0,MATCH(G$3,rastreabilidade!$F$1:$H$1,0)),rastreabilidade!$M:$M,$Q8),0)) -IF($J8="",0,IFERROR(SUMIFS(INDEX(rastreabilidade!$F:$H,0,MATCH(G$3,rastreabilidade!$F$1:$H$1,0)),rastreabilidade!$M:$M,$J8,rastreabilidade!$N:$N,$AM8),0)) -IF($K8="",0,IFERROR(SUMIFS(INDEX(rastreabilidade!$F:$H,0,MATCH(G$3,rastreabilidade!$F$1:$H$1,0)),rastreabilidade!$M:$M,$K8,rastreabilidade!$N:$N,$AM8),0)) -IF($L8="",0,IFERROR(SUMIFS(INDEX(rastreabilidade!$F:$H,0,MATCH(G$3,rastreabilidade!$F$1:$H$1,0)),rastreabilidade!$M:$M,$L8,rastreabilidade!$N:$N,$AM8),0)) -IF($M8="",0,IFERROR(SUMIFS(INDEX(rastreabilidade!$F:$H,0,MATCH(G$3,rastreabilidade!$F$1:$H$1,0)),rastreabilidade!$M:$M,$M8,rastreabilidade!$N:$N,$AM8),0)) -> 0 | I8: {=_xlfn.LET( _xlpm.mem,H8, _xlpm.retiradas,J8:M8, _xlpm.adicoes,N8:Q8, _xlpm.memAjustada,_xlfn.REDUCE(_xlpm.mem,_xlpm.retiradas,_xlfn.LAMBDA(_xlpm.x,_xlpm.y,IF(_xlpm.y<>"",SUBSTITUTE(_xlpm.x," + ("&_xlpm.y&")",""),_xlpm.x))), _xlpm.memRemovida,_xlfn.REDUCE(_xlpm.memAjustada,_xlpm.retiradas,_xlfn.LAMBDA(_xlpm.x,_xlpm.y,IF(_xlpm.y<>"",SUBSTITUTE(_xlpm.x,"("&_xlpm.y&")",""),_xlpm.x))), _xlpm.memSemSinal,IF(OR(LEFT(_xlpm.memRemovida,3)=" + ",LEFT(_xlpm.memRemovida,3)=" - "),MID(_xlpm.memRemovida,4,LEN(_xlpm.memRemovida)),_xlpm.memRemovida), _xlpm.memFinal,IF(OR(RIGHT(_xlpm.memSemSinal,3)=" + ",RIGHT(_xlpm.memSemSinal,3)=" - "),LEFT(_xlpm.memSemSinal,LEN(_xlpm.memSemSinal)-3),_xlpm.memSemSinal), _xlpm.adicoesTxt,_xlfn.TEXTJOIN(" + ",TRUE,IF(_xlpm.adicoes<>"","("&_xlpm.adicoes&")","")), IF(_xlpm.memFinal="",_xlpm.adicoesTxt,IF(_xlpm.adicoesTxt="",_xlpm.memFinal,_xlpm.memFinal&" + "&_xlpm.adicoesTxt)) )} | S8: -Custo de Produtos Vendidos | T8: =IFERROR(SUMIFS(INDEX(rastreabilidade!$F:$H,0,MATCH($T$2,rastreabilidade!$F$1:$H$1,0)),rastreabilidade!$K:$K,$S8,rastreabilidade!$D:$D,"Sim"),0) -> 0 | W8: =IFERROR(SUMIFS(INDEX(rastreabilidade!$F:$H,0,MATCH(W$3,rastreabilidade!$F$1:$H$1,0)),rastreabilidade!$N:$N,$AN8),0)*IF($AB8="sim",-1,1) +IF($AG8="",0,IFERROR(SUMIFS(INDEX(rastreabilidade!$F:$H,0,MATCH(W$3,rastreabilidade!$F$1:$H$1,0)),rastreabilidade!$M:$M,$AG8),0)) +IF($AH8="",0,IFERROR(SUMIFS(INDEX(rastreabilidade!$F:$H,0,MATCH(W$3,rastreabilidade!$F$1:$H$1,0)),rastreabilidade!$M:$M,$AH8),0)) +IF($AI8="",0,IFERROR(SUMIFS(INDEX(rastreabilidade!$F:$H,0,MATCH(W$3,rastreabilidade!$F$1:$H$1,0)),rastreabilidade!$M:$M,$AI8),0)) +IF($AJ8="",0,IFERROR(SUMIFS(INDEX(rastreabilidade!$F:$H,0,MATCH(W$3,rastreabilidade!$F$1:$H$1,0)),rastreabilidade!$M:$M,$AJ8),0)) -IF($AC8="",0,IFERROR(SUMIFS(INDEX(rastreabilidade!$F:$H,0,MATCH(W$3,rastreabilidade!$F$1:$H$1,0)),rastreabilidade!$M:$M,$AC8,rastreabilidade!$N:$N,$AN8),0)) -IF($AD8="",0,IFERROR(SUMIFS(INDEX(rastreabilidade!$F:$H,0,MATCH(W$3,rastreabilidade!$F$1:$H$1,0)),rastreabilidade!$M:$M,$AD8,rastreabilidade!$N:$N,$AN8),0)) -IF($AE8="",0,IFERROR(SUMIFS(INDEX(rastreabilidade!$F:$H,0,MATCH(W$3,rastreabilidade!$F$1:$H$1,0)),rastreabilidade!$M:$M,$AE8,rastreabilidade!$N:$N,$AN8),0)) -IF($AF8="",0,IFERROR(SUMIFS(INDEX(rastreabilidade!$F:$H,0,MATCH(W$3,rastreabilidade!$F$1:$H$1,0)),rastreabilidade!$M:$M,$AF8,rastreabilidade!$N:$N,$AN8),0)) -> 0 | X8: =IFERROR(SUMIFS(INDEX(rastreabilidade!$F:$H,0,MATCH(X$3,rastreabilidade!$F$1:$H$1,0)),rastreabilidade!$N:$N,$AN8),0)*IF($AB8="sim",-1,1) +IF($AG8="",0,IFERROR(SUMIFS(INDEX(rastreabilidade!$F:$H,0,MATCH(X$3,rastreabilidade!$F$1:$H$1,0)),rastreabilidade!$M:$M,$AG8),0)) +IF($AH8="",0,IFERROR(SUMIFS(INDEX(rastreabilidade!$F:$H,0,MATCH(X$3,rastreabilidade!$F$1:$H$1,0)),rastreabilidade!$M:$M,$AH8),0)) +IF($AI8="",0,IFERROR(SUMIFS(INDEX(rastreabilidade!$F:$H,0,MATCH(X$3,rastreabilidade!$F$1:$H$1,0)),rastreabilidade!$M:$M,$AI8),0)) +IF($AJ8="",0,IFERROR(SUMIFS(INDEX(rastreabilidade!$F:$H,0,MATCH(X$3,rastreabilidade!$F$1:$H$1,0)),rastreabilidade!$M:$M,$AJ8),0)) -IF($AC8="",0,IFERROR(SUMIFS(INDEX(rastreabilidade!$F:$H,0,MATCH(X$3,rastreabilidade!$F$1:$H$1,0)),rastreabilidade!$M:$M,$AC8,rastreabilidade!$N:$N,$AN8),0)) -IF($AD8="",0,IFERROR(SUMIFS(INDEX(rastreabilidade!$F:$H,0,MATCH(X$3,rastreabilidade!$F$1:$H$1,0)),rastreabilidade!$M:$M,$AD8,rastreabilidade!$N:$N,$AN8),0)) -IF($AE8="",0,IFERROR(SUMIFS(INDEX(rastreabilidade!$F:$H,0,MATCH(X$3,rastreabilidade!$F$1:$H$1,0)),rastreabilidade!$M:$M,$AE8,rastreabilidade!$N:$N,$AN8),0)) -IF($AF8="",0,IFERROR(SUMIFS(INDEX(rastreabilidade!$F:$H,0,MATCH(X$3,rastreabilidade!$F$1:$H$1,0)),rastreabilidade!$M:$M,$AF8,rastreabilidade!$N:$N,$AN8),0)) -> 0 | Y8: =IFERROR(SUMIFS(INDEX(rastreabilidade!$F:$H,0,MATCH(Y$3,rastreabilidade!$F$1:$H$1,0)),rastreabilidade!$N:$N,$AN8),0)*IF($AB8="sim",-1,1) +IF($AG8="",0,IFERROR(SUMIFS(INDEX(rastreabilidade!$F:$H,0,MATCH(Y$3,rastreabilidade!$F$1:$H$1,0)),rastreabilidade!$M:$M,$AG8),0)) +IF($AH8="",0,IFERROR(SUMIFS(INDEX(rastreabilidade!$F:$H,0,MATCH(Y$3,rastreabilidade!$F$1:$H$1,0)),rastreabilidade!$M:$M,$AH8),0)) +IF($AI8="",0,IFERROR(SUMIFS(INDEX(rastreabilidade!$F:$H,0,MATCH(Y$3,rastreabilidade!$F$1:$H$1,0)),rastreabilidade!$M:$M,$AI8),0)) +IF($AJ8="",0,IFERROR(SUMIFS(INDEX(rastreabilidade!$F:$H,0,MATCH(Y$3,rastreabilidade!$F$1:$H$1,0)),rastreabilidade!$M:$M,$AJ8),0)) -IF($AC8="",0,IFERROR(SUMIFS(INDEX(rastreabilidade!$F:$H,0,MATCH(Y$3,rastreabilidade!$F$1:$H$1,0)),rastreabilidade!$M:$M,$AC8,rastreabilidade!$N:$N,$AN8),0)) -IF($AD8="",0,IFERROR(SUMIFS(INDEX(rastreabilidade!$F:$H,0,MATCH(Y$3,rastreabilidade!$F$1:$H$1,0)),rastreabilidade!$M:$M,$AD8,rastreabilidade!$N:$N,$AN8),0)) -IF($AE8="",0,IFERROR(SUMIFS(INDEX(rastreabilidade!$F:$H,0,MATCH(Y$3,rastreabilidade!$F$1:$H$1,0)),rastreabilidade!$M:$M,$AE8,rastreabilidade!$N:$N,$AN8),0)) -IF($AF8="",0,IFERROR(SUMIFS(INDEX(rastreabilidade!$F:$H,0,MATCH(Y$3,rastreabilidade!$F$1:$H$1,0)),rastreabilidade!$M:$M,$AF8,rastreabilidade!$N:$N,$AN8),0)) -> 0 | AA8: {=_xlfn.LET( _xlpm.mem,Z8, _xlpm.retiradas,AC8:AF8, _xlpm.adicoes,AG8:AJ8, _xlpm.memAjustada,_xlfn.REDUCE(_xlpm.mem,_xlpm.retiradas,_xlfn.LAMBDA(_xlpm.x,_xlpm.y,IF(_xlpm.y<>"",SUBSTITUTE(_xlpm.x," + ("&_xlpm.y&")",""),_xlpm.x))), _xlpm.memRemovida,_xlfn.REDUCE(_xlpm.memAjustada,_xlpm.retiradas,_xlfn.LAMBDA(_xlpm.x,_xlpm.y,IF(_xlpm.y<>"",SUBSTITUTE(_xlpm.x,"("&_xlpm.y&")",""),_xlpm.x))), _xlpm.memSemSinal,IF(OR(LEFT(_xlpm.memRemovida,3)=" + ",LEFT(_xlpm.memRemovida,3)=" - "),MID(_xlpm.memRemovida,4,LEN(_xlpm.memRemovida)),_xlpm.memRemovida), _xlpm.memFinal,IF(OR(RIGHT(_xlpm.memSemSinal,3)=" + ",RIGHT(_xlpm.memSemSinal,3)=" - "),LEFT(_xlpm.memSemSinal,LEN(_xlpm.memSemSinal)-3),_xlpm.memSemSinal), _xlpm.adicoesTxt,_xlfn.TEXTJOIN(" + ",TRUE,IF(_xlpm.adicoes<>"","("&_xlpm.adicoes&")","")), IF(_xlpm.memFinal="",_xlpm.adicoesTxt,IF(_xlpm.adicoesTxt="",_xlpm.memFinal,_xlpm.memFinal&" + "&_xlpm.adicoesTxt)) )} | AM8: =_xlfn.TEXTJOIN("|",TRUE,A8,"Ativo","Circulante") -> Clientes|Ativo|Circulante | AN8: =_xlfn.CONCAT(S8,"|","DRE","|","DRE",) -> -Custo de Produtos Vendidos|DRE|DRE
A9: Clientes - Grupo | B9: =IFERROR(SUMIFS(INDEX(rastreabilidade!$F:$H,0,MATCH($B$2,rastreabilidade!$F$1:$H$1,0)),rastreabilidade!$K:$K,$A9,rastreabilidade!$D:$D,"Sim"),0) -> 0 | E9: =IFERROR(SUMIFS(INDEX(rastreabilidade!$F:$H,0,MATCH(E$3,rastreabilidade!$F$1:$H$1,0)),rastreabilidade!$N:$N,$AM9),0) +IF($N9="",0,IFERROR(SUMIFS(INDEX(rastreabilidade!$F:$H,0,MATCH(E$3,rastreabilidade!$F$1:$H$1,0)),rastreabilidade!$M:$M,$N9),0)) +IF($O9="",0,IFERROR(SUMIFS(INDEX(rastreabilidade!$F:$H,0,MATCH(E$3,rastreabilidade!$F$1:$H$1,0)),rastreabilidade!$M:$M,$O9),0)) +IF($P9="",0,IFERROR(SUMIFS(INDEX(rastreabilidade!$F:$H,0,MATCH(E$3,rastreabilidade!$F$1:$H$1,0)),rastreabilidade!$M:$M,$P9),0)) +IF($Q9="",0,IFERROR(SUMIFS(INDEX(rastreabilidade!$F:$H,0,MATCH(E$3,rastreabilidade!$F$1:$H$1,0)),rastreabilidade!$M:$M,$Q9),0)) -IF($J9="",0,IFERROR(SUMIFS(INDEX(rastreabilidade!$F:$H,0,MATCH(E$3,rastreabilidade!$F$1:$H$1,0)),rastreabilidade!$M:$M,$J9,rastreabilidade!$N:$N,$AM9),0)) -IF($K9="",0,IFERROR(SUMIFS(INDEX(rastreabilidade!$F:$H,0,MATCH(E$3,rastreabilidade!$F$1:$H$1,0)),rastreabilidade!$M:$M,$K9,rastreabilidade!$N:$N,$AM9),0)) -IF($L9="",0,IFERROR(SUMIFS(INDEX(rastreabilidade!$F:$H,0,MATCH(E$3,rastreabilidade!$F$1:$H$1,0)),rastreabilidade!$M:$M,$L9,rastreabilidade!$N:$N,$AM9),0)) -IF($M9="",0,IFERROR(SUMIFS(INDEX(rastreabilidade!$F:$H,0,MATCH(E$3,rastreabilidade!$F$1:$H$1,0)),rastreabilidade!$M:$M,$M9,rastreabilidade!$N:$N,$AM9),0)) -> 0 | F9: =IFERROR(SUMIFS(INDEX(rastreabilidade!$F:$H,0,MATCH(F$3,rastreabilidade!$F$1:$H$1,0)),rastreabilidade!$N:$N,$AM9),0) +IF($N9="",0,IFERROR(SUMIFS(INDEX(rastreabilidade!$F:$H,0,MATCH(F$3,rastreabilidade!$F$1:$H$1,0)),rastreabilidade!$M:$M,$N9),0)) +IF($O9="",0,IFERROR(SUMIFS(INDEX(rastreabilidade!$F:$H,0,MATCH(F$3,rastreabilidade!$F$1:$H$1,0)),rastreabilidade!$M:$M,$O9),0)) +IF($P9="",0,IFERROR(SUMIFS(INDEX(rastreabilidade!$F:$H,0,MATCH(F$3,rastreabilidade!$F$1:$H$1,0)),rastreabilidade!$M:$M,$P9),0)) +IF($Q9="",0,IFERROR(SUMIFS(INDEX(rastreabilidade!$F:$H,0,MATCH(F$3,rastreabilidade!$F$1:$H$1,0)),rastreabilidade!$M:$M,$Q9),0)) -IF($J9="",0,IFERROR(SUMIFS(INDEX(rastreabilidade!$F:$H,0,MATCH(F$3,rastreabilidade!$F$1:$H$1,0)),rastreabilidade!$M:$M,$J9,rastreabilidade!$N:$N,$AM9),0)) -IF($K9="",0,IFERROR(SUMIFS(INDEX(rastreabilidade!$F:$H,0,MATCH(F$3,rastreabilidade!$F$1:$H$1,0)),rastreabilidade!$M:$M,$K9,rastreabilidade!$N:$N,$AM9),0)) -IF($L9="",0,IFERROR(SUMIFS(INDEX(rastreabilidade!$F:$H,0,MATCH(F$3,rastreabilidade!$F$1:$H$1,0)),rastreabilidade!$M:$M,$L9,rastreabilidade!$N:$N,$AM9),0)) -IF($M9="",0,IFERROR(SUMIFS(INDEX(rastreabilidade!$F:$H,0,MATCH(F$3,rastreabilidade!$F$1:$H$1,0)),rastreabilidade!$M:$M,$M9,rastreabilidade!$N:$N,$AM9),0)) -> 0 | G9: =IFERROR(SUMIFS(INDEX(rastreabilidade!$F:$H,0,MATCH(G$3,rastreabilidade!$F$1:$H$1,0)),rastreabilidade!$N:$N,$AM9),0) +IF($N9="",0,IFERROR(SUMIFS(INDEX(rastreabilidade!$F:$H,0,MATCH(G$3,rastreabilidade!$F$1:$H$1,0)),rastreabilidade!$M:$M,$N9),0)) +IF($O9="",0,IFERROR(SUMIFS(INDEX(rastreabilidade!$F:$H,0,MATCH(G$3,rastreabilidade!$F$1:$H$1,0)),rastreabilidade!$M:$M,$O9),0)) +IF($P9="",0,IFERROR(SUMIFS(INDEX(rastreabilidade!$F:$H,0,MATCH(G$3,rastreabilidade!$F$1:$H$1,0)),rastreabilidade!$M:$M,$P9),0)) +IF($Q9="",0,IFERROR(SUMIFS(INDEX(rastreabilidade!$F:$H,0,MATCH(G$3,rastreabilidade!$F$1:$H$1,0)),rastreabilidade!$M:$M,$Q9),0)) -IF($J9="",0,IFERROR(SUMIFS(INDEX(rastreabilidade!$F:$H,0,MATCH(G$3,rastreabilidade!$F$1:$H$1,0)),rastreabilidade!$M:$M,$J9,rastreabilidade!$N:$N,$AM9),0)) -IF($K9="",0,IFERROR(SUMIFS(INDEX(rastreabilidade!$F:$H,0,MATCH(G$3,rastreabilidade!$F$1:$H$1,0)),rastreabilidade!$M:$M,$K9,rastreabilidade!$N:$N,$AM9),0)) -IF($L9="",0,IFERROR(SUMIFS(INDEX(rastreabilidade!$F:$H,0,MATCH(G$3,rastreabilidade!$F$1:$H$1,0)),rastreabilidade!$M:$M,$L9,rastreabilidade!$N:$N,$AM9),0)) -IF($M9="",0,IFERROR(SUMIFS(INDEX(rastreabilidade!$F:$H,0,MATCH(G$3,rastreabilidade!$F$1:$H$1,0)),rastreabilidade!$M:$M,$M9,rastreabilidade!$N:$N,$AM9),0)) -> 0 | I9: {=_xlfn.LET( _xlpm.mem,H9, _xlpm.retiradas,J9:M9, _xlpm.adicoes,N9:Q9, _xlpm.memAjustada,_xlfn.REDUCE(_xlpm.mem,_xlpm.retiradas,_xlfn.LAMBDA(_xlpm.x,_xlpm.y,IF(_xlpm.y<>"",SUBSTITUTE(_xlpm.x," + ("&_xlpm.y&")",""),_xlpm.x))), _xlpm.memRemovida,_xlfn.REDUCE(_xlpm.memAjustada,_xlpm.retiradas,_xlfn.LAMBDA(_xlpm.x,_xlpm.y,IF(_xlpm.y<>"",SUBSTITUTE(_xlpm.x,"("&_xlpm.y&")",""),_xlpm.x))), _xlpm.memSemSinal,IF(OR(LEFT(_xlpm.memRemovida,3)=" + ",LEFT(_xlpm.memRemovida,3)=" - "),MID(_xlpm.memRemovida,4,LEN(_xlpm.memRemovida)),_xlpm.memRemovida), _xlpm.memFinal,IF(OR(RIGHT(_xlpm.memSemSinal,3)=" + ",RIGHT(_xlpm.memSemSinal,3)=" - "),LEFT(_xlpm.memSemSinal,LEN(_xlpm.memSemSinal)-3),_xlpm.memSemSinal), _xlpm.adicoesTxt,_xlfn.TEXTJOIN(" + ",TRUE,IF(_xlpm.adicoes<>"","("&_xlpm.adicoes&")","")), IF(_xlpm.memFinal="",_xlpm.adicoesTxt,IF(_xlpm.adicoesTxt="",_xlpm.memFinal,_xlpm.memFinal&" + "&_xlpm.adicoesTxt)) )} | S9: Resultado Bruto | T9: =+T7-T8 -> 0 | W9: =+W7-W8 -> 0 | X9: =+X7-X8 -> 0 | Y9: =+Y7-Y8 -> 0 | AM9: =_xlfn.TEXTJOIN("|",TRUE,A9,"Ativo","Circulante") -> Clientes - Grupo|Ativo|Circulante | AN9: =_xlfn.CONCAT(S9,"|","DRE","|","DRE",) -> Resultado Bruto|DRE|DRE
A10: -PDD | B10: =IFERROR(SUMIFS(INDEX(rastreabilidade!$F:$H,0,MATCH($B$2,rastreabilidade!$F$1:$H$1,0)),rastreabilidade!$K:$K,$A10,rastreabilidade!$D:$D,"Sim"),0) -> 0 | E10: =IFERROR(SUMIFS(INDEX(rastreabilidade!$F:$H,0,MATCH(E$3,rastreabilidade!$F$1:$H$1,0)),rastreabilidade!$N:$N,$AM10),0) +IF($N10="",0,IFERROR(SUMIFS(INDEX(rastreabilidade!$F:$H,0,MATCH(E$3,rastreabilidade!$F$1:$H$1,0)),rastreabilidade!$M:$M,$N10),0)) +IF($O10="",0,IFERROR(SUMIFS(INDEX(rastreabilidade!$F:$H,0,MATCH(E$3,rastreabilidade!$F$1:$H$1,0)),rastreabilidade!$M:$M,$O10),0)) +IF($P10="",0,IFERROR(SUMIFS(INDEX(rastreabilidade!$F:$H,0,MATCH(E$3,rastreabilidade!$F$1:$H$1,0)),rastreabilidade!$M:$M,$P10),0)) +IF($Q10="",0,IFERROR(SUMIFS(INDEX(rastreabilidade!$F:$H,0,MATCH(E$3,rastreabilidade!$F$1:$H$1,0)),rastreabilidade!$M:$M,$Q10),0)) -IF($J10="",0,IFERROR(SUMIFS(INDEX(rastreabilidade!$F:$H,0,MATCH(E$3,rastreabilidade!$F$1:$H$1,0)),rastreabilidade!$M:$M,$J10,rastreabilidade!$N:$N,$AM10),0)) -IF($K10="",0,IFERROR(SUMIFS(INDEX(rastreabilidade!$F:$H,0,MATCH(E$3,rastreabilidade!$F$1:$H$1,0)),rastreabilidade!$M:$M,$K10,rastreabilidade!$N:$N,$AM10),0)) -IF($L10="",0,IFERROR(SUMIFS(INDEX(rastreabilidade!$F:$H,0,MATCH(E$3,rastreabilidade!$F$1:$H$1,0)),rastreabilidade!$M:$M,$L10,rastreabilidade!$N:$N,$AM10),0)) -IF($M10="",0,IFERROR(SUMIFS(INDEX(rastreabilidade!$F:$H,0,MATCH(E$3,rastreabilidade!$F$1:$H$1,0)),rastreabilidade!$M:$M,$M10,rastreabilidade!$N:$N,$AM10),0)) -> 0 | F10: =IFERROR(SUMIFS(INDEX(rastreabilidade!$F:$H,0,MATCH(F$3,rastreabilidade!$F$1:$H$1,0)),rastreabilidade!$N:$N,$AM10),0) +IF($N10="",0,IFERROR(SUMIFS(INDEX(rastreabilidade!$F:$H,0,MATCH(F$3,rastreabilidade!$F$1:$H$1,0)),rastreabilidade!$M:$M,$N10),0)) +IF($O10="",0,IFERROR(SUMIFS(INDEX(rastreabilidade!$F:$H,0,MATCH(F$3,rastreabilidade!$F$1:$H$1,0)),rastreabilidade!$M:$M,$O10),0)) +IF($P10="",0,IFERROR(SUMIFS(INDEX(rastreabilidade!$F:$H,0,MATCH(F$3,rastreabilidade!$F$1:$H$1,0)),rastreabilidade!$M:$M,$P10),0)) +IF($Q10="",0,IFERROR(SUMIFS(INDEX(rastreabilidade!$F:$H,0,MATCH(F$3,rastreabilidade!$F$1:$H$1,0)),rastreabilidade!$M:$M,$Q10),0)) -IF($J10="",0,IFERROR(SUMIFS(INDEX(rastreabilidade!$F:$H,0,MATCH(F$3,rastreabilidade!$F$1:$H$1,0)),rastreabilidade!$M:$M,$J10,rastreabilidade!$N:$N,$AM10),0)) -IF($K10="",0,IFERROR(SUMIFS(INDEX(rastreabilidade!$F:$H,0,MATCH(F$3,rastreabilidade!$F$1:$H$1,0)),rastreabilidade!$M:$M,$K10,rastreabilidade!$N:$N,$AM10),0)) -IF($L10="",0,IFERROR(SUMIFS(INDEX(rastreabilidade!$F:$H,0,MATCH(F$3,rastreabilidade!$F$1:$H$1,0)),rastreabilidade!$M:$M,$L10,rastreabilidade!$N:$N,$AM10),0)) -IF($M10="",0,IFERROR(SUMIFS(INDEX(rastreabilidade!$F:$H,0,MATCH(F$3,rastreabilidade!$F$1:$H$1,0)),rastreabilidade!$M:$M,$M10,rastreabilidade!$N:$N,$AM10),0)) -> 0 | G10: =IFERROR(SUMIFS(INDEX(rastreabilidade!$F:$H,0,MATCH(G$3,rastreabilidade!$F$1:$H$1,0)),rastreabilidade!$N:$N,$AM10),0) +IF($N10="",0,IFERROR(SUMIFS(INDEX(rastreabilidade!$F:$H,0,MATCH(G$3,rastreabilidade!$F$1:$H$1,0)),rastreabilidade!$M:$M,$N10),0)) +IF($O10="",0,IFERROR(SUMIFS(INDEX(rastreabilidade!$F:$H,0,MATCH(G$3,rastreabilidade!$F$1:$H$1,0)),rastreabilidade!$M:$M,$O10),0)) +IF($P10="",0,IFERROR(SUMIFS(INDEX(rastreabilidade!$F:$H,0,MATCH(G$3,rastreabilidade!$F$1:$H$1,0)),rastreabilidade!$M:$M,$P10),0)) +IF($Q10="",0,IFERROR(SUMIFS(INDEX(rastreabilidade!$F:$H,0,MATCH(G$3,rastreabilidade!$F$1:$H$1,0)),rastreabilidade!$M:$M,$Q10),0)) -IF($J10="",0,IFERROR(SUMIFS(INDEX(rastreabilidade!$F:$H,0,MATCH(G$3,rastreabilidade!$F$1:$H$1,0)),rastreabilidade!$M:$M,$J10,rastreabilidade!$N:$N,$AM10),0)) -IF($K10="",0,IFERROR(SUMIFS(INDEX(rastreabilidade!$F:$H,0,MATCH(G$3,rastreabilidade!$F$1:$H$1,0)),rastreabilidade!$M:$M,$K10,rastreabilidade!$N:$N,$AM10),0)) -IF($L10="",0,IFERROR(SUMIFS(INDEX(rastreabilidade!$F:$H,0,MATCH(G$3,rastreabilidade!$F$1:$H$1,0)),rastreabilidade!$M:$M,$L10,rastreabilidade!$N:$N,$AM10),0)) -IF($M10="",0,IFERROR(SUMIFS(INDEX(rastreabilidade!$F:$H,0,MATCH(G$3,rastreabilidade!$F$1:$H$1,0)),rastreabilidade!$M:$M,$M10,rastreabilidade!$N:$N,$AM10),0)) -> 0 | I10: {=_xlfn.LET( _xlpm.mem,H10, _xlpm.retiradas,J10:M10, _xlpm.adicoes,N10:Q10, _xlpm.memAjustada,_xlfn.REDUCE(_xlpm.mem,_xlpm.retiradas,_xlfn.LAMBDA(_xlpm.x,_xlpm.y,IF(_xlpm.y<>"",SUBSTITUTE(_xlpm.x," + ("&_xlpm.y&")",""),_xlpm.x))), _xlpm.memRemovida,_xlfn.REDUCE(_xlpm.memAjustada,_xlpm.retiradas,_xlfn.LAMBDA(_xlpm.x,_xlpm.y,IF(_xlpm.y<>"",SUBSTITUTE(_xlpm.x,"("&_xlpm.y&")",""),_xlpm.x))), _xlpm.memSemSinal,IF(OR(LEFT(_xlpm.memRemovida,3)=" + ",LEFT(_xlpm.memRemovida,3)=" - "),MID(_xlpm.memRemovida,4,LEN(_xlpm.memRemovida)),_xlpm.memRemovida), _xlpm.memFinal,IF(OR(RIGHT(_xlpm.memSemSinal,3)=" + ",RIGHT(_xlpm.memSemSinal,3)=" - "),LEFT(_xlpm.memSemSinal,LEN(_xlpm.memSemSinal)-3),_xlpm.memSemSinal), _xlpm.adicoesTxt,_xlfn.TEXTJOIN(" + ",TRUE,IF(_xlpm.adicoes<>"","("&_xlpm.adicoes&")","")), IF(_xlpm.memFinal="",_xlpm.adicoesTxt,IF(_xlpm.adicoesTxt="",_xlpm.memFinal,_xlpm.memFinal&" + "&_xlpm.adicoesTxt)) )} | S10: - Despesas com Vendas | T10: =IFERROR(SUMIFS(INDEX(rastreabilidade!$F:$H,0,MATCH($T$2,rastreabilidade!$F$1:$H$1,0)),rastreabilidade!$K:$K,$S10,rastreabilidade!$D:$D,"Sim"),0) -> 0 | W10: =IFERROR(SUMIFS(INDEX(rastreabilidade!$F:$H,0,MATCH(W$3,rastreabilidade!$F$1:$H$1,0)),rastreabilidade!$N:$N,$AN10),0)*IF($AB10="sim",-1,1) +IF($AG10="",0,IFERROR(SUMIFS(INDEX(rastreabilidade!$F:$H,0,MATCH(W$3,rastreabilidade!$F$1:$H$1,0)),rastreabilidade!$M:$M,$AG10),0)) +IF($AH10="",0,IFERROR(SUMIFS(INDEX(rastreabilidade!$F:$H,0,MATCH(W$3,rastreabilidade!$F$1:$H$1,0)),rastreabilidade!$M:$M,$AH10),0)) +IF($AI10="",0,IFERROR(SUMIFS(INDEX(rastreabilidade!$F:$H,0,MATCH(W$3,rastreabilidade!$F$1:$H$1,0)),rastreabilidade!$M:$M,$AI10),0)) +IF($AJ10="",0,IFERROR(SUMIFS(INDEX(rastreabilidade!$F:$H,0,MATCH(W$3,rastreabilidade!$F$1:$H$1,0)),rastreabilidade!$M:$M,$AJ10),0)) -IF($AC10="",0,IFERROR(SUMIFS(INDEX(rastreabilidade!$F:$H,0,MATCH(W$3,rastreabilidade!$F$1:$H$1,0)),rastreabilidade!$M:$M,$AC10,rastreabilidade!$N:$N,$AN10),0)) -IF($AD10="",0,IFERROR(SUMIFS(INDEX(rastreabilidade!$F:$H,0,MATCH(W$3,rastreabilidade!$F$1:$H$1,0)),rastreabilidade!$M:$M,$AD10,rastreabilidade!$N:$N,$AN10),0)) -IF($AE10="",0,IFERROR(SUMIFS(INDEX(rastreabilidade!$F:$H,0,MATCH(W$3,rastreabilidade!$F$1:$H$1,0)),rastreabilidade!$M:$M,$AE10,rastreabilidade!$N:$N,$AN10),0)) -IF($AF10="",0,IFERROR(SUMIFS(INDEX(rastreabilidade!$F:$H,0,MATCH(W$3,rastreabilidade!$F$1:$H$1,0)),rastreabilidade!$M:$M,$AF10,rastreabilidade!$N:$N,$AN10),0)) -> 0 | X10: =IFERROR(SUMIFS(INDEX(rastreabilidade!$F:$H,0,MATCH(X$3,rastreabilidade!$F$1:$H$1,0)),rastreabilidade!$N:$N,$AN10),0)*IF($AB10="sim",-1,1) +IF($AG10="",0,IFERROR(SUMIFS(INDEX(rastreabilidade!$F:$H,0,MATCH(X$3,rastreabilidade!$F$1:$H$1,0)),rastreabilidade!$M:$M,$AG10),0)) +IF($AH10="",0,IFERROR(SUMIFS(INDEX(rastreabilidade!$F:$H,0,MATCH(X$3,rastreabilidade!$F$1:$H$1,0)),rastreabilidade!$M:$M,$AH10),0)) +IF($AI10="",0,IFERROR(SUMIFS(INDEX(rastreabilidade!$F:$H,0,MATCH(X$3,rastreabilidade!$F$1:$H$1,0)),rastreabilidade!$M:$M,$AI10),0)) +IF($AJ10="",0,IFERROR(SUMIFS(INDEX(rastreabilidade!$F:$H,0,MATCH(X$3,rastreabilidade!$F$1:$H$1,0)),rastreabilidade!$M:$M,$AJ10),0)) -IF($AC10="",0,IFERROR(SUMIFS(INDEX(rastreabilidade!$F:$H,0,MATCH(X$3,rastreabilidade!$F$1:$H$1,0)),rastreabilidade!$M:$M,$AC10,rastreabilidade!$N:$N,$AN10),0)) -IF($AD10="",0,IFERROR(SUMIFS(INDEX(rastreabilidade!$F:$H,0,MATCH(X$3,rastreabilidade!$F$1:$H$1,0)),rastreabilidade!$M:$M,$AD10,rastreabilidade!$N:$N,$AN10),0)) -IF($AE10="",0,IFERROR(SUMIFS(INDEX(rastreabilidade!$F:$H,0,MATCH(X$3,rastreabilidade!$F$1:$H$1,0)),rastreabilidade!$M:$M,$AE10,rastreabilidade!$N:$N,$AN10),0)) -IF($AF10="",0,IFERROR(SUMIFS(INDEX(rastreabilidade!$F:$H,0,MATCH(X$3,rastreabilidade!$F$1:$H$1,0)),rastreabilidade!$M:$M,$AF10,rastreabilidade!$N:$N,$AN10),0)) -> 0 | Y10: =IFERROR(SUMIFS(INDEX(rastreabilidade!$F:$H,0,MATCH(Y$3,rastreabilidade!$F$1:$H$1,0)),rastreabilidade!$N:$N,$AN10),0)*IF($AB10="sim",-1,1) +IF($AG10="",0,IFERROR(SUMIFS(INDEX(rastreabilidade!$F:$H,0,MATCH(Y$3,rastreabilidade!$F$1:$H$1,0)),rastreabilidade!$M:$M,$AG10),0)) +IF($AH10="",0,IFERROR(SUMIFS(INDEX(rastreabilidade!$F:$H,0,MATCH(Y$3,rastreabilidade!$F$1:$H$1,0)),rastreabilidade!$M:$M,$AH10),0)) +IF($AI10="",0,IFERROR(SUMIFS(INDEX(rastreabilidade!$F:$H,0,MATCH(Y$3,rastreabilidade!$F$1:$H$1,0)),rastreabilidade!$M:$M,$AI10),0)) +IF($AJ10="",0,IFERROR(SUMIFS(INDEX(rastreabilidade!$F:$H,0,MATCH(Y$3,rastreabilidade!$F$1:$H$1,0)),rastreabilidade!$M:$M,$AJ10),0)) -IF($AC10="",0,IFERROR(SUMIFS(INDEX(rastreabilidade!$F:$H,0,MATCH(Y$3,rastreabilidade!$F$1:$H$1,0)),rastreabilidade!$M:$M,$AC10,rastreabilidade!$N:$N,$AN10),0)) -IF($AD10="",0,IFERROR(SUMIFS(INDEX(rastreabilidade!$F:$H,0,MATCH(Y$3,rastreabilidade!$F$1:$H$1,0)),rastreabilidade!$M:$M,$AD10,rastreabilidade!$N:$N,$AN10),0)) -IF($AE10="",0,IFERROR(SUMIFS(INDEX(rastreabilidade!$F:$H,0,MATCH(Y$3,rastreabilidade!$F$1:$H$1,0)),rastreabilidade!$M:$M,$AE10,rastreabilidade!$N:$N,$AN10),0)) -IF($AF10="",0,IFERROR(SUMIFS(INDEX(rastreabilidade!$F:$H,0,MATCH(Y$3,rastreabilidade!$F$1:$H$1,0)),rastreabilidade!$M:$M,$AF10,rastreabilidade!$N:$N,$AN10),0)) -> 0 | AA10: {=_xlfn.LET( _xlpm.mem,Z10, _xlpm.retiradas,AC10:AF10, _xlpm.adicoes,AG10:AJ10, _xlpm.memAjustada,_xlfn.REDUCE(_xlpm.mem,_xlpm.retiradas,_xlfn.LAMBDA(_xlpm.x,_xlpm.y,IF(_xlpm.y<>"",SUBSTITUTE(_xlpm.x," + ("&_xlpm.y&")",""),_xlpm.x))), _xlpm.memRemovida,_xlfn.REDUCE(_xlpm.memAjustada,_xlpm.retiradas,_xlfn.LAMBDA(_xlpm.x,_xlpm.y,IF(_xlpm.y<>"",SUBSTITUTE(_xlpm.x,"("&_xlpm.y&")",""),_xlpm.x))), _xlpm.memSemSinal,IF(OR(LEFT(_xlpm.memRemovida,3)=" + ",LEFT(_xlpm.memRemovida,3)=" - "),MID(_xlpm.memRemovida,4,LEN(_xlpm.memRemovida)),_xlpm.memRemovida), _xlpm.memFinal,IF(OR(RIGHT(_xlpm.memSemSinal,3)=" + ",RIGHT(_xlpm.memSemSinal,3)=" - "),LEFT(_xlpm.memSemSinal,LEN(_xlpm.memSemSinal)-3),_xlpm.memSemSinal), _xlpm.adicoesTxt,_xlfn.TEXTJOIN(" + ",TRUE,IF(_xlpm.adicoes<>"","("&_xlpm.adicoes&")","")), IF(_xlpm.memFinal="",_xlpm.adicoesTxt,IF(_xlpm.adicoesTxt="",_xlpm.memFinal,_xlpm.memFinal&" + "&_xlpm.adicoesTxt)) )} | AM10: =_xlfn.TEXTJOIN("|",TRUE,A10,"Ativo","Circulante") -> -PDD|Ativo|Circulante | AN10: =_xlfn.CONCAT(S10,"|","DRE","|","DRE",) -> - Despesas com Vendas|DRE|DRE
A11: Clientes Líquido | B11: =+B8+B9-B10 -> 0 | E11: =+E8+E9-E10 -> 0 | F11: =+F8+F9-F10 -> 0 | G11: =+G8+G9-G10 -> 0 | J11: =+J8+J9-J10 -> 0 | Q11: =+Q8+Q9-Q10 -> 0 | S11: - Despesas Administrativas | T11: =IFERROR(SUMIFS(INDEX(rastreabilidade!$F:$H,0,MATCH($T$2,rastreabilidade!$F$1:$H$1,0)),rastreabilidade!$K:$K,$S11,rastreabilidade!$D:$D,"Sim"),0) -> 0 | W11: =IFERROR(SUMIFS(INDEX(rastreabilidade!$F:$H,0,MATCH(W$3,rastreabilidade!$F$1:$H$1,0)),rastreabilidade!$N:$N,$AN11),0)*IF($AB11="sim",-1,1) +IF($AG11="",0,IFERROR(SUMIFS(INDEX(rastreabilidade!$F:$H,0,MATCH(W$3,rastreabilidade!$F$1:$H$1,0)),rastreabilidade!$M:$M,$AG11),0)) +IF($AH11="",0,IFERROR(SUMIFS(INDEX(rastreabilidade!$F:$H,0,MATCH(W$3,rastreabilidade!$F$1:$H$1,0)),rastreabilidade!$M:$M,$AH11),0)) +IF($AI11="",0,IFERROR(SUMIFS(INDEX(rastreabilidade!$F:$H,0,MATCH(W$3,rastreabilidade!$F$1:$H$1,0)),rastreabilidade!$M:$M,$AI11),0)) +IF($AJ11="",0,IFERROR(SUMIFS(INDEX(rastreabilidade!$F:$H,0,MATCH(W$3,rastreabilidade!$F$1:$H$1,0)),rastreabilidade!$M:$M,$AJ11),0)) -IF($AC11="",0,IFERROR(SUMIFS(INDEX(rastreabilidade!$F:$H,0,MATCH(W$3,rastreabilidade!$F$1:$H$1,0)),rastreabilidade!$M:$M,$AC11,rastreabilidade!$N:$N,$AN11),0)) -IF($AD11="",0,IFERROR(SUMIFS(INDEX(rastreabilidade!$F:$H,0,MATCH(W$3,rastreabilidade!$F$1:$H$1,0)),rastreabilidade!$M:$M,$AD11,rastreabilidade!$N:$N,$AN11),0)) -IF($AE11="",0,IFERROR(SUMIFS(INDEX(rastreabilidade!$F:$H,0,MATCH(W$3,rastreabilidade!$F$1:$H$1,0)),rastreabilidade!$M:$M,$AE11,rastreabilidade!$N:$N,$AN11),0)) -IF($AF11="",0,IFERROR(SUMIFS(INDEX(rastreabilidade!$F:$H,0,MATCH(W$3,rastreabilidade!$F$1:$H$1,0)),rastreabilidade!$M:$M,$AF11,rastreabilidade!$N:$N,$AN11),0)) -> 0 | X11: =IFERROR(SUMIFS(INDEX(rastreabilidade!$F:$H,0,MATCH(X$3,rastreabilidade!$F$1:$H$1,0)),rastreabilidade!$N:$N,$AN11),0)*IF($AB11="sim",-1,1) +IF($AG11="",0,IFERROR(SUMIFS(INDEX(rastreabilidade!$F:$H,0,MATCH(X$3,rastreabilidade!$F$1:$H$1,0)),rastreabilidade!$M:$M,$AG11),0)) +IF($AH11="",0,IFERROR(SUMIFS(INDEX(rastreabilidade!$F:$H,0,MATCH(X$3,rastreabilidade!$F$1:$H$1,0)),rastreabilidade!$M:$M,$AH11),0)) +IF($AI11="",0,IFERROR(SUMIFS(INDEX(rastreabilidade!$F:$H,0,MATCH(X$3,rastreabilidade!$F$1:$H$1,0)),rastreabilidade!$M:$M,$AI11),0)) +IF($AJ11="",0,IFERROR(SUMIFS(INDEX(rastreabilidade!$F:$H,0,MATCH(X$3,rastreabilidade!$F$1:$H$1,0)),rastreabilidade!$M:$M,$AJ11),0)) -IF($AC11="",0,IFERROR(SUMIFS(INDEX(rastreabilidade!$F:$H,0,MATCH(X$3,rastreabilidade!$F$1:$H$1,0)),rastreabilidade!$M:$M,$AC11,rastreabilidade!$N:$N,$AN11),0)) -IF($AD11="",0,IFERROR(SUMIFS(INDEX(rastreabilidade!$F:$H,0,MATCH(X$3,rastreabilidade!$F$1:$H$1,0)),rastreabilidade!$M:$M,$AD11,rastreabilidade!$N:$N,$AN11),0)) -IF($AE11="",0,IFERROR(SUMIFS(INDEX(rastreabilidade!$F:$H,0,MATCH(X$3,rastreabilidade!$F$1:$H$1,0)),rastreabilidade!$M:$M,$AE11,rastreabilidade!$N:$N,$AN11),0)) -IF($AF11="",0,IFERROR(SUMIFS(INDEX(rastreabilidade!$F:$H,0,MATCH(X$3,rastreabilidade!$F$1:$H$1,0)),rastreabilidade!$M:$M,$AF11,rastreabilidade!$N:$N,$AN11),0)) -> 0 | Y11: =IFERROR(SUMIFS(INDEX(rastreabilidade!$F:$H,0,MATCH(Y$3,rastreabilidade!$F$1:$H$1,0)),rastreabilidade!$N:$N,$AN11),0)*IF($AB11="sim",-1,1) +IF($AG11="",0,IFERROR(SUMIFS(INDEX(rastreabilidade!$F:$H,0,MATCH(Y$3,rastreabilidade!$F$1:$H$1,0)),rastreabilidade!$M:$M,$AG11),0)) +IF($AH11="",0,IFERROR(SUMIFS(INDEX(rastreabilidade!$F:$H,0,MATCH(Y$3,rastreabilidade!$F$1:$H$1,0)),rastreabilidade!$M:$M,$AH11),0)) +IF($AI11="",0,IFERROR(SUMIFS(INDEX(rastreabilidade!$F:$H,0,MATCH(Y$3,rastreabilidade!$F$1:$H$1,0)),rastreabilidade!$M:$M,$AI11),0)) +IF($AJ11="",0,IFERROR(SUMIFS(INDEX(rastreabilidade!$F:$H,0,MATCH(Y$3,rastreabilidade!$F$1:$H$1,0)),rastreabilidade!$M:$M,$AJ11),0)) -IF($AC11="",0,IFERROR(SUMIFS(INDEX(rastreabilidade!$F:$H,0,MATCH(Y$3,rastreabilidade!$F$1:$H$1,0)),rastreabilidade!$M:$M,$AC11,rastreabilidade!$N:$N,$AN11),0)) -IF($AD11="",0,IFERROR(SUMIFS(INDEX(rastreabilidade!$F:$H,0,MATCH(Y$3,rastreabilidade!$F$1:$H$1,0)),rastreabilidade!$M:$M,$AD11,rastreabilidade!$N:$N,$AN11),0)) -IF($AE11="",0,IFERROR(SUMIFS(INDEX(rastreabilidade!$F:$H,0,MATCH(Y$3,rastreabilidade!$F$1:$H$1,0)),rastreabilidade!$M:$M,$AE11,rastreabilidade!$N:$N,$AN11),0)) -IF($AF11="",0,IFERROR(SUMIFS(INDEX(rastreabilidade!$F:$H,0,MATCH(Y$3,rastreabilidade!$F$1:$H$1,0)),rastreabilidade!$M:$M,$AF11,rastreabilidade!$N:$N,$AN11),0)) -> 0 | AA11: {=_xlfn.LET( _xlpm.mem,Z11, _xlpm.retiradas,AC11:AF11, _xlpm.adicoes,AG11:AJ11, _xlpm.memAjustada,_xlfn.REDUCE(_xlpm.mem,_xlpm.retiradas,_xlfn.LAMBDA(_xlpm.x,_xlpm.y,IF(_xlpm.y<>"",SUBSTITUTE(_xlpm.x," + ("&_xlpm.y&")",""),_xlpm.x))), _xlpm.memRemovida,_xlfn.REDUCE(_xlpm.memAjustada,_xlpm.retiradas,_xlfn.LAMBDA(_xlpm.x,_xlpm.y,IF(_xlpm.y<>"",SUBSTITUTE(_xlpm.x,"("&_xlpm.y&")",""),_xlpm.x))), _xlpm.memSemSinal,IF(OR(LEFT(_xlpm.memRemovida,3)=" + ",LEFT(_xlpm.memRemovida,3)=" - "),MID(_xlpm.memRemovida,4,LEN(_xlpm.memRemovida)),_xlpm.memRemovida), _xlpm.memFinal,IF(OR(RIGHT(_xlpm.memSemSinal,3)=" + ",RIGHT(_xlpm.memSemSinal,3)=" - "),LEFT(_xlpm.memSemSinal,LEN(_xlpm.memSemSinal)-3),_xlpm.memSemSinal), _xlpm.adicoesTxt,_xlfn.TEXTJOIN(" + ",TRUE,IF(_xlpm.adicoes<>"","("&_xlpm.adicoes&")","")), IF(_xlpm.memFinal="",_xlpm.adicoesTxt,IF(_xlpm.adicoesTxt="",_xlpm.memFinal,_xlpm.memFinal&" + "&_xlpm.adicoesTxt)) )} | AM11: =_xlfn.TEXTJOIN("|",TRUE,A11,"Ativo","Circulante") -> Clientes Líquido|Ativo|Circulante | AN11: =_xlfn.CONCAT(S11,"|","DRE","|","DRE",) -> - Despesas Administrativas|DRE|DRE
A12: Matéria-Prima | B12: =IFERROR(SUMIFS(INDEX(rastreabilidade!$F:$H,0,MATCH($B$2,rastreabilidade!$F$1:$H$1,0)),rastreabilidade!$K:$K,$A12,rastreabilidade!$D:$D,"Sim"),0) -> 0 | E12: =IFERROR(SUMIFS(INDEX(rastreabilidade!$F:$H,0,MATCH(E$3,rastreabilidade!$F$1:$H$1,0)),rastreabilidade!$N:$N,$AM12),0) +IF($N12="",0,IFERROR(SUMIFS(INDEX(rastreabilidade!$F:$H,0,MATCH(E$3,rastreabilidade!$F$1:$H$1,0)),rastreabilidade!$M:$M,$N12),0)) +IF($O12="",0,IFERROR(SUMIFS(INDEX(rastreabilidade!$F:$H,0,MATCH(E$3,rastreabilidade!$F$1:$H$1,0)),rastreabilidade!$M:$M,$O12),0)) +IF($P12="",0,IFERROR(SUMIFS(INDEX(rastreabilidade!$F:$H,0,MATCH(E$3,rastreabilidade!$F$1:$H$1,0)),rastreabilidade!$M:$M,$P12),0)) +IF($Q12="",0,IFERROR(SUMIFS(INDEX(rastreabilidade!$F:$H,0,MATCH(E$3,rastreabilidade!$F$1:$H$1,0)),rastreabilidade!$M:$M,$Q12),0)) -IF($J12="",0,IFERROR(SUMIFS(INDEX(rastreabilidade!$F:$H,0,MATCH(E$3,rastreabilidade!$F$1:$H$1,0)),rastreabilidade!$M:$M,$J12,rastreabilidade!$N:$N,$AM12),0)) -IF($K12="",0,IFERROR(SUMIFS(INDEX(rastreabilidade!$F:$H,0,MATCH(E$3,rastreabilidade!$F$1:$H$1,0)),rastreabilidade!$M:$M,$K12,rastreabilidade!$N:$N,$AM12),0)) -IF($L12="",0,IFERROR(SUMIFS(INDEX(rastreabilidade!$F:$H,0,MATCH(E$3,rastreabilidade!$F$1:$H$1,0)),rastreabilidade!$M:$M,$L12,rastreabilidade!$N:$N,$AM12),0)) -IF($M12="",0,IFERROR(SUMIFS(INDEX(rastreabilidade!$F:$H,0,MATCH(E$3,rastreabilidade!$F$1:$H$1,0)),rastreabilidade!$M:$M,$M12,rastreabilidade!$N:$N,$AM12),0)) -> 0 | F12: =IFERROR(SUMIFS(INDEX(rastreabilidade!$F:$H,0,MATCH(F$3,rastreabilidade!$F$1:$H$1,0)),rastreabilidade!$N:$N,$AM12),0) +IF($N12="",0,IFERROR(SUMIFS(INDEX(rastreabilidade!$F:$H,0,MATCH(F$3,rastreabilidade!$F$1:$H$1,0)),rastreabilidade!$M:$M,$N12),0)) +IF($O12="",0,IFERROR(SUMIFS(INDEX(rastreabilidade!$F:$H,0,MATCH(F$3,rastreabilidade!$F$1:$H$1,0)),rastreabilidade!$M:$M,$O12),0)) +IF($P12="",0,IFERROR(SUMIFS(INDEX(rastreabilidade!$F:$H,0,MATCH(F$3,rastreabilidade!$F$1:$H$1,0)),rastreabilidade!$M:$M,$P12),0)) +IF($Q12="",0,IFERROR(SUMIFS(INDEX(rastreabilidade!$F:$H,0,MATCH(F$3,rastreabilidade!$F$1:$H$1,0)),rastreabilidade!$M:$M,$Q12),0)) -IF($J12="",0,IFERROR(SUMIFS(INDEX(rastreabilidade!$F:$H,0,MATCH(F$3,rastreabilidade!$F$1:$H$1,0)),rastreabilidade!$M:$M,$J12,rastreabilidade!$N:$N,$AM12),0)) -IF($K12="",0,IFERROR(SUMIFS(INDEX(rastreabilidade!$F:$H,0,MATCH(F$3,rastreabilidade!$F$1:$H$1,0)),rastreabilidade!$M:$M,$K12,rastreabilidade!$N:$N,$AM12),0)) -IF($L12="",0,IFERROR(SUMIFS(INDEX(rastreabilidade!$F:$H,0,MATCH(F$3,rastreabilidade!$F$1:$H$1,0)),rastreabilidade!$M:$M,$L12,rastreabilidade!$N:$N,$AM12),0)) -IF($M12="",0,IFERROR(SUMIFS(INDEX(rastreabilidade!$F:$H,0,MATCH(F$3,rastreabilidade!$F$1:$H$1,0)),rastreabilidade!$M:$M,$M12,rastreabilidade!$N:$N,$AM12),0)) -> 0 | G12: =IFERROR(SUMIFS(INDEX(rastreabilidade!$F:$H,0,MATCH(G$3,rastreabilidade!$F$1:$H$1,0)),rastreabilidade!$N:$N,$AM12),0) +IF($N12="",0,IFERROR(SUMIFS(INDEX(rastreabilidade!$F:$H,0,MATCH(G$3,rastreabilidade!$F$1:$H$1,0)),rastreabilidade!$M:$M,$N12),0)) +IF($O12="",0,IFERROR(SUMIFS(INDEX(rastreabilidade!$F:$H,0,MATCH(G$3,rastreabilidade!$F$1:$H$1,0)),rastreabilidade!$M:$M,$O12),0)) +IF($P12="",0,IFERROR(SUMIFS(INDEX(rastreabilidade!$F:$H,0,MATCH(G$3,rastreabilidade!$F$1:$H$1,0)),rastreabilidade!$M:$M,$P12),0)) +IF($Q12="",0,IFERROR(SUMIFS(INDEX(rastreabilidade!$F:$H,0,MATCH(G$3,rastreabilidade!$F$1:$H$1,0)),rastreabilidade!$M:$M,$Q12),0)) -IF($J12="",0,IFERROR(SUMIFS(INDEX(rastreabilidade!$F:$H,0,MATCH(G$3,rastreabilidade!$F$1:$H$1,0)),rastreabilidade!$M:$M,$J12,rastreabilidade!$N:$N,$AM12),0)) -IF($K12="",0,IFERROR(SUMIFS(INDEX(rastreabilidade!$F:$H,0,MATCH(G$3,rastreabilidade!$F$1:$H$1,0)),rastreabilidade!$M:$M,$K12,rastreabilidade!$N:$N,$AM12),0)) -IF($L12="",0,IFERROR(SUMIFS(INDEX(rastreabilidade!$F:$H,0,MATCH(G$3,rastreabilidade!$F$1:$H$1,0)),rastreabilidade!$M:$M,$L12,rastreabilidade!$N:$N,$AM12),0)) -IF($M12="",0,IFERROR(SUMIFS(INDEX(rastreabilidade!$F:$H,0,MATCH(G$3,rastreabilidade!$F$1:$H$1,0)),rastreabilidade!$M:$M,$M12,rastreabilidade!$N:$N,$AM12),0)) -> 0 | I12: {=_xlfn.LET( _xlpm.mem,H12, _xlpm.retiradas,J12:M12, _xlpm.adicoes,N12:Q12, _xlpm.memAjustada,_xlfn.REDUCE(_xlpm.mem,_xlpm.retiradas,_xlfn.LAMBDA(_xlpm.x,_xlpm.y,IF(_xlpm.y<>"",SUBSTITUTE(_xlpm.x," + ("&_xlpm.y&")",""),_xlpm.x))), _xlpm.memRemovida,_xlfn.REDUCE(_xlpm.memAjustada,_xlpm.retiradas,_xlfn.LAMBDA(_xlpm.x,_xlpm.y,IF(_xlpm.y<>"",SUBSTITUTE(_xlpm.x,"("&_xlpm.y&")",""),_xlpm.x))), _xlpm.memSemSinal,IF(OR(LEFT(_xlpm.memRemovida,3)=" + ",LEFT(_xlpm.memRemovida,3)=" - "),MID(_xlpm.memRemovida,4,LEN(_xlpm.memRemovida)),_xlpm.memRemovida), _xlpm.memFinal,IF(OR(RIGHT(_xlpm.memSemSinal,3)=" + ",RIGHT(_xlpm.memSemSinal,3)=" - "),LEFT(_xlpm.memSemSinal,LEN(_xlpm.memSemSinal)-3),_xlpm.memSemSinal), _xlpm.adicoesTxt,_xlfn.TEXTJOIN(" + ",TRUE,IF(_xlpm.adicoes<>"","("&_xlpm.adicoes&")","")), IF(_xlpm.memFinal="",_xlpm.adicoesTxt,IF(_xlpm.adicoesTxt="",_xlpm.memFinal,_xlpm.memFinal&" + "&_xlpm.adicoesTxt)) )} | S12: Resultado da Exploração | T12: =T9-T10-T11 -> 0 | W12: =W9-W10-W11 -> 0 | X12: =X9-X10-X11 -> 0 | Y12: =Y9-Y10-Y11 -> 0 | AM12: =_xlfn.TEXTJOIN("|",TRUE,A12,"Ativo","Circulante") -> Matéria-Prima|Ativo|Circulante | AN12: =_xlfn.CONCAT(S12,"|","DRE","|","DRE",) -> Resultado da Exploração |DRE|DRE
A13: Produtos em Elaboração | B13: =IFERROR(SUMIFS(INDEX(rastreabilidade!$F:$H,0,MATCH($B$2,rastreabilidade!$F$1:$H$1,0)),rastreabilidade!$K:$K,$A13,rastreabilidade!$D:$D,"Sim"),0) -> 0 | E13: =IFERROR(SUMIFS(INDEX(rastreabilidade!$F:$H,0,MATCH(E$3,rastreabilidade!$F$1:$H$1,0)),rastreabilidade!$N:$N,$AM13),0) +IF($N13="",0,IFERROR(SUMIFS(INDEX(rastreabilidade!$F:$H,0,MATCH(E$3,rastreabilidade!$F$1:$H$1,0)),rastreabilidade!$M:$M,$N13),0)) +IF($O13="",0,IFERROR(SUMIFS(INDEX(rastreabilidade!$F:$H,0,MATCH(E$3,rastreabilidade!$F$1:$H$1,0)),rastreabilidade!$M:$M,$O13),0)) +IF($P13="",0,IFERROR(SUMIFS(INDEX(rastreabilidade!$F:$H,0,MATCH(E$3,rastreabilidade!$F$1:$H$1,0)),rastreabilidade!$M:$M,$P13),0)) +IF($Q13="",0,IFERROR(SUMIFS(INDEX(rastreabilidade!$F:$H,0,MATCH(E$3,rastreabilidade!$F$1:$H$1,0)),rastreabilidade!$M:$M,$Q13),0)) -IF($J13="",0,IFERROR(SUMIFS(INDEX(rastreabilidade!$F:$H,0,MATCH(E$3,rastreabilidade!$F$1:$H$1,0)),rastreabilidade!$M:$M,$J13,rastreabilidade!$N:$N,$AM13),0)) -IF($K13="",0,IFERROR(SUMIFS(INDEX(rastreabilidade!$F:$H,0,MATCH(E$3,rastreabilidade!$F$1:$H$1,0)),rastreabilidade!$M:$M,$K13,rastreabilidade!$N:$N,$AM13),0)) -IF($L13="",0,IFERROR(SUMIFS(INDEX(rastreabilidade!$F:$H,0,MATCH(E$3,rastreabilidade!$F$1:$H$1,0)),rastreabilidade!$M:$M,$L13,rastreabilidade!$N:$N,$AM13),0)) -IF($M13="",0,IFERROR(SUMIFS(INDEX(rastreabilidade!$F:$H,0,MATCH(E$3,rastreabilidade!$F$1:$H$1,0)),rastreabilidade!$M:$M,$M13,rastreabilidade!$N:$N,$AM13),0)) -> 0 | F13: =IFERROR(SUMIFS(INDEX(rastreabilidade!$F:$H,0,MATCH(F$3,rastreabilidade!$F$1:$H$1,0)),rastreabilidade!$N:$N,$AM13),0) +IF($N13="",0,IFERROR(SUMIFS(INDEX(rastreabilidade!$F:$H,0,MATCH(F$3,rastreabilidade!$F$1:$H$1,0)),rastreabilidade!$M:$M,$N13),0)) +IF($O13="",0,IFERROR(SUMIFS(INDEX(rastreabilidade!$F:$H,0,MATCH(F$3,rastreabilidade!$F$1:$H$1,0)),rastreabilidade!$M:$M,$O13),0)) +IF($P13="",0,IFERROR(SUMIFS(INDEX(rastreabilidade!$F:$H,0,MATCH(F$3,rastreabilidade!$F$1:$H$1,0)),rastreabilidade!$M:$M,$P13),0)) +IF($Q13="",0,IFERROR(SUMIFS(INDEX(rastreabilidade!$F:$H,0,MATCH(F$3,rastreabilidade!$F$1:$H$1,0)),rastreabilidade!$M:$M,$Q13),0)) -IF($J13="",0,IFERROR(SUMIFS(INDEX(rastreabilidade!$F:$H,0,MATCH(F$3,rastreabilidade!$F$1:$H$1,0)),rastreabilidade!$M:$M,$J13,rastreabilidade!$N:$N,$AM13),0)) -IF($K13="",0,IFERROR(SUMIFS(INDEX(rastreabilidade!$F:$H,0,MATCH(F$3,rastreabilidade!$F$1:$H$1,0)),rastreabilidade!$M:$M,$K13,rastreabilidade!$N:$N,$AM13),0)) -IF($L13="",0,IFERROR(SUMIFS(INDEX(rastreabilidade!$F:$H,0,MATCH(F$3,rastreabilidade!$F$1:$H$1,0)),rastreabilidade!$M:$M,$L13,rastreabilidade!$N:$N,$AM13),0)) -IF($M13="",0,IFERROR(SUMIFS(INDEX(rastreabilidade!$F:$H,0,MATCH(F$3,rastreabilidade!$F$1:$H$1,0)),rastreabilidade!$M:$M,$M13,rastreabilidade!$N:$N,$AM13),0)) -> 0 | G13: =IFERROR(SUMIFS(INDEX(rastreabilidade!$F:$H,0,MATCH(G$3,rastreabilidade!$F$1:$H$1,0)),rastreabilidade!$N:$N,$AM13),0) +IF($N13="",0,IFERROR(SUMIFS(INDEX(rastreabilidade!$F:$H,0,MATCH(G$3,rastreabilidade!$F$1:$H$1,0)),rastreabilidade!$M:$M,$N13),0)) +IF($O13="",0,IFERROR(SUMIFS(INDEX(rastreabilidade!$F:$H,0,MATCH(G$3,rastreabilidade!$F$1:$H$1,0)),rastreabilidade!$M:$M,$O13),0)) +IF($P13="",0,IFERROR(SUMIFS(INDEX(rastreabilidade!$F:$H,0,MATCH(G$3,rastreabilidade!$F$1:$H$1,0)),rastreabilidade!$M:$M,$P13),0)) +IF($Q13="",0,IFERROR(SUMIFS(INDEX(rastreabilidade!$F:$H,0,MATCH(G$3,rastreabilidade!$F$1:$H$1,0)),rastreabilidade!$M:$M,$Q13),0)) -IF($J13="",0,IFERROR(SUMIFS(INDEX(rastreabilidade!$F:$H,0,MATCH(G$3,rastreabilidade!$F$1:$H$1,0)),rastreabilidade!$M:$M,$J13,rastreabilidade!$N:$N,$AM13),0)) -IF($K13="",0,IFERROR(SUMIFS(INDEX(rastreabilidade!$F:$H,0,MATCH(G$3,rastreabilidade!$F$1:$H$1,0)),rastreabilidade!$M:$M,$K13,rastreabilidade!$N:$N,$AM13),0)) -IF($L13="",0,IFERROR(SUMIFS(INDEX(rastreabilidade!$F:$H,0,MATCH(G$3,rastreabilidade!$F$1:$H$1,0)),rastreabilidade!$M:$M,$L13,rastreabilidade!$N:$N,$AM13),0)) -IF($M13="",0,IFERROR(SUMIFS(INDEX(rastreabilidade!$F:$H,0,MATCH(G$3,rastreabilidade!$F$1:$H$1,0)),rastreabilidade!$M:$M,$M13,rastreabilidade!$N:$N,$AM13),0)) -> 0 | I13: {=_xlfn.LET( _xlpm.mem,H13, _xlpm.retiradas,J13:M13, _xlpm.adicoes,N13:Q13, _xlpm.memAjustada,_xlfn.REDUCE(_xlpm.mem,_xlpm.retiradas,_xlfn.LAMBDA(_xlpm.x,_xlpm.y,IF(_xlpm.y<>"",SUBSTITUTE(_xlpm.x," + ("&_xlpm.y&")",""),_xlpm.x))), _xlpm.memRemovida,_xlfn.REDUCE(_xlpm.memAjustada,_xlpm.retiradas,_xlfn.LAMBDA(_xlpm.x,_xlpm.y,IF(_xlpm.y<>"",SUBSTITUTE(_xlpm.x,"("&_xlpm.y&")",""),_xlpm.x))), _xlpm.memSemSinal,IF(OR(LEFT(_xlpm.memRemovida,3)=" + ",LEFT(_xlpm.memRemovida,3)=" - "),MID(_xlpm.memRemovida,4,LEN(_xlpm.memRemovida)),_xlpm.memRemovida), _xlpm.memFinal,IF(OR(RIGHT(_xlpm.memSemSinal,3)=" + ",RIGHT(_xlpm.memSemSinal,3)=" - "),LEFT(_xlpm.memSemSinal,LEN(_xlpm.memSemSinal)-3),_xlpm.memSemSinal), _xlpm.adicoesTxt,_xlfn.TEXTJOIN(" + ",TRUE,IF(_xlpm.adicoes<>"","("&_xlpm.adicoes&")","")), IF(_xlpm.memFinal="",_xlpm.adicoesTxt,IF(_xlpm.adicoesTxt="",_xlpm.memFinal,_xlpm.memFinal&" + "&_xlpm.adicoesTxt)) )} | S13: +/-Outras Receitas/Despesas Operacionais | T13: =IFERROR(SUMIFS(INDEX(rastreabilidade!$F:$H,0,MATCH($T$2,rastreabilidade!$F$1:$H$1,0)),rastreabilidade!$K:$K,$S13,rastreabilidade!$D:$D,"Sim"),0) -> 0 | W13: =IFERROR(SUMIFS(INDEX(rastreabilidade!$F:$H,0,MATCH(W$3,rastreabilidade!$F$1:$H$1,0)),rastreabilidade!$N:$N,$AN13),0)*IF($AB13="sim",-1,1) +IF($AG13="",0,IFERROR(SUMIFS(INDEX(rastreabilidade!$F:$H,0,MATCH(W$3,rastreabilidade!$F$1:$H$1,0)),rastreabilidade!$M:$M,$AG13),0)) +IF($AH13="",0,IFERROR(SUMIFS(INDEX(rastreabilidade!$F:$H,0,MATCH(W$3,rastreabilidade!$F$1:$H$1,0)),rastreabilidade!$M:$M,$AH13),0)) +IF($AI13="",0,IFERROR(SUMIFS(INDEX(rastreabilidade!$F:$H,0,MATCH(W$3,rastreabilidade!$F$1:$H$1,0)),rastreabilidade!$M:$M,$AI13),0)) +IF($AJ13="",0,IFERROR(SUMIFS(INDEX(rastreabilidade!$F:$H,0,MATCH(W$3,rastreabilidade!$F$1:$H$1,0)),rastreabilidade!$M:$M,$AJ13),0)) -IF($AC13="",0,IFERROR(SUMIFS(INDEX(rastreabilidade!$F:$H,0,MATCH(W$3,rastreabilidade!$F$1:$H$1,0)),rastreabilidade!$M:$M,$AC13,rastreabilidade!$N:$N,$AN13),0)) -IF($AD13="",0,IFERROR(SUMIFS(INDEX(rastreabilidade!$F:$H,0,MATCH(W$3,rastreabilidade!$F$1:$H$1,0)),rastreabilidade!$M:$M,$AD13,rastreabilidade!$N:$N,$AN13),0)) -IF($AE13="",0,IFERROR(SUMIFS(INDEX(rastreabilidade!$F:$H,0,MATCH(W$3,rastreabilidade!$F$1:$H$1,0)),rastreabilidade!$M:$M,$AE13,rastreabilidade!$N:$N,$AN13),0)) -IF($AF13="",0,IFERROR(SUMIFS(INDEX(rastreabilidade!$F:$H,0,MATCH(W$3,rastreabilidade!$F$1:$H$1,0)),rastreabilidade!$M:$M,$AF13,rastreabilidade!$N:$N,$AN13),0)) -> 0 | X13: =IFERROR(SUMIFS(INDEX(rastreabilidade!$F:$H,0,MATCH(X$3,rastreabilidade!$F$1:$H$1,0)),rastreabilidade!$N:$N,$AN13),0)*IF($AB13="sim",-1,1) +IF($AG13="",0,IFERROR(SUMIFS(INDEX(rastreabilidade!$F:$H,0,MATCH(X$3,rastreabilidade!$F$1:$H$1,0)),rastreabilidade!$M:$M,$AG13),0)) +IF($AH13="",0,IFERROR(SUMIFS(INDEX(rastreabilidade!$F:$H,0,MATCH(X$3,rastreabilidade!$F$1:$H$1,0)),rastreabilidade!$M:$M,$AH13),0)) +IF($AI13="",0,IFERROR(SUMIFS(INDEX(rastreabilidade!$F:$H,0,MATCH(X$3,rastreabilidade!$F$1:$H$1,0)),rastreabilidade!$M:$M,$AI13),0)) +IF($AJ13="",0,IFERROR(SUMIFS(INDEX(rastreabilidade!$F:$H,0,MATCH(X$3,rastreabilidade!$F$1:$H$1,0)),rastreabilidade!$M:$M,$AJ13),0)) -IF($AC13="",0,IFERROR(SUMIFS(INDEX(rastreabilidade!$F:$H,0,MATCH(X$3,rastreabilidade!$F$1:$H$1,0)),rastreabilidade!$M:$M,$AC13,rastreabilidade!$N:$N,$AN13),0)) -IF($AD13="",0,IFERROR(SUMIFS(INDEX(rastreabilidade!$F:$H,0,MATCH(X$3,rastreabilidade!$F$1:$H$1,0)),rastreabilidade!$M:$M,$AD13,rastreabilidade!$N:$N,$AN13),0)) -IF($AE13="",0,IFERROR(SUMIFS(INDEX(rastreabilidade!$F:$H,0,MATCH(X$3,rastreabilidade!$F$1:$H$1,0)),rastreabilidade!$M:$M,$AE13,rastreabilidade!$N:$N,$AN13),0)) -IF($AF13="",0,IFERROR(SUMIFS(INDEX(rastreabilidade!$F:$H,0,MATCH(X$3,rastreabilidade!$F$1:$H$1,0)),rastreabilidade!$M:$M,$AF13,rastreabilidade!$N:$N,$AN13),0)) -> 0 | Y13: =IFERROR(SUMIFS(INDEX(rastreabilidade!$F:$H,0,MATCH(Y$3,rastreabilidade!$F$1:$H$1,0)),rastreabilidade!$N:$N,$AN13),0)*IF($AB13="sim",-1,1) +IF($AG13="",0,IFERROR(SUMIFS(INDEX(rastreabilidade!$F:$H,0,MATCH(Y$3,rastreabilidade!$F$1:$H$1,0)),rastreabilidade!$M:$M,$AG13),0)) +IF($AH13="",0,IFERROR(SUMIFS(INDEX(rastreabilidade!$F:$H,0,MATCH(Y$3,rastreabilidade!$F$1:$H$1,0)),rastreabilidade!$M:$M,$AH13),0)) +IF($AI13="",0,IFERROR(SUMIFS(INDEX(rastreabilidade!$F:$H,0,MATCH(Y$3,rastreabilidade!$F$1:$H$1,0)),rastreabilidade!$M:$M,$AI13),0)) +IF($AJ13="",0,IFERROR(SUMIFS(INDEX(rastreabilidade!$F:$H,0,MATCH(Y$3,rastreabilidade!$F$1:$H$1,0)),rastreabilidade!$M:$M,$AJ13),0)) -IF($AC13="",0,IFERROR(SUMIFS(INDEX(rastreabilidade!$F:$H,0,MATCH(Y$3,rastreabilidade!$F$1:$H$1,0)),rastreabilidade!$M:$M,$AC13,rastreabilidade!$N:$N,$AN13),0)) -IF($AD13="",0,IFERROR(SUMIFS(INDEX(rastreabilidade!$F:$H,0,MATCH(Y$3,rastreabilidade!$F$1:$H$1,0)),rastreabilidade!$M:$M,$AD13,rastreabilidade!$N:$N,$AN13),0)) -IF($AE13="",0,IFERROR(SUMIFS(INDEX(rastreabilidade!$F:$H,0,MATCH(Y$3,rastreabilidade!$F$1:$H$1,0)),rastreabilidade!$M:$M,$AE13,rastreabilidade!$N:$N,$AN13),0)) -IF($AF13="",0,IFERROR(SUMIFS(INDEX(rastreabilidade!$F:$H,0,MATCH(Y$3,rastreabilidade!$F$1:$H$1,0)),rastreabilidade!$M:$M,$AF13,rastreabilidade!$N:$N,$AN13),0)) -> 0 | AA13: {=_xlfn.LET( _xlpm.mem,Z13, _xlpm.retiradas,AC13:AF13, _xlpm.adicoes,AG13:AJ13, _xlpm.memAjustada,_xlfn.REDUCE(_xlpm.mem,_xlpm.retiradas,_xlfn.LAMBDA(_xlpm.x,_xlpm.y,IF(_xlpm.y<>"",SUBSTITUTE(_xlpm.x," + ("&_xlpm.y&")",""),_xlpm.x))), _xlpm.memRemovida,_xlfn.REDUCE(_xlpm.memAjustada,_xlpm.retiradas,_xlfn.LAMBDA(_xlpm.x,_xlpm.y,IF(_xlpm.y<>"",SUBSTITUTE(_xlpm.x,"("&_xlpm.y&")",""),_xlpm.x))), _xlpm.memSemSinal,IF(OR(LEFT(_xlpm.memRemovida,3)=" + ",LEFT(_xlpm.memRemovida,3)=" - "),MID(_xlpm.memRemovida,4,LEN(_xlpm.memRemovida)),_xlpm.memRemovida), _xlpm.memFinal,IF(OR(RIGHT(_xlpm.memSemSinal,3)=" + ",RIGHT(_xlpm.memSemSinal,3)=" - "),LEFT(_xlpm.memSemSinal,LEN(_xlpm.memSemSinal)-3),_xlpm.memSemSinal), _xlpm.adicoesTxt,_xlfn.TEXTJOIN(" + ",TRUE,IF(_xlpm.adicoes<>"","("&_xlpm.adicoes&")","")), IF(_xlpm.memFinal="",_xlpm.adicoesTxt,IF(_xlpm.adicoesTxt="",_xlpm.memFinal,_xlpm.memFinal&" + "&_xlpm.adicoesTxt)) )} | AM13: =_xlfn.TEXTJOIN("|",TRUE,A13,"Ativo","Circulante") -> Produtos em Elaboração|Ativo|Circulante | AN13: =_xlfn.CONCAT(S13,"|","DRE","|","DRE",) -> +/-Outras Receitas/Despesas Operacionais|DRE|DRE
A14: Produtos Acabados | B14: =IFERROR(SUMIFS(INDEX(rastreabilidade!$F:$H,0,MATCH($B$2,rastreabilidade!$F$1:$H$1,0)),rastreabilidade!$K:$K,$A14,rastreabilidade!$D:$D,"Sim"),0) -> 0 | E14: =IFERROR(SUMIFS(INDEX(rastreabilidade!$F:$H,0,MATCH(E$3,rastreabilidade!$F$1:$H$1,0)),rastreabilidade!$N:$N,$AM14),0) +IF($N14="",0,IFERROR(SUMIFS(INDEX(rastreabilidade!$F:$H,0,MATCH(E$3,rastreabilidade!$F$1:$H$1,0)),rastreabilidade!$M:$M,$N14),0)) +IF($O14="",0,IFERROR(SUMIFS(INDEX(rastreabilidade!$F:$H,0,MATCH(E$3,rastreabilidade!$F$1:$H$1,0)),rastreabilidade!$M:$M,$O14),0)) +IF($P14="",0,IFERROR(SUMIFS(INDEX(rastreabilidade!$F:$H,0,MATCH(E$3,rastreabilidade!$F$1:$H$1,0)),rastreabilidade!$M:$M,$P14),0)) +IF($Q14="",0,IFERROR(SUMIFS(INDEX(rastreabilidade!$F:$H,0,MATCH(E$3,rastreabilidade!$F$1:$H$1,0)),rastreabilidade!$M:$M,$Q14),0)) -IF($J14="",0,IFERROR(SUMIFS(INDEX(rastreabilidade!$F:$H,0,MATCH(E$3,rastreabilidade!$F$1:$H$1,0)),rastreabilidade!$M:$M,$J14,rastreabilidade!$N:$N,$AM14),0)) -IF($K14="",0,IFERROR(SUMIFS(INDEX(rastreabilidade!$F:$H,0,MATCH(E$3,rastreabilidade!$F$1:$H$1,0)),rastreabilidade!$M:$M,$K14,rastreabilidade!$N:$N,$AM14),0)) -IF($L14="",0,IFERROR(SUMIFS(INDEX(rastreabilidade!$F:$H,0,MATCH(E$3,rastreabilidade!$F$1:$H$1,0)),rastreabilidade!$M:$M,$L14,rastreabilidade!$N:$N,$AM14),0)) -IF($M14="",0,IFERROR(SUMIFS(INDEX(rastreabilidade!$F:$H,0,MATCH(E$3,rastreabilidade!$F$1:$H$1,0)),rastreabilidade!$M:$M,$M14,rastreabilidade!$N:$N,$AM14),0)) -> 0 | F14: =IFERROR(SUMIFS(INDEX(rastreabilidade!$F:$H,0,MATCH(F$3,rastreabilidade!$F$1:$H$1,0)),rastreabilidade!$N:$N,$AM14),0) +IF($N14="",0,IFERROR(SUMIFS(INDEX(rastreabilidade!$F:$H,0,MATCH(F$3,rastreabilidade!$F$1:$H$1,0)),rastreabilidade!$M:$M,$N14),0)) +IF($O14="",0,IFERROR(SUMIFS(INDEX(rastreabilidade!$F:$H,0,MATCH(F$3,rastreabilidade!$F$1:$H$1,0)),rastreabilidade!$M:$M,$O14),0)) +IF($P14="",0,IFERROR(SUMIFS(INDEX(rastreabilidade!$F:$H,0,MATCH(F$3,rastreabilidade!$F$1:$H$1,0)),rastreabilidade!$M:$M,$P14),0)) +IF($Q14="",0,IFERROR(SUMIFS(INDEX(rastreabilidade!$F:$H,0,MATCH(F$3,rastreabilidade!$F$1:$H$1,0)),rastreabilidade!$M:$M,$Q14),0)) -IF($J14="",0,IFERROR(SUMIFS(INDEX(rastreabilidade!$F:$H,0,MATCH(F$3,rastreabilidade!$F$1:$H$1,0)),rastreabilidade!$M:$M,$J14,rastreabilidade!$N:$N,$AM14),0)) -IF($K14="",0,IFERROR(SUMIFS(INDEX(rastreabilidade!$F:$H,0,MATCH(F$3,rastreabilidade!$F$1:$H$1,0)),rastreabilidade!$M:$M,$K14,rastreabilidade!$N:$N,$AM14),0)) -IF($L14="",0,IFERROR(SUMIFS(INDEX(rastreabilidade!$F:$H,0,MATCH(F$3,rastreabilidade!$F$1:$H$1,0)),rastreabilidade!$M:$M,$L14,rastreabilidade!$N:$N,$AM14),0)) -IF($M14="",0,IFERROR(SUMIFS(INDEX(rastreabilidade!$F:$H,0,MATCH(F$3,rastreabilidade!$F$1:$H$1,0)),rastreabilidade!$M:$M,$M14,rastreabilidade!$N:$N,$AM14),0)) -> 0 | G14: =IFERROR(SUMIFS(INDEX(rastreabilidade!$F:$H,0,MATCH(G$3,rastreabilidade!$F$1:$H$1,0)),rastreabilidade!$N:$N,$AM14),0) +IF($N14="",0,IFERROR(SUMIFS(INDEX(rastreabilidade!$F:$H,0,MATCH(G$3,rastreabilidade!$F$1:$H$1,0)),rastreabilidade!$M:$M,$N14),0)) +IF($O14="",0,IFERROR(SUMIFS(INDEX(rastreabilidade!$F:$H,0,MATCH(G$3,rastreabilidade!$F$1:$H$1,0)),rastreabilidade!$M:$M,$O14),0)) +IF($P14="",0,IFERROR(SUMIFS(INDEX(rastreabilidade!$F:$H,0,MATCH(G$3,rastreabilidade!$F$1:$H$1,0)),rastreabilidade!$M:$M,$P14),0)) +IF($Q14="",0,IFERROR(SUMIFS(INDEX(rastreabilidade!$F:$H,0,MATCH(G$3,rastreabilidade!$F$1:$H$1,0)),rastreabilidade!$M:$M,$Q14),0)) -IF($J14="",0,IFERROR(SUMIFS(INDEX(rastreabilidade!$F:$H,0,MATCH(G$3,rastreabilidade!$F$1:$H$1,0)),rastreabilidade!$M:$M,$J14,rastreabilidade!$N:$N,$AM14),0)) -IF($K14="",0,IFERROR(SUMIFS(INDEX(rastreabilidade!$F:$H,0,MATCH(G$3,rastreabilidade!$F$1:$H$1,0)),rastreabilidade!$M:$M,$K14,rastreabilidade!$N:$N,$AM14),0)) -IF($L14="",0,IFERROR(SUMIFS(INDEX(rastreabilidade!$F:$H,0,MATCH(G$3,rastreabilidade!$F$1:$H$1,0)),rastreabilidade!$M:$M,$L14,rastreabilidade!$N:$N,$AM14),0)) -IF($M14="",0,IFERROR(SUMIFS(INDEX(rastreabilidade!$F:$H,0,MATCH(G$3,rastreabilidade!$F$1:$H$1,0)),rastreabilidade!$M:$M,$M14,rastreabilidade!$N:$N,$AM14),0)) -> 0 | I14: {=_xlfn.LET( _xlpm.mem,H14, _xlpm.retiradas,J14:M14, _xlpm.adicoes,N14:Q14, _xlpm.memAjustada,_xlfn.REDUCE(_xlpm.mem,_xlpm.retiradas,_xlfn.LAMBDA(_xlpm.x,_xlpm.y,IF(_xlpm.y<>"",SUBSTITUTE(_xlpm.x," + ("&_xlpm.y&")",""),_xlpm.x))), _xlpm.memRemovida,_xlfn.REDUCE(_xlpm.memAjustada,_xlpm.retiradas,_xlfn.LAMBDA(_xlpm.x,_xlpm.y,IF(_xlpm.y<>"",SUBSTITUTE(_xlpm.x,"("&_xlpm.y&")",""),_xlpm.x))), _xlpm.memSemSinal,IF(OR(LEFT(_xlpm.memRemovida,3)=" + ",LEFT(_xlpm.memRemovida,3)=" - "),MID(_xlpm.memRemovida,4,LEN(_xlpm.memRemovida)),_xlpm.memRemovida), _xlpm.memFinal,IF(OR(RIGHT(_xlpm.memSemSinal,3)=" + ",RIGHT(_xlpm.memSemSinal,3)=" - "),LEFT(_xlpm.memSemSinal,LEN(_xlpm.memSemSinal)-3),_xlpm.memSemSinal), _xlpm.adicoesTxt,_xlfn.TEXTJOIN(" + ",TRUE,IF(_xlpm.adicoes<>"","("&_xlpm.adicoes&")","")), IF(_xlpm.memFinal="",_xlpm.adicoesTxt,IF(_xlpm.adicoesTxt="",_xlpm.memFinal,_xlpm.memFinal&" + "&_xlpm.adicoesTxt)) )} | S14: +/-Provisões Operacionais | T14: =IFERROR(SUMIFS(INDEX(rastreabilidade!$F:$H,0,MATCH($T$2,rastreabilidade!$F$1:$H$1,0)),rastreabilidade!$K:$K,$S14,rastreabilidade!$D:$D,"Sim"),0) -> 0 | W14: =IFERROR(SUMIFS(INDEX(rastreabilidade!$F:$H,0,MATCH(W$3,rastreabilidade!$F$1:$H$1,0)),rastreabilidade!$N:$N,$AN14),0)*IF($AB14="sim",-1,1) +IF($AG14="",0,IFERROR(SUMIFS(INDEX(rastreabilidade!$F:$H,0,MATCH(W$3,rastreabilidade!$F$1:$H$1,0)),rastreabilidade!$M:$M,$AG14),0)) +IF($AH14="",0,IFERROR(SUMIFS(INDEX(rastreabilidade!$F:$H,0,MATCH(W$3,rastreabilidade!$F$1:$H$1,0)),rastreabilidade!$M:$M,$AH14),0)) +IF($AI14="",0,IFERROR(SUMIFS(INDEX(rastreabilidade!$F:$H,0,MATCH(W$3,rastreabilidade!$F$1:$H$1,0)),rastreabilidade!$M:$M,$AI14),0)) +IF($AJ14="",0,IFERROR(SUMIFS(INDEX(rastreabilidade!$F:$H,0,MATCH(W$3,rastreabilidade!$F$1:$H$1,0)),rastreabilidade!$M:$M,$AJ14),0)) -IF($AC14="",0,IFERROR(SUMIFS(INDEX(rastreabilidade!$F:$H,0,MATCH(W$3,rastreabilidade!$F$1:$H$1,0)),rastreabilidade!$M:$M,$AC14,rastreabilidade!$N:$N,$AN14),0)) -IF($AD14="",0,IFERROR(SUMIFS(INDEX(rastreabilidade!$F:$H,0,MATCH(W$3,rastreabilidade!$F$1:$H$1,0)),rastreabilidade!$M:$M,$AD14,rastreabilidade!$N:$N,$AN14),0)) -IF($AE14="",0,IFERROR(SUMIFS(INDEX(rastreabilidade!$F:$H,0,MATCH(W$3,rastreabilidade!$F$1:$H$1,0)),rastreabilidade!$M:$M,$AE14,rastreabilidade!$N:$N,$AN14),0)) -IF($AF14="",0,IFERROR(SUMIFS(INDEX(rastreabilidade!$F:$H,0,MATCH(W$3,rastreabilidade!$F$1:$H$1,0)),rastreabilidade!$M:$M,$AF14,rastreabilidade!$N:$N,$AN14),0)) -> 0 | X14: =IFERROR(SUMIFS(INDEX(rastreabilidade!$F:$H,0,MATCH(X$3,rastreabilidade!$F$1:$H$1,0)),rastreabilidade!$N:$N,$AN14),0)*IF($AB14="sim",-1,1) +IF($AG14="",0,IFERROR(SUMIFS(INDEX(rastreabilidade!$F:$H,0,MATCH(X$3,rastreabilidade!$F$1:$H$1,0)),rastreabilidade!$M:$M,$AG14),0)) +IF($AH14="",0,IFERROR(SUMIFS(INDEX(rastreabilidade!$F:$H,0,MATCH(X$3,rastreabilidade!$F$1:$H$1,0)),rastreabilidade!$M:$M,$AH14),0)) +IF($AI14="",0,IFERROR(SUMIFS(INDEX(rastreabilidade!$F:$H,0,MATCH(X$3,rastreabilidade!$F$1:$H$1,0)),rastreabilidade!$M:$M,$AI14),0)) +IF($AJ14="",0,IFERROR(SUMIFS(INDEX(rastreabilidade!$F:$H,0,MATCH(X$3,rastreabilidade!$F$1:$H$1,0)),rastreabilidade!$M:$M,$AJ14),0)) -IF($AC14="",0,IFERROR(SUMIFS(INDEX(rastreabilidade!$F:$H,0,MATCH(X$3,rastreabilidade!$F$1:$H$1,0)),rastreabilidade!$M:$M,$AC14,rastreabilidade!$N:$N,$AN14),0)) -IF($AD14="",0,IFERROR(SUMIFS(INDEX(rastreabilidade!$F:$H,0,MATCH(X$3,rastreabilidade!$F$1:$H$1,0)),rastreabilidade!$M:$M,$AD14,rastreabilidade!$N:$N,$AN14),0)) -IF($AE14="",0,IFERROR(SUMIFS(INDEX(rastreabilidade!$F:$H,0,MATCH(X$3,rastreabilidade!$F$1:$H$1,0)),rastreabilidade!$M:$M,$AE14,rastreabilidade!$N:$N,$AN14),0)) -IF($AF14="",0,IFERROR(SUMIFS(INDEX(rastreabilidade!$F:$H,0,MATCH(X$3,rastreabilidade!$F$1:$H$1,0)),rastreabilidade!$M:$M,$AF14,rastreabilidade!$N:$N,$AN14),0)) -> 0 | Y14: =IFERROR(SUMIFS(INDEX(rastreabilidade!$F:$H,0,MATCH(Y$3,rastreabilidade!$F$1:$H$1,0)),rastreabilidade!$N:$N,$AN14),0)*IF($AB14="sim",-1,1) +IF($AG14="",0,IFERROR(SUMIFS(INDEX(rastreabilidade!$F:$H,0,MATCH(Y$3,rastreabilidade!$F$1:$H$1,0)),rastreabilidade!$M:$M,$AG14),0)) +IF($AH14="",0,IFERROR(SUMIFS(INDEX(rastreabilidade!$F:$H,0,MATCH(Y$3,rastreabilidade!$F$1:$H$1,0)),rastreabilidade!$M:$M,$AH14),0)) +IF($AI14="",0,IFERROR(SUMIFS(INDEX(rastreabilidade!$F:$H,0,MATCH(Y$3,rastreabilidade!$F$1:$H$1,0)),rastreabilidade!$M:$M,$AI14),0)) +IF($AJ14="",0,IFERROR(SUMIFS(INDEX(rastreabilidade!$F:$H,0,MATCH(Y$3,rastreabilidade!$F$1:$H$1,0)),rastreabilidade!$M:$M,$AJ14),0)) -IF($AC14="",0,IFERROR(SUMIFS(INDEX(rastreabilidade!$F:$H,0,MATCH(Y$3,rastreabilidade!$F$1:$H$1,0)),rastreabilidade!$M:$M,$AC14,rastreabilidade!$N:$N,$AN14),0)) -IF($AD14="",0,IFERROR(SUMIFS(INDEX(rastreabilidade!$F:$H,0,MATCH(Y$3,rastreabilidade!$F$1:$H$1,0)),rastreabilidade!$M:$M,$AD14,rastreabilidade!$N:$N,$AN14),0)) -IF($AE14="",0,IFERROR(SUMIFS(INDEX(rastreabilidade!$F:$H,0,MATCH(Y$3,rastreabilidade!$F$1:$H$1,0)),rastreabilidade!$M:$M,$AE14,rastreabilidade!$N:$N,$AN14),0)) -IF($AF14="",0,IFERROR(SUMIFS(INDEX(rastreabilidade!$F:$H,0,MATCH(Y$3,rastreabilidade!$F$1:$H$1,0)),rastreabilidade!$M:$M,$AF14,rastreabilidade!$N:$N,$AN14),0)) -> 0 | AA14: {=_xlfn.LET( _xlpm.mem,Z14, _xlpm.retiradas,AC14:AF14, _xlpm.adicoes,AG14:AJ14, _xlpm.memAjustada,_xlfn.REDUCE(_xlpm.mem,_xlpm.retiradas,_xlfn.LAMBDA(_xlpm.x,_xlpm.y,IF(_xlpm.y<>"",SUBSTITUTE(_xlpm.x," + ("&_xlpm.y&")",""),_xlpm.x))), _xlpm.memRemovida,_xlfn.REDUCE(_xlpm.memAjustada,_xlpm.retiradas,_xlfn.LAMBDA(_xlpm.x,_xlpm.y,IF(_xlpm.y<>"",SUBSTITUTE(_xlpm.x,"("&_xlpm.y&")",""),_xlpm.x))), _xlpm.memSemSinal,IF(OR(LEFT(_xlpm.memRemovida,3)=" + ",LEFT(_xlpm.memRemovida,3)=" - "),MID(_xlpm.memRemovida,4,LEN(_xlpm.memRemovida)),_xlpm.memRemovida), _xlpm.memFinal,IF(OR(RIGHT(_xlpm.memSemSinal,3)=" + ",RIGHT(_xlpm.memSemSinal,3)=" - "),LEFT(_xlpm.memSemSinal,LEN(_xlpm.memSemSinal)-3),_xlpm.memSemSinal), _xlpm.adicoesTxt,_xlfn.TEXTJOIN(" + ",TRUE,IF(_xlpm.adicoes<>"","("&_xlpm.adicoes&")","")), IF(_xlpm.memFinal="",_xlpm.adicoesTxt,IF(_xlpm.adicoesTxt="",_xlpm.memFinal,_xlpm.memFinal&" + "&_xlpm.adicoesTxt)) )} | AM14: =_xlfn.TEXTJOIN("|",TRUE,A14,"Ativo","Circulante") -> Produtos Acabados|Ativo|Circulante | AN14: =_xlfn.CONCAT(S14,"|","DRE","|","DRE",) -> +/-Provisões Operacionais|DRE|DRE
A15: Estoques | B15: =+B12+B13+B14 -> 0 | E15: =+E12+E13+E14 -> 0 | F15: =+F12+F13+F14 -> 0 | G15: =+G12+G13+G14 -> 0 | J15: =+J12+J13+J14 -> 0 | Q15: =+Q12+Q13+Q14 -> 0 | S15: Resultado Operacional (EBIT) | T15: =SUM(T12:T14) -> 0 | W15: =SUM(W12:W14) -> 0 | X15: =SUM(X12:X14) -> 0 | Y15: =SUM(Y12:Y14) -> 0 | AM15: =_xlfn.TEXTJOIN("|",TRUE,A15,"Ativo","Circulante") -> Estoques|Ativo|Circulante | AN15: =_xlfn.CONCAT(S15,"|","DRE","|","DRE",) -> Resultado Operacional (EBIT)|DRE|DRE
A16: Ajustes derivativos / cambio (AC) | B16: =IFERROR(SUMIFS(INDEX(rastreabilidade!$F:$H,0,MATCH($B$2,rastreabilidade!$F$1:$H$1,0)),rastreabilidade!$K:$K,$A16,rastreabilidade!$D:$D,"Sim"),0) -> 0 | E16: =IFERROR(SUMIFS(INDEX(rastreabilidade!$F:$H,0,MATCH(E$3,rastreabilidade!$F$1:$H$1,0)),rastreabilidade!$N:$N,$AM16),0) +IF($N16="",0,IFERROR(SUMIFS(INDEX(rastreabilidade!$F:$H,0,MATCH(E$3,rastreabilidade!$F$1:$H$1,0)),rastreabilidade!$M:$M,$N16),0)) +IF($O16="",0,IFERROR(SUMIFS(INDEX(rastreabilidade!$F:$H,0,MATCH(E$3,rastreabilidade!$F$1:$H$1,0)),rastreabilidade!$M:$M,$O16),0)) +IF($P16="",0,IFERROR(SUMIFS(INDEX(rastreabilidade!$F:$H,0,MATCH(E$3,rastreabilidade!$F$1:$H$1,0)),rastreabilidade!$M:$M,$P16),0)) +IF($Q16="",0,IFERROR(SUMIFS(INDEX(rastreabilidade!$F:$H,0,MATCH(E$3,rastreabilidade!$F$1:$H$1,0)),rastreabilidade!$M:$M,$Q16),0)) -IF($J16="",0,IFERROR(SUMIFS(INDEX(rastreabilidade!$F:$H,0,MATCH(E$3,rastreabilidade!$F$1:$H$1,0)),rastreabilidade!$M:$M,$J16,rastreabilidade!$N:$N,$AM16),0)) -IF($K16="",0,IFERROR(SUMIFS(INDEX(rastreabilidade!$F:$H,0,MATCH(E$3,rastreabilidade!$F$1:$H$1,0)),rastreabilidade!$M:$M,$K16,rastreabilidade!$N:$N,$AM16),0)) -IF($L16="",0,IFERROR(SUMIFS(INDEX(rastreabilidade!$F:$H,0,MATCH(E$3,rastreabilidade!$F$1:$H$1,0)),rastreabilidade!$M:$M,$L16,rastreabilidade!$N:$N,$AM16),0)) -IF($M16="",0,IFERROR(SUMIFS(INDEX(rastreabilidade!$F:$H,0,MATCH(E$3,rastreabilidade!$F$1:$H$1,0)),rastreabilidade!$M:$M,$M16,rastreabilidade!$N:$N,$AM16),0)) -> 0 | F16: =IFERROR(SUMIFS(INDEX(rastreabilidade!$F:$H,0,MATCH(F$3,rastreabilidade!$F$1:$H$1,0)),rastreabilidade!$N:$N,$AM16),0) +IF($N16="",0,IFERROR(SUMIFS(INDEX(rastreabilidade!$F:$H,0,MATCH(F$3,rastreabilidade!$F$1:$H$1,0)),rastreabilidade!$M:$M,$N16),0)) +IF($O16="",0,IFERROR(SUMIFS(INDEX(rastreabilidade!$F:$H,0,MATCH(F$3,rastreabilidade!$F$1:$H$1,0)),rastreabilidade!$M:$M,$O16),0)) +IF($P16="",0,IFERROR(SUMIFS(INDEX(rastreabilidade!$F:$H,0,MATCH(F$3,rastreabilidade!$F$1:$H$1,0)),rastreabilidade!$M:$M,$P16),0)) +IF($Q16="",0,IFERROR(SUMIFS(INDEX(rastreabilidade!$F:$H,0,MATCH(F$3,rastreabilidade!$F$1:$H$1,0)),rastreabilidade!$M:$M,$Q16),0)) -IF($J16="",0,IFERROR(SUMIFS(INDEX(rastreabilidade!$F:$H,0,MATCH(F$3,rastreabilidade!$F$1:$H$1,0)),rastreabilidade!$M:$M,$J16,rastreabilidade!$N:$N,$AM16),0)) -IF($K16="",0,IFERROR(SUMIFS(INDEX(rastreabilidade!$F:$H,0,MATCH(F$3,rastreabilidade!$F$1:$H$1,0)),rastreabilidade!$M:$M,$K16,rastreabilidade!$N:$N,$AM16),0)) -IF($L16="",0,IFERROR(SUMIFS(INDEX(rastreabilidade!$F:$H,0,MATCH(F$3,rastreabilidade!$F$1:$H$1,0)),rastreabilidade!$M:$M,$L16,rastreabilidade!$N:$N,$AM16),0)) -IF($M16="",0,IFERROR(SUMIFS(INDEX(rastreabilidade!$F:$H,0,MATCH(F$3,rastreabilidade!$F$1:$H$1,0)),rastreabilidade!$M:$M,$M16,rastreabilidade!$N:$N,$AM16),0)) -> 0 | G16: =IFERROR(SUMIFS(INDEX(rastreabilidade!$F:$H,0,MATCH(G$3,rastreabilidade!$F$1:$H$1,0)),rastreabilidade!$N:$N,$AM16),0) +IF($N16="",0,IFERROR(SUMIFS(INDEX(rastreabilidade!$F:$H,0,MATCH(G$3,rastreabilidade!$F$1:$H$1,0)),rastreabilidade!$M:$M,$N16),0)) +IF($O16="",0,IFERROR(SUMIFS(INDEX(rastreabilidade!$F:$H,0,MATCH(G$3,rastreabilidade!$F$1:$H$1,0)),rastreabilidade!$M:$M,$O16),0)) +IF($P16="",0,IFERROR(SUMIFS(INDEX(rastreabilidade!$F:$H,0,MATCH(G$3,rastreabilidade!$F$1:$H$1,0)),rastreabilidade!$M:$M,$P16),0)) +IF($Q16="",0,IFERROR(SUMIFS(INDEX(rastreabilidade!$F:$H,0,MATCH(G$3,rastreabilidade!$F$1:$H$1,0)),rastreabilidade!$M:$M,$Q16),0)) -IF($J16="",0,IFERROR(SUMIFS(INDEX(rastreabilidade!$F:$H,0,MATCH(G$3,rastreabilidade!$F$1:$H$1,0)),rastreabilidade!$M:$M,$J16,rastreabilidade!$N:$N,$AM16),0)) -IF($K16="",0,IFERROR(SUMIFS(INDEX(rastreabilidade!$F:$H,0,MATCH(G$3,rastreabilidade!$F$1:$H$1,0)),rastreabilidade!$M:$M,$K16,rastreabilidade!$N:$N,$AM16),0)) -IF($L16="",0,IFERROR(SUMIFS(INDEX(rastreabilidade!$F:$H,0,MATCH(G$3,rastreabilidade!$F$1:$H$1,0)),rastreabilidade!$M:$M,$L16,rastreabilidade!$N:$N,$AM16),0)) -IF($M16="",0,IFERROR(SUMIFS(INDEX(rastreabilidade!$F:$H,0,MATCH(G$3,rastreabilidade!$F$1:$H$1,0)),rastreabilidade!$M:$M,$M16,rastreabilidade!$N:$N,$AM16),0)) -> 0 | I16: {=_xlfn.LET( _xlpm.mem,H16, _xlpm.retiradas,J16:M16, _xlpm.adicoes,N16:Q16, _xlpm.memAjustada,_xlfn.REDUCE(_xlpm.mem,_xlpm.retiradas,_xlfn.LAMBDA(_xlpm.x,_xlpm.y,IF(_xlpm.y<>"",SUBSTITUTE(_xlpm.x," + ("&_xlpm.y&")",""),_xlpm.x))), _xlpm.memRemovida,_xlfn.REDUCE(_xlpm.memAjustada,_xlpm.retiradas,_xlfn.LAMBDA(_xlpm.x,_xlpm.y,IF(_xlpm.y<>"",SUBSTITUTE(_xlpm.x,"("&_xlpm.y&")",""),_xlpm.x))), _xlpm.memSemSinal,IF(OR(LEFT(_xlpm.memRemovida,3)=" + ",LEFT(_xlpm.memRemovida,3)=" - "),MID(_xlpm.memRemovida,4,LEN(_xlpm.memRemovida)),_xlpm.memRemovida), _xlpm.memFinal,IF(OR(RIGHT(_xlpm.memSemSinal,3)=" + ",RIGHT(_xlpm.memSemSinal,3)=" - "),LEFT(_xlpm.memSemSinal,LEN(_xlpm.memSemSinal)-3),_xlpm.memSemSinal), _xlpm.adicoesTxt,_xlfn.TEXTJOIN(" + ",TRUE,IF(_xlpm.adicoes<>"","("&_xlpm.adicoes&")","")), IF(_xlpm.memFinal="",_xlpm.adicoesTxt,IF(_xlpm.adicoesTxt="",_xlpm.memFinal,_xlpm.memFinal&" + "&_xlpm.adicoesTxt)) )} | S16: - Depreciação e amortização (imob e intang) | T16: =IFERROR(SUMIFS(INDEX(rastreabilidade!$F:$H,0,MATCH($T$2,rastreabilidade!$F$1:$H$1,0)),rastreabilidade!$K:$K,$S16,rastreabilidade!$D:$D,"Sim"),0) -> 0 | W16: =IFERROR(SUMIFS(INDEX(rastreabilidade!$F:$H,0,MATCH(W$3,rastreabilidade!$F$1:$H$1,0)),rastreabilidade!$N:$N,$AN16),0)*IF($AB16="sim",-1,1) +IF($AG16="",0,IFERROR(SUMIFS(INDEX(rastreabilidade!$F:$H,0,MATCH(W$3,rastreabilidade!$F$1:$H$1,0)),rastreabilidade!$M:$M,$AG16),0)) +IF($AH16="",0,IFERROR(SUMIFS(INDEX(rastreabilidade!$F:$H,0,MATCH(W$3,rastreabilidade!$F$1:$H$1,0)),rastreabilidade!$M:$M,$AH16),0)) +IF($AI16="",0,IFERROR(SUMIFS(INDEX(rastreabilidade!$F:$H,0,MATCH(W$3,rastreabilidade!$F$1:$H$1,0)),rastreabilidade!$M:$M,$AI16),0)) +IF($AJ16="",0,IFERROR(SUMIFS(INDEX(rastreabilidade!$F:$H,0,MATCH(W$3,rastreabilidade!$F$1:$H$1,0)),rastreabilidade!$M:$M,$AJ16),0)) -IF($AC16="",0,IFERROR(SUMIFS(INDEX(rastreabilidade!$F:$H,0,MATCH(W$3,rastreabilidade!$F$1:$H$1,0)),rastreabilidade!$M:$M,$AC16,rastreabilidade!$N:$N,$AN16),0)) -IF($AD16="",0,IFERROR(SUMIFS(INDEX(rastreabilidade!$F:$H,0,MATCH(W$3,rastreabilidade!$F$1:$H$1,0)),rastreabilidade!$M:$M,$AD16,rastreabilidade!$N:$N,$AN16),0)) -IF($AE16="",0,IFERROR(SUMIFS(INDEX(rastreabilidade!$F:$H,0,MATCH(W$3,rastreabilidade!$F$1:$H$1,0)),rastreabilidade!$M:$M,$AE16,rastreabilidade!$N:$N,$AN16),0)) -IF($AF16="",0,IFERROR(SUMIFS(INDEX(rastreabilidade!$F:$H,0,MATCH(W$3,rastreabilidade!$F$1:$H$1,0)),rastreabilidade!$M:$M,$AF16,rastreabilidade!$N:$N,$AN16),0)) -> 0 | X16: =IFERROR(SUMIFS(INDEX(rastreabilidade!$F:$H,0,MATCH(X$3,rastreabilidade!$F$1:$H$1,0)),rastreabilidade!$N:$N,$AN16),0)*IF($AB16="sim",-1,1) +IF($AG16="",0,IFERROR(SUMIFS(INDEX(rastreabilidade!$F:$H,0,MATCH(X$3,rastreabilidade!$F$1:$H$1,0)),rastreabilidade!$M:$M,$AG16),0)) +IF($AH16="",0,IFERROR(SUMIFS(INDEX(rastreabilidade!$F:$H,0,MATCH(X$3,rastreabilidade!$F$1:$H$1,0)),rastreabilidade!$M:$M,$AH16),0)) +IF($AI16="",0,IFERROR(SUMIFS(INDEX(rastreabilidade!$F:$H,0,MATCH(X$3,rastreabilidade!$F$1:$H$1,0)),rastreabilidade!$M:$M,$AI16),0)) +IF($AJ16="",0,IFERROR(SUMIFS(INDEX(rastreabilidade!$F:$H,0,MATCH(X$3,rastreabilidade!$F$1:$H$1,0)),rastreabilidade!$M:$M,$AJ16),0)) -IF($AC16="",0,IFERROR(SUMIFS(INDEX(rastreabilidade!$F:$H,0,MATCH(X$3,rastreabilidade!$F$1:$H$1,0)),rastreabilidade!$M:$M,$AC16,rastreabilidade!$N:$N,$AN16),0)) -IF($AD16="",0,IFERROR(SUMIFS(INDEX(rastreabilidade!$F:$H,0,MATCH(X$3,rastreabilidade!$F$1:$H$1,0)),rastreabilidade!$M:$M,$AD16,rastreabilidade!$N:$N,$AN16),0)) -IF($AE16="",0,IFERROR(SUMIFS(INDEX(rastreabilidade!$F:$H,0,MATCH(X$3,rastreabilidade!$F$1:$H$1,0)),rastreabilidade!$M:$M,$AE16,rastreabilidade!$N:$N,$AN16),0)) -IF($AF16="",0,IFERROR(SUMIFS(INDEX(rastreabilidade!$F:$H,0,MATCH(X$3,rastreabilidade!$F$1:$H$1,0)),rastreabilidade!$M:$M,$AF16,rastreabilidade!$N:$N,$AN16),0)) -> 0 | Y16: =IFERROR(SUMIFS(INDEX(rastreabilidade!$F:$H,0,MATCH(Y$3,rastreabilidade!$F$1:$H$1,0)),rastreabilidade!$N:$N,$AN16),0)*IF($AB16="sim",-1,1) +IF($AG16="",0,IFERROR(SUMIFS(INDEX(rastreabilidade!$F:$H,0,MATCH(Y$3,rastreabilidade!$F$1:$H$1,0)),rastreabilidade!$M:$M,$AG16),0)) +IF($AH16="",0,IFERROR(SUMIFS(INDEX(rastreabilidade!$F:$H,0,MATCH(Y$3,rastreabilidade!$F$1:$H$1,0)),rastreabilidade!$M:$M,$AH16),0)) +IF($AI16="",0,IFERROR(SUMIFS(INDEX(rastreabilidade!$F:$H,0,MATCH(Y$3,rastreabilidade!$F$1:$H$1,0)),rastreabilidade!$M:$M,$AI16),0)) +IF($AJ16="",0,IFERROR(SUMIFS(INDEX(rastreabilidade!$F:$H,0,MATCH(Y$3,rastreabilidade!$F$1:$H$1,0)),rastreabilidade!$M:$M,$AJ16),0)) -IF($AC16="",0,IFERROR(SUMIFS(INDEX(rastreabilidade!$F:$H,0,MATCH(Y$3,rastreabilidade!$F$1:$H$1,0)),rastreabilidade!$M:$M,$AC16,rastreabilidade!$N:$N,$AN16),0)) -IF($AD16="",0,IFERROR(SUMIFS(INDEX(rastreabilidade!$F:$H,0,MATCH(Y$3,rastreabilidade!$F$1:$H$1,0)),rastreabilidade!$M:$M,$AD16,rastreabilidade!$N:$N,$AN16),0)) -IF($AE16="",0,IFERROR(SUMIFS(INDEX(rastreabilidade!$F:$H,0,MATCH(Y$3,rastreabilidade!$F$1:$H$1,0)),rastreabilidade!$M:$M,$AE16,rastreabilidade!$N:$N,$AN16),0)) -IF($AF16="",0,IFERROR(SUMIFS(INDEX(rastreabilidade!$F:$H,0,MATCH(Y$3,rastreabilidade!$F$1:$H$1,0)),rastreabilidade!$M:$M,$AF16,rastreabilidade!$N:$N,$AN16),0)) -> 0 | AA16: {=_xlfn.LET( _xlpm.mem,Z16, _xlpm.retiradas,AC16:AF16, _xlpm.adicoes,AG16:AJ16, _xlpm.memAjustada,_xlfn.REDUCE(_xlpm.mem,_xlpm.retiradas,_xlfn.LAMBDA(_xlpm.x,_xlpm.y,IF(_xlpm.y<>"",SUBSTITUTE(_xlpm.x," + ("&_xlpm.y&")",""),_xlpm.x))), _xlpm.memRemovida,_xlfn.REDUCE(_xlpm.memAjustada,_xlpm.retiradas,_xlfn.LAMBDA(_xlpm.x,_xlpm.y,IF(_xlpm.y<>"",SUBSTITUTE(_xlpm.x,"("&_xlpm.y&")",""),_xlpm.x))), _xlpm.memSemSinal,IF(OR(LEFT(_xlpm.memRemovida,3)=" + ",LEFT(_xlpm.memRemovida,3)=" - "),MID(_xlpm.memRemovida,4,LEN(_xlpm.memRemovida)),_xlpm.memRemovida), _xlpm.memFinal,IF(OR(RIGHT(_xlpm.memSemSinal,3)=" + ",RIGHT(_xlpm.memSemSinal,3)=" - "),LEFT(_xlpm.memSemSinal,LEN(_xlpm.memSemSinal)-3),_xlpm.memSemSinal), _xlpm.adicoesTxt,_xlfn.TEXTJOIN(" + ",TRUE,IF(_xlpm.adicoes<>"","("&_xlpm.adicoes&")","")), IF(_xlpm.memFinal="",_xlpm.adicoesTxt,IF(_xlpm.adicoesTxt="",_xlpm.memFinal,_xlpm.memFinal&" + "&_xlpm.adicoesTxt)) )} | AM16: =_xlfn.TEXTJOIN("|",TRUE,A16,"Ativo","Circulante") -> Ajustes derivativos / cambio (AC)|Ativo|Circulante | AN16: =_xlfn.CONCAT(S16,"|","DRE","|","DRE",) -> - Depreciação e amortização (imob e intang)|DRE|DRE
A17: Adiantamento a Fornecedores | B17: =IFERROR(SUMIFS(INDEX(rastreabilidade!$F:$H,0,MATCH($B$2,rastreabilidade!$F$1:$H$1,0)),rastreabilidade!$K:$K,$A17,rastreabilidade!$D:$D,"Sim"),0) -> 0 | E17: =IFERROR(SUMIFS(INDEX(rastreabilidade!$F:$H,0,MATCH(E$3,rastreabilidade!$F$1:$H$1,0)),rastreabilidade!$N:$N,$AM17),0) +IF($N17="",0,IFERROR(SUMIFS(INDEX(rastreabilidade!$F:$H,0,MATCH(E$3,rastreabilidade!$F$1:$H$1,0)),rastreabilidade!$M:$M,$N17),0)) +IF($O17="",0,IFERROR(SUMIFS(INDEX(rastreabilidade!$F:$H,0,MATCH(E$3,rastreabilidade!$F$1:$H$1,0)),rastreabilidade!$M:$M,$O17),0)) +IF($P17="",0,IFERROR(SUMIFS(INDEX(rastreabilidade!$F:$H,0,MATCH(E$3,rastreabilidade!$F$1:$H$1,0)),rastreabilidade!$M:$M,$P17),0)) +IF($Q17="",0,IFERROR(SUMIFS(INDEX(rastreabilidade!$F:$H,0,MATCH(E$3,rastreabilidade!$F$1:$H$1,0)),rastreabilidade!$M:$M,$Q17),0)) -IF($J17="",0,IFERROR(SUMIFS(INDEX(rastreabilidade!$F:$H,0,MATCH(E$3,rastreabilidade!$F$1:$H$1,0)),rastreabilidade!$M:$M,$J17,rastreabilidade!$N:$N,$AM17),0)) -IF($K17="",0,IFERROR(SUMIFS(INDEX(rastreabilidade!$F:$H,0,MATCH(E$3,rastreabilidade!$F$1:$H$1,0)),rastreabilidade!$M:$M,$K17,rastreabilidade!$N:$N,$AM17),0)) -IF($L17="",0,IFERROR(SUMIFS(INDEX(rastreabilidade!$F:$H,0,MATCH(E$3,rastreabilidade!$F$1:$H$1,0)),rastreabilidade!$M:$M,$L17,rastreabilidade!$N:$N,$AM17),0)) -IF($M17="",0,IFERROR(SUMIFS(INDEX(rastreabilidade!$F:$H,0,MATCH(E$3,rastreabilidade!$F$1:$H$1,0)),rastreabilidade!$M:$M,$M17,rastreabilidade!$N:$N,$AM17),0)) -> 0 | F17: =IFERROR(SUMIFS(INDEX(rastreabilidade!$F:$H,0,MATCH(F$3,rastreabilidade!$F$1:$H$1,0)),rastreabilidade!$N:$N,$AM17),0) +IF($N17="",0,IFERROR(SUMIFS(INDEX(rastreabilidade!$F:$H,0,MATCH(F$3,rastreabilidade!$F$1:$H$1,0)),rastreabilidade!$M:$M,$N17),0)) +IF($O17="",0,IFERROR(SUMIFS(INDEX(rastreabilidade!$F:$H,0,MATCH(F$3,rastreabilidade!$F$1:$H$1,0)),rastreabilidade!$M:$M,$O17),0)) +IF($P17="",0,IFERROR(SUMIFS(INDEX(rastreabilidade!$F:$H,0,MATCH(F$3,rastreabilidade!$F$1:$H$1,0)),rastreabilidade!$M:$M,$P17),0)) +IF($Q17="",0,IFERROR(SUMIFS(INDEX(rastreabilidade!$F:$H,0,MATCH(F$3,rastreabilidade!$F$1:$H$1,0)),rastreabilidade!$M:$M,$Q17),0)) -IF($J17="",0,IFERROR(SUMIFS(INDEX(rastreabilidade!$F:$H,0,MATCH(F$3,rastreabilidade!$F$1:$H$1,0)),rastreabilidade!$M:$M,$J17,rastreabilidade!$N:$N,$AM17),0)) -IF($K17="",0,IFERROR(SUMIFS(INDEX(rastreabilidade!$F:$H,0,MATCH(F$3,rastreabilidade!$F$1:$H$1,0)),rastreabilidade!$M:$M,$K17,rastreabilidade!$N:$N,$AM17),0)) -IF($L17="",0,IFERROR(SUMIFS(INDEX(rastreabilidade!$F:$H,0,MATCH(F$3,rastreabilidade!$F$1:$H$1,0)),rastreabilidade!$M:$M,$L17,rastreabilidade!$N:$N,$AM17),0)) -IF($M17="",0,IFERROR(SUMIFS(INDEX(rastreabilidade!$F:$H,0,MATCH(F$3,rastreabilidade!$F$1:$H$1,0)),rastreabilidade!$M:$M,$M17,rastreabilidade!$N:$N,$AM17),0)) -> 0 | G17: =IFERROR(SUMIFS(INDEX(rastreabilidade!$F:$H,0,MATCH(G$3,rastreabilidade!$F$1:$H$1,0)),rastreabilidade!$N:$N,$AM17),0) +IF($N17="",0,IFERROR(SUMIFS(INDEX(rastreabilidade!$F:$H,0,MATCH(G$3,rastreabilidade!$F$1:$H$1,0)),rastreabilidade!$M:$M,$N17),0)) +IF($O17="",0,IFERROR(SUMIFS(INDEX(rastreabilidade!$F:$H,0,MATCH(G$3,rastreabilidade!$F$1:$H$1,0)),rastreabilidade!$M:$M,$O17),0)) +IF($P17="",0,IFERROR(SUMIFS(INDEX(rastreabilidade!$F:$H,0,MATCH(G$3,rastreabilidade!$F$1:$H$1,0)),rastreabilidade!$M:$M,$P17),0)) +IF($Q17="",0,IFERROR(SUMIFS(INDEX(rastreabilidade!$F:$H,0,MATCH(G$3,rastreabilidade!$F$1:$H$1,0)),rastreabilidade!$M:$M,$Q17),0)) -IF($J17="",0,IFERROR(SUMIFS(INDEX(rastreabilidade!$F:$H,0,MATCH(G$3,rastreabilidade!$F$1:$H$1,0)),rastreabilidade!$M:$M,$J17,rastreabilidade!$N:$N,$AM17),0)) -IF($K17="",0,IFERROR(SUMIFS(INDEX(rastreabilidade!$F:$H,0,MATCH(G$3,rastreabilidade!$F$1:$H$1,0)),rastreabilidade!$M:$M,$K17,rastreabilidade!$N:$N,$AM17),0)) -IF($L17="",0,IFERROR(SUMIFS(INDEX(rastreabilidade!$F:$H,0,MATCH(G$3,rastreabilidade!$F$1:$H$1,0)),rastreabilidade!$M:$M,$L17,rastreabilidade!$N:$N,$AM17),0)) -IF($M17="",0,IFERROR(SUMIFS(INDEX(rastreabilidade!$F:$H,0,MATCH(G$3,rastreabilidade!$F$1:$H$1,0)),rastreabilidade!$M:$M,$M17,rastreabilidade!$N:$N,$AM17),0)) -> 0 | I17: {=_xlfn.LET( _xlpm.mem,H17, _xlpm.retiradas,J17:M17, _xlpm.adicoes,N17:Q17, _xlpm.memAjustada,_xlfn.REDUCE(_xlpm.mem,_xlpm.retiradas,_xlfn.LAMBDA(_xlpm.x,_xlpm.y,IF(_xlpm.y<>"",SUBSTITUTE(_xlpm.x," + ("&_xlpm.y&")",""),_xlpm.x))), _xlpm.memRemovida,_xlfn.REDUCE(_xlpm.memAjustada,_xlpm.retiradas,_xlfn.LAMBDA(_xlpm.x,_xlpm.y,IF(_xlpm.y<>"",SUBSTITUTE(_xlpm.x,"("&_xlpm.y&")",""),_xlpm.x))), _xlpm.memSemSinal,IF(OR(LEFT(_xlpm.memRemovida,3)=" + ",LEFT(_xlpm.memRemovida,3)=" - "),MID(_xlpm.memRemovida,4,LEN(_xlpm.memRemovida)),_xlpm.memRemovida), _xlpm.memFinal,IF(OR(RIGHT(_xlpm.memSemSinal,3)=" + ",RIGHT(_xlpm.memSemSinal,3)=" - "),LEFT(_xlpm.memSemSinal,LEN(_xlpm.memSemSinal)-3),_xlpm.memSemSinal), _xlpm.adicoesTxt,_xlfn.TEXTJOIN(" + ",TRUE,IF(_xlpm.adicoes<>"","("&_xlpm.adicoes&")","")), IF(_xlpm.memFinal="",_xlpm.adicoesTxt,IF(_xlpm.adicoesTxt="",_xlpm.memFinal,_xlpm.memFinal&" + "&_xlpm.adicoesTxt)) )} | S17: - Depreciação/Amortização dos Arrendamentos Op. | T17: =IFERROR(SUMIFS(INDEX(rastreabilidade!$F:$H,0,MATCH($T$2,rastreabilidade!$F$1:$H$1,0)),rastreabilidade!$K:$K,$S17,rastreabilidade!$D:$D,"Sim"),0) -> 0 | W17: =IFERROR(SUMIFS(INDEX(rastreabilidade!$F:$H,0,MATCH(W$3,rastreabilidade!$F$1:$H$1,0)),rastreabilidade!$N:$N,$AN17),0)*IF($AB17="sim",-1,1) +IF($AG17="",0,IFERROR(SUMIFS(INDEX(rastreabilidade!$F:$H,0,MATCH(W$3,rastreabilidade!$F$1:$H$1,0)),rastreabilidade!$M:$M,$AG17),0)) +IF($AH17="",0,IFERROR(SUMIFS(INDEX(rastreabilidade!$F:$H,0,MATCH(W$3,rastreabilidade!$F$1:$H$1,0)),rastreabilidade!$M:$M,$AH17),0)) +IF($AI17="",0,IFERROR(SUMIFS(INDEX(rastreabilidade!$F:$H,0,MATCH(W$3,rastreabilidade!$F$1:$H$1,0)),rastreabilidade!$M:$M,$AI17),0)) +IF($AJ17="",0,IFERROR(SUMIFS(INDEX(rastreabilidade!$F:$H,0,MATCH(W$3,rastreabilidade!$F$1:$H$1,0)),rastreabilidade!$M:$M,$AJ17),0)) -IF($AC17="",0,IFERROR(SUMIFS(INDEX(rastreabilidade!$F:$H,0,MATCH(W$3,rastreabilidade!$F$1:$H$1,0)),rastreabilidade!$M:$M,$AC17,rastreabilidade!$N:$N,$AN17),0)) -IF($AD17="",0,IFERROR(SUMIFS(INDEX(rastreabilidade!$F:$H,0,MATCH(W$3,rastreabilidade!$F$1:$H$1,0)),rastreabilidade!$M:$M,$AD17,rastreabilidade!$N:$N,$AN17),0)) -IF($AE17="",0,IFERROR(SUMIFS(INDEX(rastreabilidade!$F:$H,0,MATCH(W$3,rastreabilidade!$F$1:$H$1,0)),rastreabilidade!$M:$M,$AE17,rastreabilidade!$N:$N,$AN17),0)) -IF($AF17="",0,IFERROR(SUMIFS(INDEX(rastreabilidade!$F:$H,0,MATCH(W$3,rastreabilidade!$F$1:$H$1,0)),rastreabilidade!$M:$M,$AF17,rastreabilidade!$N:$N,$AN17),0)) -> 0 | X17: =IFERROR(SUMIFS(INDEX(rastreabilidade!$F:$H,0,MATCH(X$3,rastreabilidade!$F$1:$H$1,0)),rastreabilidade!$N:$N,$AN17),0)*IF($AB17="sim",-1,1) +IF($AG17="",0,IFERROR(SUMIFS(INDEX(rastreabilidade!$F:$H,0,MATCH(X$3,rastreabilidade!$F$1:$H$1,0)),rastreabilidade!$M:$M,$AG17),0)) +IF($AH17="",0,IFERROR(SUMIFS(INDEX(rastreabilidade!$F:$H,0,MATCH(X$3,rastreabilidade!$F$1:$H$1,0)),rastreabilidade!$M:$M,$AH17),0)) +IF($AI17="",0,IFERROR(SUMIFS(INDEX(rastreabilidade!$F:$H,0,MATCH(X$3,rastreabilidade!$F$1:$H$1,0)),rastreabilidade!$M:$M,$AI17),0)) +IF($AJ17="",0,IFERROR(SUMIFS(INDEX(rastreabilidade!$F:$H,0,MATCH(X$3,rastreabilidade!$F$1:$H$1,0)),rastreabilidade!$M:$M,$AJ17),0)) -IF($AC17="",0,IFERROR(SUMIFS(INDEX(rastreabilidade!$F:$H,0,MATCH(X$3,rastreabilidade!$F$1:$H$1,0)),rastreabilidade!$M:$M,$AC17,rastreabilidade!$N:$N,$AN17),0)) -IF($AD17="",0,IFERROR(SUMIFS(INDEX(rastreabilidade!$F:$H,0,MATCH(X$3,rastreabilidade!$F$1:$H$1,0)),rastreabilidade!$M:$M,$AD17,rastreabilidade!$N:$N,$AN17),0)) -IF($AE17="",0,IFERROR(SUMIFS(INDEX(rastreabilidade!$F:$H,0,MATCH(X$3,rastreabilidade!$F$1:$H$1,0)),rastreabilidade!$M:$M,$AE17,rastreabilidade!$N:$N,$AN17),0)) -IF($AF17="",0,IFERROR(SUMIFS(INDEX(rastreabilidade!$F:$H,0,MATCH(X$3,rastreabilidade!$F$1:$H$1,0)),rastreabilidade!$M:$M,$AF17,rastreabilidade!$N:$N,$AN17),0)) -> 0 | Y17: =IFERROR(SUMIFS(INDEX(rastreabilidade!$F:$H,0,MATCH(Y$3,rastreabilidade!$F$1:$H$1,0)),rastreabilidade!$N:$N,$AN17),0)*IF($AB17="sim",-1,1) +IF($AG17="",0,IFERROR(SUMIFS(INDEX(rastreabilidade!$F:$H,0,MATCH(Y$3,rastreabilidade!$F$1:$H$1,0)),rastreabilidade!$M:$M,$AG17),0)) +IF($AH17="",0,IFERROR(SUMIFS(INDEX(rastreabilidade!$F:$H,0,MATCH(Y$3,rastreabilidade!$F$1:$H$1,0)),rastreabilidade!$M:$M,$AH17),0)) +IF($AI17="",0,IFERROR(SUMIFS(INDEX(rastreabilidade!$F:$H,0,MATCH(Y$3,rastreabilidade!$F$1:$H$1,0)),rastreabilidade!$M:$M,$AI17),0)) +IF($AJ17="",0,IFERROR(SUMIFS(INDEX(rastreabilidade!$F:$H,0,MATCH(Y$3,rastreabilidade!$F$1:$H$1,0)),rastreabilidade!$M:$M,$AJ17),0)) -IF($AC17="",0,IFERROR(SUMIFS(INDEX(rastreabilidade!$F:$H,0,MATCH(Y$3,rastreabilidade!$F$1:$H$1,0)),rastreabilidade!$M:$M,$AC17,rastreabilidade!$N:$N,$AN17),0)) -IF($AD17="",0,IFERROR(SUMIFS(INDEX(rastreabilidade!$F:$H,0,MATCH(Y$3,rastreabilidade!$F$1:$H$1,0)),rastreabilidade!$M:$M,$AD17,rastreabilidade!$N:$N,$AN17),0)) -IF($AE17="",0,IFERROR(SUMIFS(INDEX(rastreabilidade!$F:$H,0,MATCH(Y$3,rastreabilidade!$F$1:$H$1,0)),rastreabilidade!$M:$M,$AE17,rastreabilidade!$N:$N,$AN17),0)) -IF($AF17="",0,IFERROR(SUMIFS(INDEX(rastreabilidade!$F:$H,0,MATCH(Y$3,rastreabilidade!$F$1:$H$1,0)),rastreabilidade!$M:$M,$AF17,rastreabilidade!$N:$N,$AN17),0)) -> 0 | AA17: {=_xlfn.LET( _xlpm.mem,Z17, _xlpm.retiradas,AC17:AF17, _xlpm.adicoes,AG17:AJ17, _xlpm.memAjustada,_xlfn.REDUCE(_xlpm.mem,_xlpm.retiradas,_xlfn.LAMBDA(_xlpm.x,_xlpm.y,IF(_xlpm.y<>"",SUBSTITUTE(_xlpm.x," + ("&_xlpm.y&")",""),_xlpm.x))), _xlpm.memRemovida,_xlfn.REDUCE(_xlpm.memAjustada,_xlpm.retiradas,_xlfn.LAMBDA(_xlpm.x,_xlpm.y,IF(_xlpm.y<>"",SUBSTITUTE(_xlpm.x,"("&_xlpm.y&")",""),_xlpm.x))), _xlpm.memSemSinal,IF(OR(LEFT(_xlpm.memRemovida,3)=" + ",LEFT(_xlpm.memRemovida,3)=" - "),MID(_xlpm.memRemovida,4,LEN(_xlpm.memRemovida)),_xlpm.memRemovida), _xlpm.memFinal,IF(OR(RIGHT(_xlpm.memSemSinal,3)=" + ",RIGHT(_xlpm.memSemSinal,3)=" - "),LEFT(_xlpm.memSemSinal,LEN(_xlpm.memSemSinal)-3),_xlpm.memSemSinal), _xlpm.adicoesTxt,_xlfn.TEXTJOIN(" + ",TRUE,IF(_xlpm.adicoes<>"","("&_xlpm.adicoes&")","")), IF(_xlpm.memFinal="",_xlpm.adicoesTxt,IF(_xlpm.adicoesTxt="",_xlpm.memFinal,_xlpm.memFinal&" + "&_xlpm.adicoesTxt)) )} | AM17: =_xlfn.TEXTJOIN("|",TRUE,A17,"Ativo","Circulante") -> Adiantamento a Fornecedores|Ativo|Circulante | AN17: =_xlfn.CONCAT(S17,"|","DRE","|","DRE",) -> - Depreciação/Amortização dos Arrendamentos Op.|DRE|DRE
A18: Mútuo Financeiro | B18: =IFERROR(SUMIFS(INDEX(rastreabilidade!$F:$H,0,MATCH($B$2,rastreabilidade!$F$1:$H$1,0)),rastreabilidade!$K:$K,$A18,rastreabilidade!$D:$D,"Sim"),0) -> 0 | E18: =IFERROR(SUMIFS(INDEX(rastreabilidade!$F:$H,0,MATCH(E$3,rastreabilidade!$F$1:$H$1,0)),rastreabilidade!$N:$N,$AM18),0) +IF($N18="",0,IFERROR(SUMIFS(INDEX(rastreabilidade!$F:$H,0,MATCH(E$3,rastreabilidade!$F$1:$H$1,0)),rastreabilidade!$M:$M,$N18),0)) +IF($O18="",0,IFERROR(SUMIFS(INDEX(rastreabilidade!$F:$H,0,MATCH(E$3,rastreabilidade!$F$1:$H$1,0)),rastreabilidade!$M:$M,$O18),0)) +IF($P18="",0,IFERROR(SUMIFS(INDEX(rastreabilidade!$F:$H,0,MATCH(E$3,rastreabilidade!$F$1:$H$1,0)),rastreabilidade!$M:$M,$P18),0)) +IF($Q18="",0,IFERROR(SUMIFS(INDEX(rastreabilidade!$F:$H,0,MATCH(E$3,rastreabilidade!$F$1:$H$1,0)),rastreabilidade!$M:$M,$Q18),0)) -IF($J18="",0,IFERROR(SUMIFS(INDEX(rastreabilidade!$F:$H,0,MATCH(E$3,rastreabilidade!$F$1:$H$1,0)),rastreabilidade!$M:$M,$J18,rastreabilidade!$N:$N,$AM18),0)) -IF($K18="",0,IFERROR(SUMIFS(INDEX(rastreabilidade!$F:$H,0,MATCH(E$3,rastreabilidade!$F$1:$H$1,0)),rastreabilidade!$M:$M,$K18,rastreabilidade!$N:$N,$AM18),0)) -IF($L18="",0,IFERROR(SUMIFS(INDEX(rastreabilidade!$F:$H,0,MATCH(E$3,rastreabilidade!$F$1:$H$1,0)),rastreabilidade!$M:$M,$L18,rastreabilidade!$N:$N,$AM18),0)) -IF($M18="",0,IFERROR(SUMIFS(INDEX(rastreabilidade!$F:$H,0,MATCH(E$3,rastreabilidade!$F$1:$H$1,0)),rastreabilidade!$M:$M,$M18,rastreabilidade!$N:$N,$AM18),0)) -> 0 | F18: =IFERROR(SUMIFS(INDEX(rastreabilidade!$F:$H,0,MATCH(F$3,rastreabilidade!$F$1:$H$1,0)),rastreabilidade!$N:$N,$AM18),0) +IF($N18="",0,IFERROR(SUMIFS(INDEX(rastreabilidade!$F:$H,0,MATCH(F$3,rastreabilidade!$F$1:$H$1,0)),rastreabilidade!$M:$M,$N18),0)) +IF($O18="",0,IFERROR(SUMIFS(INDEX(rastreabilidade!$F:$H,0,MATCH(F$3,rastreabilidade!$F$1:$H$1,0)),rastreabilidade!$M:$M,$O18),0)) +IF($P18="",0,IFERROR(SUMIFS(INDEX(rastreabilidade!$F:$H,0,MATCH(F$3,rastreabilidade!$F$1:$H$1,0)),rastreabilidade!$M:$M,$P18),0)) +IF($Q18="",0,IFERROR(SUMIFS(INDEX(rastreabilidade!$F:$H,0,MATCH(F$3,rastreabilidade!$F$1:$H$1,0)),rastreabilidade!$M:$M,$Q18),0)) -IF($J18="",0,IFERROR(SUMIFS(INDEX(rastreabilidade!$F:$H,0,MATCH(F$3,rastreabilidade!$F$1:$H$1,0)),rastreabilidade!$M:$M,$J18,rastreabilidade!$N:$N,$AM18),0)) -IF($K18="",0,IFERROR(SUMIFS(INDEX(rastreabilidade!$F:$H,0,MATCH(F$3,rastreabilidade!$F$1:$H$1,0)),rastreabilidade!$M:$M,$K18,rastreabilidade!$N:$N,$AM18),0)) -IF($L18="",0,IFERROR(SUMIFS(INDEX(rastreabilidade!$F:$H,0,MATCH(F$3,rastreabilidade!$F$1:$H$1,0)),rastreabilidade!$M:$M,$L18,rastreabilidade!$N:$N,$AM18),0)) -IF($M18="",0,IFERROR(SUMIFS(INDEX(rastreabilidade!$F:$H,0,MATCH(F$3,rastreabilidade!$F$1:$H$1,0)),rastreabilidade!$M:$M,$M18,rastreabilidade!$N:$N,$AM18),0)) -> 0 | G18: =IFERROR(SUMIFS(INDEX(rastreabilidade!$F:$H,0,MATCH(G$3,rastreabilidade!$F$1:$H$1,0)),rastreabilidade!$N:$N,$AM18),0) +IF($N18="",0,IFERROR(SUMIFS(INDEX(rastreabilidade!$F:$H,0,MATCH(G$3,rastreabilidade!$F$1:$H$1,0)),rastreabilidade!$M:$M,$N18),0)) +IF($O18="",0,IFERROR(SUMIFS(INDEX(rastreabilidade!$F:$H,0,MATCH(G$3,rastreabilidade!$F$1:$H$1,0)),rastreabilidade!$M:$M,$O18),0)) +IF($P18="",0,IFERROR(SUMIFS(INDEX(rastreabilidade!$F:$H,0,MATCH(G$3,rastreabilidade!$F$1:$H$1,0)),rastreabilidade!$M:$M,$P18),0)) +IF($Q18="",0,IFERROR(SUMIFS(INDEX(rastreabilidade!$F:$H,0,MATCH(G$3,rastreabilidade!$F$1:$H$1,0)),rastreabilidade!$M:$M,$Q18),0)) -IF($J18="",0,IFERROR(SUMIFS(INDEX(rastreabilidade!$F:$H,0,MATCH(G$3,rastreabilidade!$F$1:$H$1,0)),rastreabilidade!$M:$M,$J18,rastreabilidade!$N:$N,$AM18),0)) -IF($K18="",0,IFERROR(SUMIFS(INDEX(rastreabilidade!$F:$H,0,MATCH(G$3,rastreabilidade!$F$1:$H$1,0)),rastreabilidade!$M:$M,$K18,rastreabilidade!$N:$N,$AM18),0)) -IF($L18="",0,IFERROR(SUMIFS(INDEX(rastreabilidade!$F:$H,0,MATCH(G$3,rastreabilidade!$F$1:$H$1,0)),rastreabilidade!$M:$M,$L18,rastreabilidade!$N:$N,$AM18),0)) -IF($M18="",0,IFERROR(SUMIFS(INDEX(rastreabilidade!$F:$H,0,MATCH(G$3,rastreabilidade!$F$1:$H$1,0)),rastreabilidade!$M:$M,$M18,rastreabilidade!$N:$N,$AM18),0)) -> 0 | I18: {=_xlfn.LET( _xlpm.mem,H18, _xlpm.retiradas,J18:M18, _xlpm.adicoes,N18:Q18, _xlpm.memAjustada,_xlfn.REDUCE(_xlpm.mem,_xlpm.retiradas,_xlfn.LAMBDA(_xlpm.x,_xlpm.y,IF(_xlpm.y<>"",SUBSTITUTE(_xlpm.x," + ("&_xlpm.y&")",""),_xlpm.x))), _xlpm.memRemovida,_xlfn.REDUCE(_xlpm.memAjustada,_xlpm.retiradas,_xlfn.LAMBDA(_xlpm.x,_xlpm.y,IF(_xlpm.y<>"",SUBSTITUTE(_xlpm.x,"("&_xlpm.y&")",""),_xlpm.x))), _xlpm.memSemSinal,IF(OR(LEFT(_xlpm.memRemovida,3)=" + ",LEFT(_xlpm.memRemovida,3)=" - "),MID(_xlpm.memRemovida,4,LEN(_xlpm.memRemovida)),_xlpm.memRemovida), _xlpm.memFinal,IF(OR(RIGHT(_xlpm.memSemSinal,3)=" + ",RIGHT(_xlpm.memSemSinal,3)=" - "),LEFT(_xlpm.memSemSinal,LEN(_xlpm.memSemSinal)-3),_xlpm.memSemSinal), _xlpm.adicoesTxt,_xlfn.TEXTJOIN(" + ",TRUE,IF(_xlpm.adicoes<>"","("&_xlpm.adicoes&")","")), IF(_xlpm.memFinal="",_xlpm.adicoesTxt,IF(_xlpm.adicoesTxt="",_xlpm.memFinal,_xlpm.memFinal&" + "&_xlpm.adicoesTxt)) )} | S18: EBITDA | T18: =+T15+T16+T17-T14 -> 0 | W18: =+W15+W16+W17-W14 -> 0 | X18: =+X15+X16+X17-X14 -> 0 | Y18: =+Y15+Y16+Y17-Y14 -> 0 | AM18: =_xlfn.TEXTJOIN("|",TRUE,A18,"Ativo","Circulante") -> Mútuo Financeiro|Ativo|Circulante | AN18: =_xlfn.CONCAT(S18,"|","DRE","|","DRE",) -> EBITDA|DRE|DRE
A19: Impostos a Recuperar | B19: =IFERROR(SUMIFS(INDEX(rastreabilidade!$F:$H,0,MATCH($B$2,rastreabilidade!$F$1:$H$1,0)),rastreabilidade!$K:$K,$A19,rastreabilidade!$D:$D,"Sim"),0) -> 0 | E19: =IFERROR(SUMIFS(INDEX(rastreabilidade!$F:$H,0,MATCH(E$3,rastreabilidade!$F$1:$H$1,0)),rastreabilidade!$N:$N,$AM19),0) +IF($N19="",0,IFERROR(SUMIFS(INDEX(rastreabilidade!$F:$H,0,MATCH(E$3,rastreabilidade!$F$1:$H$1,0)),rastreabilidade!$M:$M,$N19),0)) +IF($O19="",0,IFERROR(SUMIFS(INDEX(rastreabilidade!$F:$H,0,MATCH(E$3,rastreabilidade!$F$1:$H$1,0)),rastreabilidade!$M:$M,$O19),0)) +IF($P19="",0,IFERROR(SUMIFS(INDEX(rastreabilidade!$F:$H,0,MATCH(E$3,rastreabilidade!$F$1:$H$1,0)),rastreabilidade!$M:$M,$P19),0)) +IF($Q19="",0,IFERROR(SUMIFS(INDEX(rastreabilidade!$F:$H,0,MATCH(E$3,rastreabilidade!$F$1:$H$1,0)),rastreabilidade!$M:$M,$Q19),0)) -IF($J19="",0,IFERROR(SUMIFS(INDEX(rastreabilidade!$F:$H,0,MATCH(E$3,rastreabilidade!$F$1:$H$1,0)),rastreabilidade!$M:$M,$J19,rastreabilidade!$N:$N,$AM19),0)) -IF($K19="",0,IFERROR(SUMIFS(INDEX(rastreabilidade!$F:$H,0,MATCH(E$3,rastreabilidade!$F$1:$H$1,0)),rastreabilidade!$M:$M,$K19,rastreabilidade!$N:$N,$AM19),0)) -IF($L19="",0,IFERROR(SUMIFS(INDEX(rastreabilidade!$F:$H,0,MATCH(E$3,rastreabilidade!$F$1:$H$1,0)),rastreabilidade!$M:$M,$L19,rastreabilidade!$N:$N,$AM19),0)) -IF($M19="",0,IFERROR(SUMIFS(INDEX(rastreabilidade!$F:$H,0,MATCH(E$3,rastreabilidade!$F$1:$H$1,0)),rastreabilidade!$M:$M,$M19,rastreabilidade!$N:$N,$AM19),0)) -> 0 | F19: =IFERROR(SUMIFS(INDEX(rastreabilidade!$F:$H,0,MATCH(F$3,rastreabilidade!$F$1:$H$1,0)),rastreabilidade!$N:$N,$AM19),0) +IF($N19="",0,IFERROR(SUMIFS(INDEX(rastreabilidade!$F:$H,0,MATCH(F$3,rastreabilidade!$F$1:$H$1,0)),rastreabilidade!$M:$M,$N19),0)) +IF($O19="",0,IFERROR(SUMIFS(INDEX(rastreabilidade!$F:$H,0,MATCH(F$3,rastreabilidade!$F$1:$H$1,0)),rastreabilidade!$M:$M,$O19),0)) +IF($P19="",0,IFERROR(SUMIFS(INDEX(rastreabilidade!$F:$H,0,MATCH(F$3,rastreabilidade!$F$1:$H$1,0)),rastreabilidade!$M:$M,$P19),0)) +IF($Q19="",0,IFERROR(SUMIFS(INDEX(rastreabilidade!$F:$H,0,MATCH(F$3,rastreabilidade!$F$1:$H$1,0)),rastreabilidade!$M:$M,$Q19),0)) -IF($J19="",0,IFERROR(SUMIFS(INDEX(rastreabilidade!$F:$H,0,MATCH(F$3,rastreabilidade!$F$1:$H$1,0)),rastreabilidade!$M:$M,$J19,rastreabilidade!$N:$N,$AM19),0)) -IF($K19="",0,IFERROR(SUMIFS(INDEX(rastreabilidade!$F:$H,0,MATCH(F$3,rastreabilidade!$F$1:$H$1,0)),rastreabilidade!$M:$M,$K19,rastreabilidade!$N:$N,$AM19),0)) -IF($L19="",0,IFERROR(SUMIFS(INDEX(rastreabilidade!$F:$H,0,MATCH(F$3,rastreabilidade!$F$1:$H$1,0)),rastreabilidade!$M:$M,$L19,rastreabilidade!$N:$N,$AM19),0)) -IF($M19="",0,IFERROR(SUMIFS(INDEX(rastreabilidade!$F:$H,0,MATCH(F$3,rastreabilidade!$F$1:$H$1,0)),rastreabilidade!$M:$M,$M19,rastreabilidade!$N:$N,$AM19),0)) -> 0 | G19: =IFERROR(SUMIFS(INDEX(rastreabilidade!$F:$H,0,MATCH(G$3,rastreabilidade!$F$1:$H$1,0)),rastreabilidade!$N:$N,$AM19),0) +IF($N19="",0,IFERROR(SUMIFS(INDEX(rastreabilidade!$F:$H,0,MATCH(G$3,rastreabilidade!$F$1:$H$1,0)),rastreabilidade!$M:$M,$N19),0)) +IF($O19="",0,IFERROR(SUMIFS(INDEX(rastreabilidade!$F:$H,0,MATCH(G$3,rastreabilidade!$F$1:$H$1,0)),rastreabilidade!$M:$M,$O19),0)) +IF($P19="",0,IFERROR(SUMIFS(INDEX(rastreabilidade!$F:$H,0,MATCH(G$3,rastreabilidade!$F$1:$H$1,0)),rastreabilidade!$M:$M,$P19),0)) +IF($Q19="",0,IFERROR(SUMIFS(INDEX(rastreabilidade!$F:$H,0,MATCH(G$3,rastreabilidade!$F$1:$H$1,0)),rastreabilidade!$M:$M,$Q19),0)) -IF($J19="",0,IFERROR(SUMIFS(INDEX(rastreabilidade!$F:$H,0,MATCH(G$3,rastreabilidade!$F$1:$H$1,0)),rastreabilidade!$M:$M,$J19,rastreabilidade!$N:$N,$AM19),0)) -IF($K19="",0,IFERROR(SUMIFS(INDEX(rastreabilidade!$F:$H,0,MATCH(G$3,rastreabilidade!$F$1:$H$1,0)),rastreabilidade!$M:$M,$K19,rastreabilidade!$N:$N,$AM19),0)) -IF($L19="",0,IFERROR(SUMIFS(INDEX(rastreabilidade!$F:$H,0,MATCH(G$3,rastreabilidade!$F$1:$H$1,0)),rastreabilidade!$M:$M,$L19,rastreabilidade!$N:$N,$AM19),0)) -IF($M19="",0,IFERROR(SUMIFS(INDEX(rastreabilidade!$F:$H,0,MATCH(G$3,rastreabilidade!$F$1:$H$1,0)),rastreabilidade!$M:$M,$M19,rastreabilidade!$N:$N,$AM19),0)) -> 0 | I19: {=_xlfn.LET( _xlpm.mem,H19, _xlpm.retiradas,J19:M19, _xlpm.adicoes,N19:Q19, _xlpm.memAjustada,_xlfn.REDUCE(_xlpm.mem,_xlpm.retiradas,_xlfn.LAMBDA(_xlpm.x,_xlpm.y,IF(_xlpm.y<>"",SUBSTITUTE(_xlpm.x," + ("&_xlpm.y&")",""),_xlpm.x))), _xlpm.memRemovida,_xlfn.REDUCE(_xlpm.memAjustada,_xlpm.retiradas,_xlfn.LAMBDA(_xlpm.x,_xlpm.y,IF(_xlpm.y<>"",SUBSTITUTE(_xlpm.x,"("&_xlpm.y&")",""),_xlpm.x))), _xlpm.memSemSinal,IF(OR(LEFT(_xlpm.memRemovida,3)=" + ",LEFT(_xlpm.memRemovida,3)=" - "),MID(_xlpm.memRemovida,4,LEN(_xlpm.memRemovida)),_xlpm.memRemovida), _xlpm.memFinal,IF(OR(RIGHT(_xlpm.memSemSinal,3)=" + ",RIGHT(_xlpm.memSemSinal,3)=" - "),LEFT(_xlpm.memSemSinal,LEN(_xlpm.memSemSinal)-3),_xlpm.memSemSinal), _xlpm.adicoesTxt,_xlfn.TEXTJOIN(" + ",TRUE,IF(_xlpm.adicoes<>"","("&_xlpm.adicoes&")","")), IF(_xlpm.memFinal="",_xlpm.adicoesTxt,IF(_xlpm.adicoesTxt="",_xlpm.memFinal,_xlpm.memFinal&" + "&_xlpm.adicoesTxt)) )} | S19: - Despesas/Custo de Aluguel | T19: =IFERROR(SUMIFS(INDEX(rastreabilidade!$F:$H,0,MATCH($T$2,rastreabilidade!$F$1:$H$1,0)),rastreabilidade!$K:$K,$S19,rastreabilidade!$D:$D,"Sim"),0) -> 0 | W19: =IFERROR(SUMIFS(INDEX(rastreabilidade!$F:$H,0,MATCH(W$3,rastreabilidade!$F$1:$H$1,0)),rastreabilidade!$N:$N,$AN19),0)*IF($AB19="sim",-1,1) +IF($AG19="",0,IFERROR(SUMIFS(INDEX(rastreabilidade!$F:$H,0,MATCH(W$3,rastreabilidade!$F$1:$H$1,0)),rastreabilidade!$M:$M,$AG19),0)) +IF($AH19="",0,IFERROR(SUMIFS(INDEX(rastreabilidade!$F:$H,0,MATCH(W$3,rastreabilidade!$F$1:$H$1,0)),rastreabilidade!$M:$M,$AH19),0)) +IF($AI19="",0,IFERROR(SUMIFS(INDEX(rastreabilidade!$F:$H,0,MATCH(W$3,rastreabilidade!$F$1:$H$1,0)),rastreabilidade!$M:$M,$AI19),0)) +IF($AJ19="",0,IFERROR(SUMIFS(INDEX(rastreabilidade!$F:$H,0,MATCH(W$3,rastreabilidade!$F$1:$H$1,0)),rastreabilidade!$M:$M,$AJ19),0)) -IF($AC19="",0,IFERROR(SUMIFS(INDEX(rastreabilidade!$F:$H,0,MATCH(W$3,rastreabilidade!$F$1:$H$1,0)),rastreabilidade!$M:$M,$AC19,rastreabilidade!$N:$N,$AN19),0)) -IF($AD19="",0,IFERROR(SUMIFS(INDEX(rastreabilidade!$F:$H,0,MATCH(W$3,rastreabilidade!$F$1:$H$1,0)),rastreabilidade!$M:$M,$AD19,rastreabilidade!$N:$N,$AN19),0)) -IF($AE19="",0,IFERROR(SUMIFS(INDEX(rastreabilidade!$F:$H,0,MATCH(W$3,rastreabilidade!$F$1:$H$1,0)),rastreabilidade!$M:$M,$AE19,rastreabilidade!$N:$N,$AN19),0)) -IF($AF19="",0,IFERROR(SUMIFS(INDEX(rastreabilidade!$F:$H,0,MATCH(W$3,rastreabilidade!$F$1:$H$1,0)),rastreabilidade!$M:$M,$AF19,rastreabilidade!$N:$N,$AN19),0)) -> 0 | X19: =IFERROR(SUMIFS(INDEX(rastreabilidade!$F:$H,0,MATCH(X$3,rastreabilidade!$F$1:$H$1,0)),rastreabilidade!$N:$N,$AN19),0)*IF($AB19="sim",-1,1) +IF($AG19="",0,IFERROR(SUMIFS(INDEX(rastreabilidade!$F:$H,0,MATCH(X$3,rastreabilidade!$F$1:$H$1,0)),rastreabilidade!$M:$M,$AG19),0)) +IF($AH19="",0,IFERROR(SUMIFS(INDEX(rastreabilidade!$F:$H,0,MATCH(X$3,rastreabilidade!$F$1:$H$1,0)),rastreabilidade!$M:$M,$AH19),0)) +IF($AI19="",0,IFERROR(SUMIFS(INDEX(rastreabilidade!$F:$H,0,MATCH(X$3,rastreabilidade!$F$1:$H$1,0)),rastreabilidade!$M:$M,$AI19),0)) +IF($AJ19="",0,IFERROR(SUMIFS(INDEX(rastreabilidade!$F:$H,0,MATCH(X$3,rastreabilidade!$F$1:$H$1,0)),rastreabilidade!$M:$M,$AJ19),0)) -IF($AC19="",0,IFERROR(SUMIFS(INDEX(rastreabilidade!$F:$H,0,MATCH(X$3,rastreabilidade!$F$1:$H$1,0)),rastreabilidade!$M:$M,$AC19,rastreabilidade!$N:$N,$AN19),0)) -IF($AD19="",0,IFERROR(SUMIFS(INDEX(rastreabilidade!$F:$H,0,MATCH(X$3,rastreabilidade!$F$1:$H$1,0)),rastreabilidade!$M:$M,$AD19,rastreabilidade!$N:$N,$AN19),0)) -IF($AE19="",0,IFERROR(SUMIFS(INDEX(rastreabilidade!$F:$H,0,MATCH(X$3,rastreabilidade!$F$1:$H$1,0)),rastreabilidade!$M:$M,$AE19,rastreabilidade!$N:$N,$AN19),0)) -IF($AF19="",0,IFERROR(SUMIFS(INDEX(rastreabilidade!$F:$H,0,MATCH(X$3,rastreabilidade!$F$1:$H$1,0)),rastreabilidade!$M:$M,$AF19,rastreabilidade!$N:$N,$AN19),0)) -> 0 | Y19: =IFERROR(SUMIFS(INDEX(rastreabilidade!$F:$H,0,MATCH(Y$3,rastreabilidade!$F$1:$H$1,0)),rastreabilidade!$N:$N,$AN19),0)*IF($AB19="sim",-1,1) +IF($AG19="",0,IFERROR(SUMIFS(INDEX(rastreabilidade!$F:$H,0,MATCH(Y$3,rastreabilidade!$F$1:$H$1,0)),rastreabilidade!$M:$M,$AG19),0)) +IF($AH19="",0,IFERROR(SUMIFS(INDEX(rastreabilidade!$F:$H,0,MATCH(Y$3,rastreabilidade!$F$1:$H$1,0)),rastreabilidade!$M:$M,$AH19),0)) +IF($AI19="",0,IFERROR(SUMIFS(INDEX(rastreabilidade!$F:$H,0,MATCH(Y$3,rastreabilidade!$F$1:$H$1,0)),rastreabilidade!$M:$M,$AI19),0)) +IF($AJ19="",0,IFERROR(SUMIFS(INDEX(rastreabilidade!$F:$H,0,MATCH(Y$3,rastreabilidade!$F$1:$H$1,0)),rastreabilidade!$M:$M,$AJ19),0)) -IF($AC19="",0,IFERROR(SUMIFS(INDEX(rastreabilidade!$F:$H,0,MATCH(Y$3,rastreabilidade!$F$1:$H$1,0)),rastreabilidade!$M:$M,$AC19,rastreabilidade!$N:$N,$AN19),0)) -IF($AD19="",0,IFERROR(SUMIFS(INDEX(rastreabilidade!$F:$H,0,MATCH(Y$3,rastreabilidade!$F$1:$H$1,0)),rastreabilidade!$M:$M,$AD19,rastreabilidade!$N:$N,$AN19),0)) -IF($AE19="",0,IFERROR(SUMIFS(INDEX(rastreabilidade!$F:$H,0,MATCH(Y$3,rastreabilidade!$F$1:$H$1,0)),rastreabilidade!$M:$M,$AE19,rastreabilidade!$N:$N,$AN19),0)) -IF($AF19="",0,IFERROR(SUMIFS(INDEX(rastreabilidade!$F:$H,0,MATCH(Y$3,rastreabilidade!$F$1:$H$1,0)),rastreabilidade!$M:$M,$AF19,rastreabilidade!$N:$N,$AN19),0)) -> 0 | AA19: {=_xlfn.LET( _xlpm.mem,Z19, _xlpm.retiradas,AC19:AF19, _xlpm.adicoes,AG19:AJ19, _xlpm.memAjustada,_xlfn.REDUCE(_xlpm.mem,_xlpm.retiradas,_xlfn.LAMBDA(_xlpm.x,_xlpm.y,IF(_xlpm.y<>"",SUBSTITUTE(_xlpm.x," + ("&_xlpm.y&")",""),_xlpm.x))), _xlpm.memRemovida,_xlfn.REDUCE(_xlpm.memAjustada,_xlpm.retiradas,_xlfn.LAMBDA(_xlpm.x,_xlpm.y,IF(_xlpm.y<>"",SUBSTITUTE(_xlpm.x,"("&_xlpm.y&")",""),_xlpm.x))), _xlpm.memSemSinal,IF(OR(LEFT(_xlpm.memRemovida,3)=" + ",LEFT(_xlpm.memRemovida,3)=" - "),MID(_xlpm.memRemovida,4,LEN(_xlpm.memRemovida)),_xlpm.memRemovida), _xlpm.memFinal,IF(OR(RIGHT(_xlpm.memSemSinal,3)=" + ",RIGHT(_xlpm.memSemSinal,3)=" - "),LEFT(_xlpm.memSemSinal,LEN(_xlpm.memSemSinal)-3),_xlpm.memSemSinal), _xlpm.adicoesTxt,_xlfn.TEXTJOIN(" + ",TRUE,IF(_xlpm.adicoes<>"","("&_xlpm.adicoes&")","")), IF(_xlpm.memFinal="",_xlpm.adicoesTxt,IF(_xlpm.adicoesTxt="",_xlpm.memFinal,_xlpm.memFinal&" + "&_xlpm.adicoesTxt)) )} | AM19: =_xlfn.TEXTJOIN("|",TRUE,A19,"Ativo","Circulante") -> Impostos a Recuperar|Ativo|Circulante | AN19: =_xlfn.CONCAT(S19,"|","DRE","|","DRE",) -> - Despesas/Custo de Aluguel|DRE|DRE
A20: Outros Operacionais (AC) | B20: =IFERROR(SUMIFS(INDEX(rastreabilidade!$F:$H,0,MATCH($B$2,rastreabilidade!$F$1:$H$1,0)),rastreabilidade!$K:$K,$A20,rastreabilidade!$D:$D,"Sim"),0) -> 0 | E20: =IFERROR(SUMIFS(INDEX(rastreabilidade!$F:$H,0,MATCH(E$3,rastreabilidade!$F$1:$H$1,0)),rastreabilidade!$N:$N,$AM20),0) +IF($N20="",0,IFERROR(SUMIFS(INDEX(rastreabilidade!$F:$H,0,MATCH(E$3,rastreabilidade!$F$1:$H$1,0)),rastreabilidade!$M:$M,$N20),0)) +IF($O20="",0,IFERROR(SUMIFS(INDEX(rastreabilidade!$F:$H,0,MATCH(E$3,rastreabilidade!$F$1:$H$1,0)),rastreabilidade!$M:$M,$O20),0)) +IF($P20="",0,IFERROR(SUMIFS(INDEX(rastreabilidade!$F:$H,0,MATCH(E$3,rastreabilidade!$F$1:$H$1,0)),rastreabilidade!$M:$M,$P20),0)) +IF($Q20="",0,IFERROR(SUMIFS(INDEX(rastreabilidade!$F:$H,0,MATCH(E$3,rastreabilidade!$F$1:$H$1,0)),rastreabilidade!$M:$M,$Q20),0)) -IF($J20="",0,IFERROR(SUMIFS(INDEX(rastreabilidade!$F:$H,0,MATCH(E$3,rastreabilidade!$F$1:$H$1,0)),rastreabilidade!$M:$M,$J20,rastreabilidade!$N:$N,$AM20),0)) -IF($K20="",0,IFERROR(SUMIFS(INDEX(rastreabilidade!$F:$H,0,MATCH(E$3,rastreabilidade!$F$1:$H$1,0)),rastreabilidade!$M:$M,$K20,rastreabilidade!$N:$N,$AM20),0)) -IF($L20="",0,IFERROR(SUMIFS(INDEX(rastreabilidade!$F:$H,0,MATCH(E$3,rastreabilidade!$F$1:$H$1,0)),rastreabilidade!$M:$M,$L20,rastreabilidade!$N:$N,$AM20),0)) -IF($M20="",0,IFERROR(SUMIFS(INDEX(rastreabilidade!$F:$H,0,MATCH(E$3,rastreabilidade!$F$1:$H$1,0)),rastreabilidade!$M:$M,$M20,rastreabilidade!$N:$N,$AM20),0)) -> 0 | F20: =IFERROR(SUMIFS(INDEX(rastreabilidade!$F:$H,0,MATCH(F$3,rastreabilidade!$F$1:$H$1,0)),rastreabilidade!$N:$N,$AM20),0) +IF($N20="",0,IFERROR(SUMIFS(INDEX(rastreabilidade!$F:$H,0,MATCH(F$3,rastreabilidade!$F$1:$H$1,0)),rastreabilidade!$M:$M,$N20),0)) +IF($O20="",0,IFERROR(SUMIFS(INDEX(rastreabilidade!$F:$H,0,MATCH(F$3,rastreabilidade!$F$1:$H$1,0)),rastreabilidade!$M:$M,$O20),0)) +IF($P20="",0,IFERROR(SUMIFS(INDEX(rastreabilidade!$F:$H,0,MATCH(F$3,rastreabilidade!$F$1:$H$1,0)),rastreabilidade!$M:$M,$P20),0)) +IF($Q20="",0,IFERROR(SUMIFS(INDEX(rastreabilidade!$F:$H,0,MATCH(F$3,rastreabilidade!$F$1:$H$1,0)),rastreabilidade!$M:$M,$Q20),0)) -IF($J20="",0,IFERROR(SUMIFS(INDEX(rastreabilidade!$F:$H,0,MATCH(F$3,rastreabilidade!$F$1:$H$1,0)),rastreabilidade!$M:$M,$J20,rastreabilidade!$N:$N,$AM20),0)) -IF($K20="",0,IFERROR(SUMIFS(INDEX(rastreabilidade!$F:$H,0,MATCH(F$3,rastreabilidade!$F$1:$H$1,0)),rastreabilidade!$M:$M,$K20,rastreabilidade!$N:$N,$AM20),0)) -IF($L20="",0,IFERROR(SUMIFS(INDEX(rastreabilidade!$F:$H,0,MATCH(F$3,rastreabilidade!$F$1:$H$1,0)),rastreabilidade!$M:$M,$L20,rastreabilidade!$N:$N,$AM20),0)) -IF($M20="",0,IFERROR(SUMIFS(INDEX(rastreabilidade!$F:$H,0,MATCH(F$3,rastreabilidade!$F$1:$H$1,0)),rastreabilidade!$M:$M,$M20,rastreabilidade!$N:$N,$AM20),0)) -> 0 | G20: =IFERROR(SUMIFS(INDEX(rastreabilidade!$F:$H,0,MATCH(G$3,rastreabilidade!$F$1:$H$1,0)),rastreabilidade!$N:$N,$AM20),0) +IF($N20="",0,IFERROR(SUMIFS(INDEX(rastreabilidade!$F:$H,0,MATCH(G$3,rastreabilidade!$F$1:$H$1,0)),rastreabilidade!$M:$M,$N20),0)) +IF($O20="",0,IFERROR(SUMIFS(INDEX(rastreabilidade!$F:$H,0,MATCH(G$3,rastreabilidade!$F$1:$H$1,0)),rastreabilidade!$M:$M,$O20),0)) +IF($P20="",0,IFERROR(SUMIFS(INDEX(rastreabilidade!$F:$H,0,MATCH(G$3,rastreabilidade!$F$1:$H$1,0)),rastreabilidade!$M:$M,$P20),0)) +IF($Q20="",0,IFERROR(SUMIFS(INDEX(rastreabilidade!$F:$H,0,MATCH(G$3,rastreabilidade!$F$1:$H$1,0)),rastreabilidade!$M:$M,$Q20),0)) -IF($J20="",0,IFERROR(SUMIFS(INDEX(rastreabilidade!$F:$H,0,MATCH(G$3,rastreabilidade!$F$1:$H$1,0)),rastreabilidade!$M:$M,$J20,rastreabilidade!$N:$N,$AM20),0)) -IF($K20="",0,IFERROR(SUMIFS(INDEX(rastreabilidade!$F:$H,0,MATCH(G$3,rastreabilidade!$F$1:$H$1,0)),rastreabilidade!$M:$M,$K20,rastreabilidade!$N:$N,$AM20),0)) -IF($L20="",0,IFERROR(SUMIFS(INDEX(rastreabilidade!$F:$H,0,MATCH(G$3,rastreabilidade!$F$1:$H$1,0)),rastreabilidade!$M:$M,$L20,rastreabilidade!$N:$N,$AM20),0)) -IF($M20="",0,IFERROR(SUMIFS(INDEX(rastreabilidade!$F:$H,0,MATCH(G$3,rastreabilidade!$F$1:$H$1,0)),rastreabilidade!$M:$M,$M20,rastreabilidade!$N:$N,$AM20),0)) -> 0 | I20: {=_xlfn.LET( _xlpm.mem,H20, _xlpm.retiradas,J20:M20, _xlpm.adicoes,N20:Q20, _xlpm.memAjustada,_xlfn.REDUCE(_xlpm.mem,_xlpm.retiradas,_xlfn.LAMBDA(_xlpm.x,_xlpm.y,IF(_xlpm.y<>"",SUBSTITUTE(_xlpm.x," + ("&_xlpm.y&")",""),_xlpm.x))), _xlpm.memRemovida,_xlfn.REDUCE(_xlpm.memAjustada,_xlpm.retiradas,_xlfn.LAMBDA(_xlpm.x,_xlpm.y,IF(_xlpm.y<>"",SUBSTITUTE(_xlpm.x,"("&_xlpm.y&")",""),_xlpm.x))), _xlpm.memSemSinal,IF(OR(LEFT(_xlpm.memRemovida,3)=" + ",LEFT(_xlpm.memRemovida,3)=" - "),MID(_xlpm.memRemovida,4,LEN(_xlpm.memRemovida)),_xlpm.memRemovida), _xlpm.memFinal,IF(OR(RIGHT(_xlpm.memSemSinal,3)=" + ",RIGHT(_xlpm.memSemSinal,3)=" - "),LEFT(_xlpm.memSemSinal,LEN(_xlpm.memSemSinal)-3),_xlpm.memSemSinal), _xlpm.adicoesTxt,_xlfn.TEXTJOIN(" + ",TRUE,IF(_xlpm.adicoes<>"","("&_xlpm.adicoes&")","")), IF(_xlpm.memFinal="",_xlpm.adicoesTxt,IF(_xlpm.adicoesTxt="",_xlpm.memFinal,_xlpm.memFinal&" + "&_xlpm.adicoesTxt)) )} | S20: EBITDA ex-IFRS16 | T20: =+T18+T19 -> 0 | W20: =+W18+W19 -> 0 | X20: =+X18+X19 -> 0 | Y20: =+Y18+Y19 -> 0 | AM20: =_xlfn.TEXTJOIN("|",TRUE,A20,"Ativo","Circulante") -> Outros Operacionais (AC)|Ativo|Circulante | AN20: =_xlfn.CONCAT(S20,"|","DRE","|","DRE",) -> EBITDA ex-IFRS16|DRE|DRE
A21: Outros Não Operacionais (AC) | B21: =IFERROR(SUMIFS(INDEX(rastreabilidade!$F:$H,0,MATCH($B$2,rastreabilidade!$F$1:$H$1,0)),rastreabilidade!$K:$K,$A21,rastreabilidade!$D:$D,"Sim"),0) -> 0 | E21: =IFERROR(SUMIFS(INDEX(rastreabilidade!$F:$H,0,MATCH(E$3,rastreabilidade!$F$1:$H$1,0)),rastreabilidade!$N:$N,$AM21),0) +IF($N21="",0,IFERROR(SUMIFS(INDEX(rastreabilidade!$F:$H,0,MATCH(E$3,rastreabilidade!$F$1:$H$1,0)),rastreabilidade!$M:$M,$N21),0)) +IF($O21="",0,IFERROR(SUMIFS(INDEX(rastreabilidade!$F:$H,0,MATCH(E$3,rastreabilidade!$F$1:$H$1,0)),rastreabilidade!$M:$M,$O21),0)) +IF($P21="",0,IFERROR(SUMIFS(INDEX(rastreabilidade!$F:$H,0,MATCH(E$3,rastreabilidade!$F$1:$H$1,0)),rastreabilidade!$M:$M,$P21),0)) +IF($Q21="",0,IFERROR(SUMIFS(INDEX(rastreabilidade!$F:$H,0,MATCH(E$3,rastreabilidade!$F$1:$H$1,0)),rastreabilidade!$M:$M,$Q21),0)) -IF($J21="",0,IFERROR(SUMIFS(INDEX(rastreabilidade!$F:$H,0,MATCH(E$3,rastreabilidade!$F$1:$H$1,0)),rastreabilidade!$M:$M,$J21,rastreabilidade!$N:$N,$AM21),0)) -IF($K21="",0,IFERROR(SUMIFS(INDEX(rastreabilidade!$F:$H,0,MATCH(E$3,rastreabilidade!$F$1:$H$1,0)),rastreabilidade!$M:$M,$K21,rastreabilidade!$N:$N,$AM21),0)) -IF($L21="",0,IFERROR(SUMIFS(INDEX(rastreabilidade!$F:$H,0,MATCH(E$3,rastreabilidade!$F$1:$H$1,0)),rastreabilidade!$M:$M,$L21,rastreabilidade!$N:$N,$AM21),0)) -IF($M21="",0,IFERROR(SUMIFS(INDEX(rastreabilidade!$F:$H,0,MATCH(E$3,rastreabilidade!$F$1:$H$1,0)),rastreabilidade!$M:$M,$M21,rastreabilidade!$N:$N,$AM21),0)) -> 0 | F21: =IFERROR(SUMIFS(INDEX(rastreabilidade!$F:$H,0,MATCH(F$3,rastreabilidade!$F$1:$H$1,0)),rastreabilidade!$N:$N,$AM21),0) +IF($N21="",0,IFERROR(SUMIFS(INDEX(rastreabilidade!$F:$H,0,MATCH(F$3,rastreabilidade!$F$1:$H$1,0)),rastreabilidade!$M:$M,$N21),0)) +IF($O21="",0,IFERROR(SUMIFS(INDEX(rastreabilidade!$F:$H,0,MATCH(F$3,rastreabilidade!$F$1:$H$1,0)),rastreabilidade!$M:$M,$O21),0)) +IF($P21="",0,IFERROR(SUMIFS(INDEX(rastreabilidade!$F:$H,0,MATCH(F$3,rastreabilidade!$F$1:$H$1,0)),rastreabilidade!$M:$M,$P21),0)) +IF($Q21="",0,IFERROR(SUMIFS(INDEX(rastreabilidade!$F:$H,0,MATCH(F$3,rastreabilidade!$F$1:$H$1,0)),rastreabilidade!$M:$M,$Q21),0)) -IF($J21="",0,IFERROR(SUMIFS(INDEX(rastreabilidade!$F:$H,0,MATCH(F$3,rastreabilidade!$F$1:$H$1,0)),rastreabilidade!$M:$M,$J21,rastreabilidade!$N:$N,$AM21),0)) -IF($K21="",0,IFERROR(SUMIFS(INDEX(rastreabilidade!$F:$H,0,MATCH(F$3,rastreabilidade!$F$1:$H$1,0)),rastreabilidade!$M:$M,$K21,rastreabilidade!$N:$N,$AM21),0)) -IF($L21="",0,IFERROR(SUMIFS(INDEX(rastreabilidade!$F:$H,0,MATCH(F$3,rastreabilidade!$F$1:$H$1,0)),rastreabilidade!$M:$M,$L21,rastreabilidade!$N:$N,$AM21),0)) -IF($M21="",0,IFERROR(SUMIFS(INDEX(rastreabilidade!$F:$H,0,MATCH(F$3,rastreabilidade!$F$1:$H$1,0)),rastreabilidade!$M:$M,$M21,rastreabilidade!$N:$N,$AM21),0)) -> 0 | G21: =IFERROR(SUMIFS(INDEX(rastreabilidade!$F:$H,0,MATCH(G$3,rastreabilidade!$F$1:$H$1,0)),rastreabilidade!$N:$N,$AM21),0) +IF($N21="",0,IFERROR(SUMIFS(INDEX(rastreabilidade!$F:$H,0,MATCH(G$3,rastreabilidade!$F$1:$H$1,0)),rastreabilidade!$M:$M,$N21),0)) +IF($O21="",0,IFERROR(SUMIFS(INDEX(rastreabilidade!$F:$H,0,MATCH(G$3,rastreabilidade!$F$1:$H$1,0)),rastreabilidade!$M:$M,$O21),0)) +IF($P21="",0,IFERROR(SUMIFS(INDEX(rastreabilidade!$F:$H,0,MATCH(G$3,rastreabilidade!$F$1:$H$1,0)),rastreabilidade!$M:$M,$P21),0)) +IF($Q21="",0,IFERROR(SUMIFS(INDEX(rastreabilidade!$F:$H,0,MATCH(G$3,rastreabilidade!$F$1:$H$1,0)),rastreabilidade!$M:$M,$Q21),0)) -IF($J21="",0,IFERROR(SUMIFS(INDEX(rastreabilidade!$F:$H,0,MATCH(G$3,rastreabilidade!$F$1:$H$1,0)),rastreabilidade!$M:$M,$J21,rastreabilidade!$N:$N,$AM21),0)) -IF($K21="",0,IFERROR(SUMIFS(INDEX(rastreabilidade!$F:$H,0,MATCH(G$3,rastreabilidade!$F$1:$H$1,0)),rastreabilidade!$M:$M,$K21,rastreabilidade!$N:$N,$AM21),0)) -IF($L21="",0,IFERROR(SUMIFS(INDEX(rastreabilidade!$F:$H,0,MATCH(G$3,rastreabilidade!$F$1:$H$1,0)),rastreabilidade!$M:$M,$L21,rastreabilidade!$N:$N,$AM21),0)) -IF($M21="",0,IFERROR(SUMIFS(INDEX(rastreabilidade!$F:$H,0,MATCH(G$3,rastreabilidade!$F$1:$H$1,0)),rastreabilidade!$M:$M,$M21,rastreabilidade!$N:$N,$AM21),0)) -> 0 | I21: {=_xlfn.LET( _xlpm.mem,H21, _xlpm.retiradas,J21:M21, _xlpm.adicoes,N21:Q21, _xlpm.memAjustada,_xlfn.REDUCE(_xlpm.mem,_xlpm.retiradas,_xlfn.LAMBDA(_xlpm.x,_xlpm.y,IF(_xlpm.y<>"",SUBSTITUTE(_xlpm.x," + ("&_xlpm.y&")",""),_xlpm.x))), _xlpm.memRemovida,_xlfn.REDUCE(_xlpm.memAjustada,_xlpm.retiradas,_xlfn.LAMBDA(_xlpm.x,_xlpm.y,IF(_xlpm.y<>"",SUBSTITUTE(_xlpm.x,"("&_xlpm.y&")",""),_xlpm.x))), _xlpm.memSemSinal,IF(OR(LEFT(_xlpm.memRemovida,3)=" + ",LEFT(_xlpm.memRemovida,3)=" - "),MID(_xlpm.memRemovida,4,LEN(_xlpm.memRemovida)),_xlpm.memRemovida), _xlpm.memFinal,IF(OR(RIGHT(_xlpm.memSemSinal,3)=" + ",RIGHT(_xlpm.memSemSinal,3)=" - "),LEFT(_xlpm.memSemSinal,LEN(_xlpm.memSemSinal)-3),_xlpm.memSemSinal), _xlpm.adicoesTxt,_xlfn.TEXTJOIN(" + ",TRUE,IF(_xlpm.adicoes<>"","("&_xlpm.adicoes&")","")), IF(_xlpm.memFinal="",_xlpm.adicoesTxt,IF(_xlpm.adicoesTxt="",_xlpm.memFinal,_xlpm.memFinal&" + "&_xlpm.adicoesTxt)) )} | S21: - Despesas Financeiras | T21: =IFERROR(SUMIFS(INDEX(rastreabilidade!$F:$H,0,MATCH($T$2,rastreabilidade!$F$1:$H$1,0)),rastreabilidade!$K:$K,$S21,rastreabilidade!$D:$D,"Sim"),0) -> 0 | W21: =IFERROR(SUMIFS(INDEX(rastreabilidade!$F:$H,0,MATCH(W$3,rastreabilidade!$F$1:$H$1,0)),rastreabilidade!$N:$N,$AN21),0)*IF($AB21="sim",-1,1) +IF($AG21="",0,IFERROR(SUMIFS(INDEX(rastreabilidade!$F:$H,0,MATCH(W$3,rastreabilidade!$F$1:$H$1,0)),rastreabilidade!$M:$M,$AG21),0)) +IF($AH21="",0,IFERROR(SUMIFS(INDEX(rastreabilidade!$F:$H,0,MATCH(W$3,rastreabilidade!$F$1:$H$1,0)),rastreabilidade!$M:$M,$AH21),0)) +IF($AI21="",0,IFERROR(SUMIFS(INDEX(rastreabilidade!$F:$H,0,MATCH(W$3,rastreabilidade!$F$1:$H$1,0)),rastreabilidade!$M:$M,$AI21),0)) +IF($AJ21="",0,IFERROR(SUMIFS(INDEX(rastreabilidade!$F:$H,0,MATCH(W$3,rastreabilidade!$F$1:$H$1,0)),rastreabilidade!$M:$M,$AJ21),0)) -IF($AC21="",0,IFERROR(SUMIFS(INDEX(rastreabilidade!$F:$H,0,MATCH(W$3,rastreabilidade!$F$1:$H$1,0)),rastreabilidade!$M:$M,$AC21,rastreabilidade!$N:$N,$AN21),0)) -IF($AD21="",0,IFERROR(SUMIFS(INDEX(rastreabilidade!$F:$H,0,MATCH(W$3,rastreabilidade!$F$1:$H$1,0)),rastreabilidade!$M:$M,$AD21,rastreabilidade!$N:$N,$AN21),0)) -IF($AE21="",0,IFERROR(SUMIFS(INDEX(rastreabilidade!$F:$H,0,MATCH(W$3,rastreabilidade!$F$1:$H$1,0)),rastreabilidade!$M:$M,$AE21,rastreabilidade!$N:$N,$AN21),0)) -IF($AF21="",0,IFERROR(SUMIFS(INDEX(rastreabilidade!$F:$H,0,MATCH(W$3,rastreabilidade!$F$1:$H$1,0)),rastreabilidade!$M:$M,$AF21,rastreabilidade!$N:$N,$AN21),0)) -> 0 | X21: =IFERROR(SUMIFS(INDEX(rastreabilidade!$F:$H,0,MATCH(X$3,rastreabilidade!$F$1:$H$1,0)),rastreabilidade!$N:$N,$AN21),0)*IF($AB21="sim",-1,1) +IF($AG21="",0,IFERROR(SUMIFS(INDEX(rastreabilidade!$F:$H,0,MATCH(X$3,rastreabilidade!$F$1:$H$1,0)),rastreabilidade!$M:$M,$AG21),0)) +IF($AH21="",0,IFERROR(SUMIFS(INDEX(rastreabilidade!$F:$H,0,MATCH(X$3,rastreabilidade!$F$1:$H$1,0)),rastreabilidade!$M:$M,$AH21),0)) +IF($AI21="",0,IFERROR(SUMIFS(INDEX(rastreabilidade!$F:$H,0,MATCH(X$3,rastreabilidade!$F$1:$H$1,0)),rastreabilidade!$M:$M,$AI21),0)) +IF($AJ21="",0,IFERROR(SUMIFS(INDEX(rastreabilidade!$F:$H,0,MATCH(X$3,rastreabilidade!$F$1:$H$1,0)),rastreabilidade!$M:$M,$AJ21),0)) -IF($AC21="",0,IFERROR(SUMIFS(INDEX(rastreabilidade!$F:$H,0,MATCH(X$3,rastreabilidade!$F$1:$H$1,0)),rastreabilidade!$M:$M,$AC21,rastreabilidade!$N:$N,$AN21),0)) -IF($AD21="",0,IFERROR(SUMIFS(INDEX(rastreabilidade!$F:$H,0,MATCH(X$3,rastreabilidade!$F$1:$H$1,0)),rastreabilidade!$M:$M,$AD21,rastreabilidade!$N:$N,$AN21),0)) -IF($AE21="",0,IFERROR(SUMIFS(INDEX(rastreabilidade!$F:$H,0,MATCH(X$3,rastreabilidade!$F$1:$H$1,0)),rastreabilidade!$M:$M,$AE21,rastreabilidade!$N:$N,$AN21),0)) -IF($AF21="",0,IFERROR(SUMIFS(INDEX(rastreabilidade!$F:$H,0,MATCH(X$3,rastreabilidade!$F$1:$H$1,0)),rastreabilidade!$M:$M,$AF21,rastreabilidade!$N:$N,$AN21),0)) -> 0 | Y21: =IFERROR(SUMIFS(INDEX(rastreabilidade!$F:$H,0,MATCH(Y$3,rastreabilidade!$F$1:$H$1,0)),rastreabilidade!$N:$N,$AN21),0)*IF($AB21="sim",-1,1) +IF($AG21="",0,IFERROR(SUMIFS(INDEX(rastreabilidade!$F:$H,0,MATCH(Y$3,rastreabilidade!$F$1:$H$1,0)),rastreabilidade!$M:$M,$AG21),0)) +IF($AH21="",0,IFERROR(SUMIFS(INDEX(rastreabilidade!$F:$H,0,MATCH(Y$3,rastreabilidade!$F$1:$H$1,0)),rastreabilidade!$M:$M,$AH21),0)) +IF($AI21="",0,IFERROR(SUMIFS(INDEX(rastreabilidade!$F:$H,0,MATCH(Y$3,rastreabilidade!$F$1:$H$1,0)),rastreabilidade!$M:$M,$AI21),0)) +IF($AJ21="",0,IFERROR(SUMIFS(INDEX(rastreabilidade!$F:$H,0,MATCH(Y$3,rastreabilidade!$F$1:$H$1,0)),rastreabilidade!$M:$M,$AJ21),0)) -IF($AC21="",0,IFERROR(SUMIFS(INDEX(rastreabilidade!$F:$H,0,MATCH(Y$3,rastreabilidade!$F$1:$H$1,0)),rastreabilidade!$M:$M,$AC21,rastreabilidade!$N:$N,$AN21),0)) -IF($AD21="",0,IFERROR(SUMIFS(INDEX(rastreabilidade!$F:$H,0,MATCH(Y$3,rastreabilidade!$F$1:$H$1,0)),rastreabilidade!$M:$M,$AD21,rastreabilidade!$N:$N,$AN21),0)) -IF($AE21="",0,IFERROR(SUMIFS(INDEX(rastreabilidade!$F:$H,0,MATCH(Y$3,rastreabilidade!$F$1:$H$1,0)),rastreabilidade!$M:$M,$AE21,rastreabilidade!$N:$N,$AN21),0)) -IF($AF21="",0,IFERROR(SUMIFS(INDEX(rastreabilidade!$F:$H,0,MATCH(Y$3,rastreabilidade!$F$1:$H$1,0)),rastreabilidade!$M:$M,$AF21,rastreabilidade!$N:$N,$AN21),0)) -> 0 | AA21: {=_xlfn.LET( _xlpm.mem,Z21, _xlpm.retiradas,AC21:AF21, _xlpm.adicoes,AG21:AJ21, _xlpm.memAjustada,_xlfn.REDUCE(_xlpm.mem,_xlpm.retiradas,_xlfn.LAMBDA(_xlpm.x,_xlpm.y,IF(_xlpm.y<>"",SUBSTITUTE(_xlpm.x," + ("&_xlpm.y&")",""),_xlpm.x))), _xlpm.memRemovida,_xlfn.REDUCE(_xlpm.memAjustada,_xlpm.retiradas,_xlfn.LAMBDA(_xlpm.x,_xlpm.y,IF(_xlpm.y<>"",SUBSTITUTE(_xlpm.x,"("&_xlpm.y&")",""),_xlpm.x))), _xlpm.memSemSinal,IF(OR(LEFT(_xlpm.memRemovida,3)=" + ",LEFT(_xlpm.memRemovida,3)=" - "),MID(_xlpm.memRemovida,4,LEN(_xlpm.memRemovida)),_xlpm.memRemovida), _xlpm.memFinal,IF(OR(RIGHT(_xlpm.memSemSinal,3)=" + ",RIGHT(_xlpm.memSemSinal,3)=" - "),LEFT(_xlpm.memSemSinal,LEN(_xlpm.memSemSinal)-3),_xlpm.memSemSinal), _xlpm.adicoesTxt,_xlfn.TEXTJOIN(" + ",TRUE,IF(_xlpm.adicoes<>"","("&_xlpm.adicoes&")","")), IF(_xlpm.memFinal="",_xlpm.adicoesTxt,IF(_xlpm.adicoesTxt="",_xlpm.memFinal,_xlpm.memFinal&" + "&_xlpm.adicoesTxt)) )} | AM21: =_xlfn.TEXTJOIN("|",TRUE,A21,"Ativo","Circulante") -> Outros Não Operacionais (AC)|Ativo|Circulante | AN21: =_xlfn.CONCAT(S21,"|","DRE","|","DRE",) -> - Despesas Financeiras|DRE|DRE
A22: TOTAL ATIVO CIRCULANTE | B22: =SUM(B7,B11,B15,B16:B21) -> 0 | E22: =SUM(E7,E11,E15,E16:E21) -> 0 | F22: =SUM(F7,F11,F15,F16:F21) -> 0 | G22: =SUM(G7,G11,G15,G16:G21) -> 0 | J22: =SUM(J7,J11,J15,J16:J21) -> 0 | Q22: =SUM(Q7,Q11,Q15,Q16:Q21) -> 0 | S22: + Receitas Financeiras | T22: =IFERROR(SUMIFS(INDEX(rastreabilidade!$F:$H,0,MATCH($T$2,rastreabilidade!$F$1:$H$1,0)),rastreabilidade!$K:$K,$S22,rastreabilidade!$D:$D,"Sim"),0) -> 0 | W22: =IFERROR(SUMIFS(INDEX(rastreabilidade!$F:$H,0,MATCH(W$3,rastreabilidade!$F$1:$H$1,0)),rastreabilidade!$N:$N,$AN22),0)*IF($AB22="sim",-1,1) +IF($AG22="",0,IFERROR(SUMIFS(INDEX(rastreabilidade!$F:$H,0,MATCH(W$3,rastreabilidade!$F$1:$H$1,0)),rastreabilidade!$M:$M,$AG22),0)) +IF($AH22="",0,IFERROR(SUMIFS(INDEX(rastreabilidade!$F:$H,0,MATCH(W$3,rastreabilidade!$F$1:$H$1,0)),rastreabilidade!$M:$M,$AH22),0)) +IF($AI22="",0,IFERROR(SUMIFS(INDEX(rastreabilidade!$F:$H,0,MATCH(W$3,rastreabilidade!$F$1:$H$1,0)),rastreabilidade!$M:$M,$AI22),0)) +IF($AJ22="",0,IFERROR(SUMIFS(INDEX(rastreabilidade!$F:$H,0,MATCH(W$3,rastreabilidade!$F$1:$H$1,0)),rastreabilidade!$M:$M,$AJ22),0)) -IF($AC22="",0,IFERROR(SUMIFS(INDEX(rastreabilidade!$F:$H,0,MATCH(W$3,rastreabilidade!$F$1:$H$1,0)),rastreabilidade!$M:$M,$AC22,rastreabilidade!$N:$N,$AN22),0)) -IF($AD22="",0,IFERROR(SUMIFS(INDEX(rastreabilidade!$F:$H,0,MATCH(W$3,rastreabilidade!$F$1:$H$1,0)),rastreabilidade!$M:$M,$AD22,rastreabilidade!$N:$N,$AN22),0)) -IF($AE22="",0,IFERROR(SUMIFS(INDEX(rastreabilidade!$F:$H,0,MATCH(W$3,rastreabilidade!$F$1:$H$1,0)),rastreabilidade!$M:$M,$AE22,rastreabilidade!$N:$N,$AN22),0)) -IF($AF22="",0,IFERROR(SUMIFS(INDEX(rastreabilidade!$F:$H,0,MATCH(W$3,rastreabilidade!$F$1:$H$1,0)),rastreabilidade!$M:$M,$AF22,rastreabilidade!$N:$N,$AN22),0)) -> 0 | X22: =IFERROR(SUMIFS(INDEX(rastreabilidade!$F:$H,0,MATCH(X$3,rastreabilidade!$F$1:$H$1,0)),rastreabilidade!$N:$N,$AN22),0)*IF($AB22="sim",-1,1) +IF($AG22="",0,IFERROR(SUMIFS(INDEX(rastreabilidade!$F:$H,0,MATCH(X$3,rastreabilidade!$F$1:$H$1,0)),rastreabilidade!$M:$M,$AG22),0)) +IF($AH22="",0,IFERROR(SUMIFS(INDEX(rastreabilidade!$F:$H,0,MATCH(X$3,rastreabilidade!$F$1:$H$1,0)),rastreabilidade!$M:$M,$AH22),0)) +IF($AI22="",0,IFERROR(SUMIFS(INDEX(rastreabilidade!$F:$H,0,MATCH(X$3,rastreabilidade!$F$1:$H$1,0)),rastreabilidade!$M:$M,$AI22),0)) +IF($AJ22="",0,IFERROR(SUMIFS(INDEX(rastreabilidade!$F:$H,0,MATCH(X$3,rastreabilidade!$F$1:$H$1,0)),rastreabilidade!$M:$M,$AJ22),0)) -IF($AC22="",0,IFERROR(SUMIFS(INDEX(rastreabilidade!$F:$H,0,MATCH(X$3,rastreabilidade!$F$1:$H$1,0)),rastreabilidade!$M:$M,$AC22,rastreabilidade!$N:$N,$AN22),0)) -IF($AD22="",0,IFERROR(SUMIFS(INDEX(rastreabilidade!$F:$H,0,MATCH(X$3,rastreabilidade!$F$1:$H$1,0)),rastreabilidade!$M:$M,$AD22,rastreabilidade!$N:$N,$AN22),0)) -IF($AE22="",0,IFERROR(SUMIFS(INDEX(rastreabilidade!$F:$H,0,MATCH(X$3,rastreabilidade!$F$1:$H$1,0)),rastreabilidade!$M:$M,$AE22,rastreabilidade!$N:$N,$AN22),0)) -IF($AF22="",0,IFERROR(SUMIFS(INDEX(rastreabilidade!$F:$H,0,MATCH(X$3,rastreabilidade!$F$1:$H$1,0)),rastreabilidade!$M:$M,$AF22,rastreabilidade!$N:$N,$AN22),0)) -> 0 | Y22: =IFERROR(SUMIFS(INDEX(rastreabilidade!$F:$H,0,MATCH(Y$3,rastreabilidade!$F$1:$H$1,0)),rastreabilidade!$N:$N,$AN22),0)*IF($AB22="sim",-1,1) +IF($AG22="",0,IFERROR(SUMIFS(INDEX(rastreabilidade!$F:$H,0,MATCH(Y$3,rastreabilidade!$F$1:$H$1,0)),rastreabilidade!$M:$M,$AG22),0)) +IF($AH22="",0,IFERROR(SUMIFS(INDEX(rastreabilidade!$F:$H,0,MATCH(Y$3,rastreabilidade!$F$1:$H$1,0)),rastreabilidade!$M:$M,$AH22),0)) +IF($AI22="",0,IFERROR(SUMIFS(INDEX(rastreabilidade!$F:$H,0,MATCH(Y$3,rastreabilidade!$F$1:$H$1,0)),rastreabilidade!$M:$M,$AI22),0)) +IF($AJ22="",0,IFERROR(SUMIFS(INDEX(rastreabilidade!$F:$H,0,MATCH(Y$3,rastreabilidade!$F$1:$H$1,0)),rastreabilidade!$M:$M,$AJ22),0)) -IF($AC22="",0,IFERROR(SUMIFS(INDEX(rastreabilidade!$F:$H,0,MATCH(Y$3,rastreabilidade!$F$1:$H$1,0)),rastreabilidade!$M:$M,$AC22,rastreabilidade!$N:$N,$AN22),0)) -IF($AD22="",0,IFERROR(SUMIFS(INDEX(rastreabilidade!$F:$H,0,MATCH(Y$3,rastreabilidade!$F$1:$H$1,0)),rastreabilidade!$M:$M,$AD22,rastreabilidade!$N:$N,$AN22),0)) -IF($AE22="",0,IFERROR(SUMIFS(INDEX(rastreabilidade!$F:$H,0,MATCH(Y$3,rastreabilidade!$F$1:$H$1,0)),rastreabilidade!$M:$M,$AE22,rastreabilidade!$N:$N,$AN22),0)) -IF($AF22="",0,IFERROR(SUMIFS(INDEX(rastreabilidade!$F:$H,0,MATCH(Y$3,rastreabilidade!$F$1:$H$1,0)),rastreabilidade!$M:$M,$AF22,rastreabilidade!$N:$N,$AN22),0)) -> 0 | AA22: {=_xlfn.LET( _xlpm.mem,Z22, _xlpm.retiradas,AC22:AF22, _xlpm.adicoes,AG22:AJ22, _xlpm.memAjustada,_xlfn.REDUCE(_xlpm.mem,_xlpm.retiradas,_xlfn.LAMBDA(_xlpm.x,_xlpm.y,IF(_xlpm.y<>"",SUBSTITUTE(_xlpm.x," + ("&_xlpm.y&")",""),_xlpm.x))), _xlpm.memRemovida,_xlfn.REDUCE(_xlpm.memAjustada,_xlpm.retiradas,_xlfn.LAMBDA(_xlpm.x,_xlpm.y,IF(_xlpm.y<>"",SUBSTITUTE(_xlpm.x,"("&_xlpm.y&")",""),_xlpm.x))), _xlpm.memSemSinal,IF(OR(LEFT(_xlpm.memRemovida,3)=" + ",LEFT(_xlpm.memRemovida,3)=" - "),MID(_xlpm.memRemovida,4,LEN(_xlpm.memRemovida)),_xlpm.memRemovida), _xlpm.memFinal,IF(OR(RIGHT(_xlpm.memSemSinal,3)=" + ",RIGHT(_xlpm.memSemSinal,3)=" - "),LEFT(_xlpm.memSemSinal,LEN(_xlpm.memSemSinal)-3),_xlpm.memSemSinal), _xlpm.adicoesTxt,_xlfn.TEXTJOIN(" + ",TRUE,IF(_xlpm.adicoes<>"","("&_xlpm.adicoes&")","")), IF(_xlpm.memFinal="",_xlpm.adicoesTxt,IF(_xlpm.adicoesTxt="",_xlpm.memFinal,_xlpm.memFinal&" + "&_xlpm.adicoesTxt)) )} | AM22: =_xlfn.TEXTJOIN("|",TRUE,A22,"Ativo","Circulante") -> TOTAL ATIVO CIRCULANTE|Ativo|Circulante | AN22: =_xlfn.CONCAT(S22,"|","DRE","|","DRE",) -> + Receitas Financeiras|DRE|DRE
A23: Ajustes derivativos / cambio (ANC) | B23: =IFERROR(SUMIFS(INDEX(rastreabilidade!$F:$H,0,MATCH($B$2,rastreabilidade!$F$1:$H$1,0)),rastreabilidade!$K:$K,$A23,rastreabilidade!$D:$D,"Sim"),0) -> 0 | E23: =IFERROR(SUMIFS(INDEX(rastreabilidade!$F:$H,0,MATCH(E$3,rastreabilidade!$F$1:$H$1,0)),rastreabilidade!$N:$N,$AM23),0) +IF($N23="",0,IFERROR(SUMIFS(INDEX(rastreabilidade!$F:$H,0,MATCH(E$3,rastreabilidade!$F$1:$H$1,0)),rastreabilidade!$M:$M,$N23),0)) +IF($O23="",0,IFERROR(SUMIFS(INDEX(rastreabilidade!$F:$H,0,MATCH(E$3,rastreabilidade!$F$1:$H$1,0)),rastreabilidade!$M:$M,$O23),0)) +IF($P23="",0,IFERROR(SUMIFS(INDEX(rastreabilidade!$F:$H,0,MATCH(E$3,rastreabilidade!$F$1:$H$1,0)),rastreabilidade!$M:$M,$P23),0)) +IF($Q23="",0,IFERROR(SUMIFS(INDEX(rastreabilidade!$F:$H,0,MATCH(E$3,rastreabilidade!$F$1:$H$1,0)),rastreabilidade!$M:$M,$Q23),0)) -IF($J23="",0,IFERROR(SUMIFS(INDEX(rastreabilidade!$F:$H,0,MATCH(E$3,rastreabilidade!$F$1:$H$1,0)),rastreabilidade!$M:$M,$J23,rastreabilidade!$N:$N,$AM23),0)) -IF($K23="",0,IFERROR(SUMIFS(INDEX(rastreabilidade!$F:$H,0,MATCH(E$3,rastreabilidade!$F$1:$H$1,0)),rastreabilidade!$M:$M,$K23,rastreabilidade!$N:$N,$AM23),0)) -IF($L23="",0,IFERROR(SUMIFS(INDEX(rastreabilidade!$F:$H,0,MATCH(E$3,rastreabilidade!$F$1:$H$1,0)),rastreabilidade!$M:$M,$L23,rastreabilidade!$N:$N,$AM23),0)) -IF($M23="",0,IFERROR(SUMIFS(INDEX(rastreabilidade!$F:$H,0,MATCH(E$3,rastreabilidade!$F$1:$H$1,0)),rastreabilidade!$M:$M,$M23,rastreabilidade!$N:$N,$AM23),0)) -> 0 | F23: =IFERROR(SUMIFS(INDEX(rastreabilidade!$F:$H,0,MATCH(F$3,rastreabilidade!$F$1:$H$1,0)),rastreabilidade!$N:$N,$AM23),0) +IF($N23="",0,IFERROR(SUMIFS(INDEX(rastreabilidade!$F:$H,0,MATCH(F$3,rastreabilidade!$F$1:$H$1,0)),rastreabilidade!$M:$M,$N23),0)) +IF($O23="",0,IFERROR(SUMIFS(INDEX(rastreabilidade!$F:$H,0,MATCH(F$3,rastreabilidade!$F$1:$H$1,0)),rastreabilidade!$M:$M,$O23),0)) +IF($P23="",0,IFERROR(SUMIFS(INDEX(rastreabilidade!$F:$H,0,MATCH(F$3,rastreabilidade!$F$1:$H$1,0)),rastreabilidade!$M:$M,$P23),0)) +IF($Q23="",0,IFERROR(SUMIFS(INDEX(rastreabilidade!$F:$H,0,MATCH(F$3,rastreabilidade!$F$1:$H$1,0)),rastreabilidade!$M:$M,$Q23),0)) -IF($J23="",0,IFERROR(SUMIFS(INDEX(rastreabilidade!$F:$H,0,MATCH(F$3,rastreabilidade!$F$1:$H$1,0)),rastreabilidade!$M:$M,$J23,rastreabilidade!$N:$N,$AM23),0)) -IF($K23="",0,IFERROR(SUMIFS(INDEX(rastreabilidade!$F:$H,0,MATCH(F$3,rastreabilidade!$F$1:$H$1,0)),rastreabilidade!$M:$M,$K23,rastreabilidade!$N:$N,$AM23),0)) -IF($L23="",0,IFERROR(SUMIFS(INDEX(rastreabilidade!$F:$H,0,MATCH(F$3,rastreabilidade!$F$1:$H$1,0)),rastreabilidade!$M:$M,$L23,rastreabilidade!$N:$N,$AM23),0)) -IF($M23="",0,IFERROR(SUMIFS(INDEX(rastreabilidade!$F:$H,0,MATCH(F$3,rastreabilidade!$F$1:$H$1,0)),rastreabilidade!$M:$M,$M23,rastreabilidade!$N:$N,$AM23),0)) -> 0 | G23: =IFERROR(SUMIFS(INDEX(rastreabilidade!$F:$H,0,MATCH(G$3,rastreabilidade!$F$1:$H$1,0)),rastreabilidade!$N:$N,$AM23),0) +IF($N23="",0,IFERROR(SUMIFS(INDEX(rastreabilidade!$F:$H,0,MATCH(G$3,rastreabilidade!$F$1:$H$1,0)),rastreabilidade!$M:$M,$N23),0)) +IF($O23="",0,IFERROR(SUMIFS(INDEX(rastreabilidade!$F:$H,0,MATCH(G$3,rastreabilidade!$F$1:$H$1,0)),rastreabilidade!$M:$M,$O23),0)) +IF($P23="",0,IFERROR(SUMIFS(INDEX(rastreabilidade!$F:$H,0,MATCH(G$3,rastreabilidade!$F$1:$H$1,0)),rastreabilidade!$M:$M,$P23),0)) +IF($Q23="",0,IFERROR(SUMIFS(INDEX(rastreabilidade!$F:$H,0,MATCH(G$3,rastreabilidade!$F$1:$H$1,0)),rastreabilidade!$M:$M,$Q23),0)) -IF($J23="",0,IFERROR(SUMIFS(INDEX(rastreabilidade!$F:$H,0,MATCH(G$3,rastreabilidade!$F$1:$H$1,0)),rastreabilidade!$M:$M,$J23,rastreabilidade!$N:$N,$AM23),0)) -IF($K23="",0,IFERROR(SUMIFS(INDEX(rastreabilidade!$F:$H,0,MATCH(G$3,rastreabilidade!$F$1:$H$1,0)),rastreabilidade!$M:$M,$K23,rastreabilidade!$N:$N,$AM23),0)) -IF($L23="",0,IFERROR(SUMIFS(INDEX(rastreabilidade!$F:$H,0,MATCH(G$3,rastreabilidade!$F$1:$H$1,0)),rastreabilidade!$M:$M,$L23,rastreabilidade!$N:$N,$AM23),0)) -IF($M23="",0,IFERROR(SUMIFS(INDEX(rastreabilidade!$F:$H,0,MATCH(G$3,rastreabilidade!$F$1:$H$1,0)),rastreabilidade!$M:$M,$M23,rastreabilidade!$N:$N,$AM23),0)) -> 0 | I23: {=_xlfn.LET( _xlpm.mem,H23, _xlpm.retiradas,J23:M23, _xlpm.adicoes,N23:Q23, _xlpm.memAjustada,_xlfn.REDUCE(_xlpm.mem,_xlpm.retiradas,_xlfn.LAMBDA(_xlpm.x,_xlpm.y,IF(_xlpm.y<>"",SUBSTITUTE(_xlpm.x," + ("&_xlpm.y&")",""),_xlpm.x))), _xlpm.memRemovida,_xlfn.REDUCE(_xlpm.memAjustada,_xlpm.retiradas,_xlfn.LAMBDA(_xlpm.x,_xlpm.y,IF(_xlpm.y<>"",SUBSTITUTE(_xlpm.x,"("&_xlpm.y&")",""),_xlpm.x))), _xlpm.memSemSinal,IF(OR(LEFT(_xlpm.memRemovida,3)=" + ",LEFT(_xlpm.memRemovida,3)=" - "),MID(_xlpm.memRemovida,4,LEN(_xlpm.memRemovida)),_xlpm.memRemovida), _xlpm.memFinal,IF(OR(RIGHT(_xlpm.memSemSinal,3)=" + ",RIGHT(_xlpm.memSemSinal,3)=" - "),LEFT(_xlpm.memSemSinal,LEN(_xlpm.memSemSinal)-3),_xlpm.memSemSinal), _xlpm.adicoesTxt,_xlfn.TEXTJOIN(" + ",TRUE,IF(_xlpm.adicoes<>"","("&_xlpm.adicoes&")","")), IF(_xlpm.memFinal="",_xlpm.adicoesTxt,IF(_xlpm.adicoesTxt="",_xlpm.memFinal,_xlpm.memFinal&" + "&_xlpm.adicoesTxt)) )} | S23: +/- Resultado Financeiro | T23: =-T21+T22 -> 0 | W23: =-W21+W22 -> 0 | X23: =-X21+X22 -> 0 | Y23: =-Y21+Y22 -> 0 | AM23: =_xlfn.TEXTJOIN("|",TRUE,A23,"Ativo","Não Circulante") -> Ajustes derivativos / cambio (ANC)|Ativo|Não Circulante | AN23: =_xlfn.CONCAT(S23,"|","DRE","|","DRE",) -> +/- Resultado Financeiro|DRE|DRE
A24: Impostos Diferidos | B24: =IFERROR(SUMIFS(INDEX(rastreabilidade!$F:$H,0,MATCH($B$2,rastreabilidade!$F$1:$H$1,0)),rastreabilidade!$K:$K,$A24,rastreabilidade!$D:$D,"Sim"),0) -> 0 | E24: =IFERROR(SUMIFS(INDEX(rastreabilidade!$F:$H,0,MATCH(E$3,rastreabilidade!$F$1:$H$1,0)),rastreabilidade!$N:$N,$AM24),0) +IF($N24="",0,IFERROR(SUMIFS(INDEX(rastreabilidade!$F:$H,0,MATCH(E$3,rastreabilidade!$F$1:$H$1,0)),rastreabilidade!$M:$M,$N24),0)) +IF($O24="",0,IFERROR(SUMIFS(INDEX(rastreabilidade!$F:$H,0,MATCH(E$3,rastreabilidade!$F$1:$H$1,0)),rastreabilidade!$M:$M,$O24),0)) +IF($P24="",0,IFERROR(SUMIFS(INDEX(rastreabilidade!$F:$H,0,MATCH(E$3,rastreabilidade!$F$1:$H$1,0)),rastreabilidade!$M:$M,$P24),0)) +IF($Q24="",0,IFERROR(SUMIFS(INDEX(rastreabilidade!$F:$H,0,MATCH(E$3,rastreabilidade!$F$1:$H$1,0)),rastreabilidade!$M:$M,$Q24),0)) -IF($J24="",0,IFERROR(SUMIFS(INDEX(rastreabilidade!$F:$H,0,MATCH(E$3,rastreabilidade!$F$1:$H$1,0)),rastreabilidade!$M:$M,$J24,rastreabilidade!$N:$N,$AM24),0)) -IF($K24="",0,IFERROR(SUMIFS(INDEX(rastreabilidade!$F:$H,0,MATCH(E$3,rastreabilidade!$F$1:$H$1,0)),rastreabilidade!$M:$M,$K24,rastreabilidade!$N:$N,$AM24),0)) -IF($L24="",0,IFERROR(SUMIFS(INDEX(rastreabilidade!$F:$H,0,MATCH(E$3,rastreabilidade!$F$1:$H$1,0)),rastreabilidade!$M:$M,$L24,rastreabilidade!$N:$N,$AM24),0)) -IF($M24="",0,IFERROR(SUMIFS(INDEX(rastreabilidade!$F:$H,0,MATCH(E$3,rastreabilidade!$F$1:$H$1,0)),rastreabilidade!$M:$M,$M24,rastreabilidade!$N:$N,$AM24),0)) -> 0 | F24: =IFERROR(SUMIFS(INDEX(rastreabilidade!$F:$H,0,MATCH(F$3,rastreabilidade!$F$1:$H$1,0)),rastreabilidade!$N:$N,$AM24),0) +IF($N24="",0,IFERROR(SUMIFS(INDEX(rastreabilidade!$F:$H,0,MATCH(F$3,rastreabilidade!$F$1:$H$1,0)),rastreabilidade!$M:$M,$N24),0)) +IF($O24="",0,IFERROR(SUMIFS(INDEX(rastreabilidade!$F:$H,0,MATCH(F$3,rastreabilidade!$F$1:$H$1,0)),rastreabilidade!$M:$M,$O24),0)) +IF($P24="",0,IFERROR(SUMIFS(INDEX(rastreabilidade!$F:$H,0,MATCH(F$3,rastreabilidade!$F$1:$H$1,0)),rastreabilidade!$M:$M,$P24),0)) +IF($Q24="",0,IFERROR(SUMIFS(INDEX(rastreabilidade!$F:$H,0,MATCH(F$3,rastreabilidade!$F$1:$H$1,0)),rastreabilidade!$M:$M,$Q24),0)) -IF($J24="",0,IFERROR(SUMIFS(INDEX(rastreabilidade!$F:$H,0,MATCH(F$3,rastreabilidade!$F$1:$H$1,0)),rastreabilidade!$M:$M,$J24,rastreabilidade!$N:$N,$AM24),0)) -IF($K24="",0,IFERROR(SUMIFS(INDEX(rastreabilidade!$F:$H,0,MATCH(F$3,rastreabilidade!$F$1:$H$1,0)),rastreabilidade!$M:$M,$K24,rastreabilidade!$N:$N,$AM24),0)) -IF($L24="",0,IFERROR(SUMIFS(INDEX(rastreabilidade!$F:$H,0,MATCH(F$3,rastreabilidade!$F$1:$H$1,0)),rastreabilidade!$M:$M,$L24,rastreabilidade!$N:$N,$AM24),0)) -IF($M24="",0,IFERROR(SUMIFS(INDEX(rastreabilidade!$F:$H,0,MATCH(F$3,rastreabilidade!$F$1:$H$1,0)),rastreabilidade!$M:$M,$M24,rastreabilidade!$N:$N,$AM24),0)) -> 0 | G24: =IFERROR(SUMIFS(INDEX(rastreabilidade!$F:$H,0,MATCH(G$3,rastreabilidade!$F$1:$H$1,0)),rastreabilidade!$N:$N,$AM24),0) +IF($N24="",0,IFERROR(SUMIFS(INDEX(rastreabilidade!$F:$H,0,MATCH(G$3,rastreabilidade!$F$1:$H$1,0)),rastreabilidade!$M:$M,$N24),0)) +IF($O24="",0,IFERROR(SUMIFS(INDEX(rastreabilidade!$F:$H,0,MATCH(G$3,rastreabilidade!$F$1:$H$1,0)),rastreabilidade!$M:$M,$O24),0)) +IF($P24="",0,IFERROR(SUMIFS(INDEX(rastreabilidade!$F:$H,0,MATCH(G$3,rastreabilidade!$F$1:$H$1,0)),rastreabilidade!$M:$M,$P24),0)) +IF($Q24="",0,IFERROR(SUMIFS(INDEX(rastreabilidade!$F:$H,0,MATCH(G$3,rastreabilidade!$F$1:$H$1,0)),rastreabilidade!$M:$M,$Q24),0)) -IF($J24="",0,IFERROR(SUMIFS(INDEX(rastreabilidade!$F:$H,0,MATCH(G$3,rastreabilidade!$F$1:$H$1,0)),rastreabilidade!$M:$M,$J24,rastreabilidade!$N:$N,$AM24),0)) -IF($K24="",0,IFERROR(SUMIFS(INDEX(rastreabilidade!$F:$H,0,MATCH(G$3,rastreabilidade!$F$1:$H$1,0)),rastreabilidade!$M:$M,$K24,rastreabilidade!$N:$N,$AM24),0)) -IF($L24="",0,IFERROR(SUMIFS(INDEX(rastreabilidade!$F:$H,0,MATCH(G$3,rastreabilidade!$F$1:$H$1,0)),rastreabilidade!$M:$M,$L24,rastreabilidade!$N:$N,$AM24),0)) -IF($M24="",0,IFERROR(SUMIFS(INDEX(rastreabilidade!$F:$H,0,MATCH(G$3,rastreabilidade!$F$1:$H$1,0)),rastreabilidade!$M:$M,$M24,rastreabilidade!$N:$N,$AM24),0)) -> 0 | I24: {=_xlfn.LET( _xlpm.mem,H24, _xlpm.retiradas,J24:M24, _xlpm.adicoes,N24:Q24, _xlpm.memAjustada,_xlfn.REDUCE(_xlpm.mem,_xlpm.retiradas,_xlfn.LAMBDA(_xlpm.x,_xlpm.y,IF(_xlpm.y<>"",SUBSTITUTE(_xlpm.x," + ("&_xlpm.y&")",""),_xlpm.x))), _xlpm.memRemovida,_xlfn.REDUCE(_xlpm.memAjustada,_xlpm.retiradas,_xlfn.LAMBDA(_xlpm.x,_xlpm.y,IF(_xlpm.y<>"",SUBSTITUTE(_xlpm.x,"("&_xlpm.y&")",""),_xlpm.x))), _xlpm.memSemSinal,IF(OR(LEFT(_xlpm.memRemovida,3)=" + ",LEFT(_xlpm.memRemovida,3)=" - "),MID(_xlpm.memRemovida,4,LEN(_xlpm.memRemovida)),_xlpm.memRemovida), _xlpm.memFinal,IF(OR(RIGHT(_xlpm.memSemSinal,3)=" + ",RIGHT(_xlpm.memSemSinal,3)=" - "),LEFT(_xlpm.memSemSinal,LEN(_xlpm.memSemSinal)-3),_xlpm.memSemSinal), _xlpm.adicoesTxt,_xlfn.TEXTJOIN(" + ",TRUE,IF(_xlpm.adicoes<>"","("&_xlpm.adicoes&")","")), IF(_xlpm.memFinal="",_xlpm.adicoesTxt,IF(_xlpm.adicoesTxt="",_xlpm.memFinal,_xlpm.memFinal&" + "&_xlpm.adicoesTxt)) )} | S24: +/- Variações Cambiais | T24: =IFERROR(SUMIFS(INDEX(rastreabilidade!$F:$H,0,MATCH($T$2,rastreabilidade!$F$1:$H$1,0)),rastreabilidade!$K:$K,$S24,rastreabilidade!$D:$D,"Sim"),0) -> 0 | W24: =IFERROR(SUMIFS(INDEX(rastreabilidade!$F:$H,0,MATCH(W$3,rastreabilidade!$F$1:$H$1,0)),rastreabilidade!$N:$N,$AN24),0)*IF($AB24="sim",-1,1) +IF($AG24="",0,IFERROR(SUMIFS(INDEX(rastreabilidade!$F:$H,0,MATCH(W$3,rastreabilidade!$F$1:$H$1,0)),rastreabilidade!$M:$M,$AG24),0)) +IF($AH24="",0,IFERROR(SUMIFS(INDEX(rastreabilidade!$F:$H,0,MATCH(W$3,rastreabilidade!$F$1:$H$1,0)),rastreabilidade!$M:$M,$AH24),0)) +IF($AI24="",0,IFERROR(SUMIFS(INDEX(rastreabilidade!$F:$H,0,MATCH(W$3,rastreabilidade!$F$1:$H$1,0)),rastreabilidade!$M:$M,$AI24),0)) +IF($AJ24="",0,IFERROR(SUMIFS(INDEX(rastreabilidade!$F:$H,0,MATCH(W$3,rastreabilidade!$F$1:$H$1,0)),rastreabilidade!$M:$M,$AJ24),0)) -IF($AC24="",0,IFERROR(SUMIFS(INDEX(rastreabilidade!$F:$H,0,MATCH(W$3,rastreabilidade!$F$1:$H$1,0)),rastreabilidade!$M:$M,$AC24,rastreabilidade!$N:$N,$AN24),0)) -IF($AD24="",0,IFERROR(SUMIFS(INDEX(rastreabilidade!$F:$H,0,MATCH(W$3,rastreabilidade!$F$1:$H$1,0)),rastreabilidade!$M:$M,$AD24,rastreabilidade!$N:$N,$AN24),0)) -IF($AE24="",0,IFERROR(SUMIFS(INDEX(rastreabilidade!$F:$H,0,MATCH(W$3,rastreabilidade!$F$1:$H$1,0)),rastreabilidade!$M:$M,$AE24,rastreabilidade!$N:$N,$AN24),0)) -IF($AF24="",0,IFERROR(SUMIFS(INDEX(rastreabilidade!$F:$H,0,MATCH(W$3,rastreabilidade!$F$1:$H$1,0)),rastreabilidade!$M:$M,$AF24,rastreabilidade!$N:$N,$AN24),0)) -> 0 | X24: =IFERROR(SUMIFS(INDEX(rastreabilidade!$F:$H,0,MATCH(X$3,rastreabilidade!$F$1:$H$1,0)),rastreabilidade!$N:$N,$AN24),0)*IF($AB24="sim",-1,1) +IF($AG24="",0,IFERROR(SUMIFS(INDEX(rastreabilidade!$F:$H,0,MATCH(X$3,rastreabilidade!$F$1:$H$1,0)),rastreabilidade!$M:$M,$AG24),0)) +IF($AH24="",0,IFERROR(SUMIFS(INDEX(rastreabilidade!$F:$H,0,MATCH(X$3,rastreabilidade!$F$1:$H$1,0)),rastreabilidade!$M:$M,$AH24),0)) +IF($AI24="",0,IFERROR(SUMIFS(INDEX(rastreabilidade!$F:$H,0,MATCH(X$3,rastreabilidade!$F$1:$H$1,0)),rastreabilidade!$M:$M,$AI24),0)) +IF($AJ24="",0,IFERROR(SUMIFS(INDEX(rastreabilidade!$F:$H,0,MATCH(X$3,rastreabilidade!$F$1:$H$1,0)),rastreabilidade!$M:$M,$AJ24),0)) -IF($AC24="",0,IFERROR(SUMIFS(INDEX(rastreabilidade!$F:$H,0,MATCH(X$3,rastreabilidade!$F$1:$H$1,0)),rastreabilidade!$M:$M,$AC24,rastreabilidade!$N:$N,$AN24),0)) -IF($AD24="",0,IFERROR(SUMIFS(INDEX(rastreabilidade!$F:$H,0,MATCH(X$3,rastreabilidade!$F$1:$H$1,0)),rastreabilidade!$M:$M,$AD24,rastreabilidade!$N:$N,$AN24),0)) -IF($AE24="",0,IFERROR(SUMIFS(INDEX(rastreabilidade!$F:$H,0,MATCH(X$3,rastreabilidade!$F$1:$H$1,0)),rastreabilidade!$M:$M,$AE24,rastreabilidade!$N:$N,$AN24),0)) -IF($AF24="",0,IFERROR(SUMIFS(INDEX(rastreabilidade!$F:$H,0,MATCH(X$3,rastreabilidade!$F$1:$H$1,0)),rastreabilidade!$M:$M,$AF24,rastreabilidade!$N:$N,$AN24),0)) -> 0 | Y24: =IFERROR(SUMIFS(INDEX(rastreabilidade!$F:$H,0,MATCH(Y$3,rastreabilidade!$F$1:$H$1,0)),rastreabilidade!$N:$N,$AN24),0)*IF($AB24="sim",-1,1) +IF($AG24="",0,IFERROR(SUMIFS(INDEX(rastreabilidade!$F:$H,0,MATCH(Y$3,rastreabilidade!$F$1:$H$1,0)),rastreabilidade!$M:$M,$AG24),0)) +IF($AH24="",0,IFERROR(SUMIFS(INDEX(rastreabilidade!$F:$H,0,MATCH(Y$3,rastreabilidade!$F$1:$H$1,0)),rastreabilidade!$M:$M,$AH24),0)) +IF($AI24="",0,IFERROR(SUMIFS(INDEX(rastreabilidade!$F:$H,0,MATCH(Y$3,rastreabilidade!$F$1:$H$1,0)),rastreabilidade!$M:$M,$AI24),0)) +IF($AJ24="",0,IFERROR(SUMIFS(INDEX(rastreabilidade!$F:$H,0,MATCH(Y$3,rastreabilidade!$F$1:$H$1,0)),rastreabilidade!$M:$M,$AJ24),0)) -IF($AC24="",0,IFERROR(SUMIFS(INDEX(rastreabilidade!$F:$H,0,MATCH(Y$3,rastreabilidade!$F$1:$H$1,0)),rastreabilidade!$M:$M,$AC24,rastreabilidade!$N:$N,$AN24),0)) -IF($AD24="",0,IFERROR(SUMIFS(INDEX(rastreabilidade!$F:$H,0,MATCH(Y$3,rastreabilidade!$F$1:$H$1,0)),rastreabilidade!$M:$M,$AD24,rastreabilidade!$N:$N,$AN24),0)) -IF($AE24="",0,IFERROR(SUMIFS(INDEX(rastreabilidade!$F:$H,0,MATCH(Y$3,rastreabilidade!$F$1:$H$1,0)),rastreabilidade!$M:$M,$AE24,rastreabilidade!$N:$N,$AN24),0)) -IF($AF24="",0,IFERROR(SUMIFS(INDEX(rastreabilidade!$F:$H,0,MATCH(Y$3,rastreabilidade!$F$1:$H$1,0)),rastreabilidade!$M:$M,$AF24,rastreabilidade!$N:$N,$AN24),0)) -> 0 | AA24: {=_xlfn.LET( _xlpm.mem,Z24, _xlpm.retiradas,AC24:AF24, _xlpm.adicoes,AG24:AJ24, _xlpm.memAjustada,_xlfn.REDUCE(_xlpm.mem,_xlpm.retiradas,_xlfn.LAMBDA(_xlpm.x,_xlpm.y,IF(_xlpm.y<>"",SUBSTITUTE(_xlpm.x," + ("&_xlpm.y&")",""),_xlpm.x))), _xlpm.memRemovida,_xlfn.REDUCE(_xlpm.memAjustada,_xlpm.retiradas,_xlfn.LAMBDA(_xlpm.x,_xlpm.y,IF(_xlpm.y<>"",SUBSTITUTE(_xlpm.x,"("&_xlpm.y&")",""),_xlpm.x))), _xlpm.memSemSinal,IF(OR(LEFT(_xlpm.memRemovida,3)=" + ",LEFT(_xlpm.memRemovida,3)=" - "),MID(_xlpm.memRemovida,4,LEN(_xlpm.memRemovida)),_xlpm.memRemovida), _xlpm.memFinal,IF(OR(RIGHT(_xlpm.memSemSinal,3)=" + ",RIGHT(_xlpm.memSemSinal,3)=" - "),LEFT(_xlpm.memSemSinal,LEN(_xlpm.memSemSinal)-3),_xlpm.memSemSinal), _xlpm.adicoesTxt,_xlfn.TEXTJOIN(" + ",TRUE,IF(_xlpm.adicoes<>"","("&_xlpm.adicoes&")","")), IF(_xlpm.memFinal="",_xlpm.adicoesTxt,IF(_xlpm.adicoesTxt="",_xlpm.memFinal,_xlpm.memFinal&" + "&_xlpm.adicoesTxt)) )} | AM24: =_xlfn.TEXTJOIN("|",TRUE,A24,"Ativo","Não Circulante") -> Impostos Diferidos|Ativo|Não Circulante | AN24: =_xlfn.CONCAT(S24,"|","DRE","|","DRE",) -> +/- Variações Cambiais|DRE|DRE
A25: Impostos a recuperar/Crédito tributário | B25: =IFERROR(SUMIFS(INDEX(rastreabilidade!$F:$H,0,MATCH($B$2,rastreabilidade!$F$1:$H$1,0)),rastreabilidade!$K:$K,$A25,rastreabilidade!$D:$D,"Sim"),0) -> 0 | E25: =IFERROR(SUMIFS(INDEX(rastreabilidade!$F:$H,0,MATCH(E$3,rastreabilidade!$F$1:$H$1,0)),rastreabilidade!$N:$N,$AM25),0) +IF($N25="",0,IFERROR(SUMIFS(INDEX(rastreabilidade!$F:$H,0,MATCH(E$3,rastreabilidade!$F$1:$H$1,0)),rastreabilidade!$M:$M,$N25),0)) +IF($O25="",0,IFERROR(SUMIFS(INDEX(rastreabilidade!$F:$H,0,MATCH(E$3,rastreabilidade!$F$1:$H$1,0)),rastreabilidade!$M:$M,$O25),0)) +IF($P25="",0,IFERROR(SUMIFS(INDEX(rastreabilidade!$F:$H,0,MATCH(E$3,rastreabilidade!$F$1:$H$1,0)),rastreabilidade!$M:$M,$P25),0)) +IF($Q25="",0,IFERROR(SUMIFS(INDEX(rastreabilidade!$F:$H,0,MATCH(E$3,rastreabilidade!$F$1:$H$1,0)),rastreabilidade!$M:$M,$Q25),0)) -IF($J25="",0,IFERROR(SUMIFS(INDEX(rastreabilidade!$F:$H,0,MATCH(E$3,rastreabilidade!$F$1:$H$1,0)),rastreabilidade!$M:$M,$J25,rastreabilidade!$N:$N,$AM25),0)) -IF($K25="",0,IFERROR(SUMIFS(INDEX(rastreabilidade!$F:$H,0,MATCH(E$3,rastreabilidade!$F$1:$H$1,0)),rastreabilidade!$M:$M,$K25,rastreabilidade!$N:$N,$AM25),0)) -IF($L25="",0,IFERROR(SUMIFS(INDEX(rastreabilidade!$F:$H,0,MATCH(E$3,rastreabilidade!$F$1:$H$1,0)),rastreabilidade!$M:$M,$L25,rastreabilidade!$N:$N,$AM25),0)) -IF($M25="",0,IFERROR(SUMIFS(INDEX(rastreabilidade!$F:$H,0,MATCH(E$3,rastreabilidade!$F$1:$H$1,0)),rastreabilidade!$M:$M,$M25,rastreabilidade!$N:$N,$AM25),0)) -> 0 | F25: =IFERROR(SUMIFS(INDEX(rastreabilidade!$F:$H,0,MATCH(F$3,rastreabilidade!$F$1:$H$1,0)),rastreabilidade!$N:$N,$AM25),0) +IF($N25="",0,IFERROR(SUMIFS(INDEX(rastreabilidade!$F:$H,0,MATCH(F$3,rastreabilidade!$F$1:$H$1,0)),rastreabilidade!$M:$M,$N25),0)) +IF($O25="",0,IFERROR(SUMIFS(INDEX(rastreabilidade!$F:$H,0,MATCH(F$3,rastreabilidade!$F$1:$H$1,0)),rastreabilidade!$M:$M,$O25),0)) +IF($P25="",0,IFERROR(SUMIFS(INDEX(rastreabilidade!$F:$H,0,MATCH(F$3,rastreabilidade!$F$1:$H$1,0)),rastreabilidade!$M:$M,$P25),0)) +IF($Q25="",0,IFERROR(SUMIFS(INDEX(rastreabilidade!$F:$H,0,MATCH(F$3,rastreabilidade!$F$1:$H$1,0)),rastreabilidade!$M:$M,$Q25),0)) -IF($J25="",0,IFERROR(SUMIFS(INDEX(rastreabilidade!$F:$H,0,MATCH(F$3,rastreabilidade!$F$1:$H$1,0)),rastreabilidade!$M:$M,$J25,rastreabilidade!$N:$N,$AM25),0)) -IF($K25="",0,IFERROR(SUMIFS(INDEX(rastreabilidade!$F:$H,0,MATCH(F$3,rastreabilidade!$F$1:$H$1,0)),rastreabilidade!$M:$M,$K25,rastreabilidade!$N:$N,$AM25),0)) -IF($L25="",0,IFERROR(SUMIFS(INDEX(rastreabilidade!$F:$H,0,MATCH(F$3,rastreabilidade!$F$1:$H$1,0)),rastreabilidade!$M:$M,$L25,rastreabilidade!$N:$N,$AM25),0)) -IF($M25="",0,IFERROR(SUMIFS(INDEX(rastreabilidade!$F:$H,0,MATCH(F$3,rastreabilidade!$F$1:$H$1,0)),rastreabilidade!$M:$M,$M25,rastreabilidade!$N:$N,$AM25),0)) -> 0 | G25: =IFERROR(SUMIFS(INDEX(rastreabilidade!$F:$H,0,MATCH(G$3,rastreabilidade!$F$1:$H$1,0)),rastreabilidade!$N:$N,$AM25),0) +IF($N25="",0,IFERROR(SUMIFS(INDEX(rastreabilidade!$F:$H,0,MATCH(G$3,rastreabilidade!$F$1:$H$1,0)),rastreabilidade!$M:$M,$N25),0)) +IF($O25="",0,IFERROR(SUMIFS(INDEX(rastreabilidade!$F:$H,0,MATCH(G$3,rastreabilidade!$F$1:$H$1,0)),rastreabilidade!$M:$M,$O25),0)) +IF($P25="",0,IFERROR(SUMIFS(INDEX(rastreabilidade!$F:$H,0,MATCH(G$3,rastreabilidade!$F$1:$H$1,0)),rastreabilidade!$M:$M,$P25),0)) +IF($Q25="",0,IFERROR(SUMIFS(INDEX(rastreabilidade!$F:$H,0,MATCH(G$3,rastreabilidade!$F$1:$H$1,0)),rastreabilidade!$M:$M,$Q25),0)) -IF($J25="",0,IFERROR(SUMIFS(INDEX(rastreabilidade!$F:$H,0,MATCH(G$3,rastreabilidade!$F$1:$H$1,0)),rastreabilidade!$M:$M,$J25,rastreabilidade!$N:$N,$AM25),0)) -IF($K25="",0,IFERROR(SUMIFS(INDEX(rastreabilidade!$F:$H,0,MATCH(G$3,rastreabilidade!$F$1:$H$1,0)),rastreabilidade!$M:$M,$K25,rastreabilidade!$N:$N,$AM25),0)) -IF($L25="",0,IFERROR(SUMIFS(INDEX(rastreabilidade!$F:$H,0,MATCH(G$3,rastreabilidade!$F$1:$H$1,0)),rastreabilidade!$M:$M,$L25,rastreabilidade!$N:$N,$AM25),0)) -IF($M25="",0,IFERROR(SUMIFS(INDEX(rastreabilidade!$F:$H,0,MATCH(G$3,rastreabilidade!$F$1:$H$1,0)),rastreabilidade!$M:$M,$M25,rastreabilidade!$N:$N,$AM25),0)) -> 0 | I25: {=_xlfn.LET( _xlpm.mem,H25, _xlpm.retiradas,J25:M25, _xlpm.adicoes,N25:Q25, _xlpm.memAjustada,_xlfn.REDUCE(_xlpm.mem,_xlpm.retiradas,_xlfn.LAMBDA(_xlpm.x,_xlpm.y,IF(_xlpm.y<>"",SUBSTITUTE(_xlpm.x," + ("&_xlpm.y&")",""),_xlpm.x))), _xlpm.memRemovida,_xlfn.REDUCE(_xlpm.memAjustada,_xlpm.retiradas,_xlfn.LAMBDA(_xlpm.x,_xlpm.y,IF(_xlpm.y<>"",SUBSTITUTE(_xlpm.x,"("&_xlpm.y&")",""),_xlpm.x))), _xlpm.memSemSinal,IF(OR(LEFT(_xlpm.memRemovida,3)=" + ",LEFT(_xlpm.memRemovida,3)=" - "),MID(_xlpm.memRemovida,4,LEN(_xlpm.memRemovida)),_xlpm.memRemovida), _xlpm.memFinal,IF(OR(RIGHT(_xlpm.memSemSinal,3)=" + ",RIGHT(_xlpm.memSemSinal,3)=" - "),LEFT(_xlpm.memSemSinal,LEN(_xlpm.memSemSinal)-3),_xlpm.memSemSinal), _xlpm.adicoesTxt,_xlfn.TEXTJOIN(" + ",TRUE,IF(_xlpm.adicoes<>"","("&_xlpm.adicoes&")","")), IF(_xlpm.memFinal="",_xlpm.adicoesTxt,IF(_xlpm.adicoesTxt="",_xlpm.memFinal,_xlpm.memFinal&" + "&_xlpm.adicoesTxt)) )} | S25: +/- Equivalência Patrimonial | T25: =IFERROR(SUMIFS(INDEX(rastreabilidade!$F:$H,0,MATCH($T$2,rastreabilidade!$F$1:$H$1,0)),rastreabilidade!$K:$K,$S25,rastreabilidade!$D:$D,"Sim"),0) -> 0 | W25: =IFERROR(SUMIFS(INDEX(rastreabilidade!$F:$H,0,MATCH(W$3,rastreabilidade!$F$1:$H$1,0)),rastreabilidade!$N:$N,$AN25),0)*IF($AB25="sim",-1,1) +IF($AG25="",0,IFERROR(SUMIFS(INDEX(rastreabilidade!$F:$H,0,MATCH(W$3,rastreabilidade!$F$1:$H$1,0)),rastreabilidade!$M:$M,$AG25),0)) +IF($AH25="",0,IFERROR(SUMIFS(INDEX(rastreabilidade!$F:$H,0,MATCH(W$3,rastreabilidade!$F$1:$H$1,0)),rastreabilidade!$M:$M,$AH25),0)) +IF($AI25="",0,IFERROR(SUMIFS(INDEX(rastreabilidade!$F:$H,0,MATCH(W$3,rastreabilidade!$F$1:$H$1,0)),rastreabilidade!$M:$M,$AI25),0)) +IF($AJ25="",0,IFERROR(SUMIFS(INDEX(rastreabilidade!$F:$H,0,MATCH(W$3,rastreabilidade!$F$1:$H$1,0)),rastreabilidade!$M:$M,$AJ25),0)) -IF($AC25="",0,IFERROR(SUMIFS(INDEX(rastreabilidade!$F:$H,0,MATCH(W$3,rastreabilidade!$F$1:$H$1,0)),rastreabilidade!$M:$M,$AC25,rastreabilidade!$N:$N,$AN25),0)) -IF($AD25="",0,IFERROR(SUMIFS(INDEX(rastreabilidade!$F:$H,0,MATCH(W$3,rastreabilidade!$F$1:$H$1,0)),rastreabilidade!$M:$M,$AD25,rastreabilidade!$N:$N,$AN25),0)) -IF($AE25="",0,IFERROR(SUMIFS(INDEX(rastreabilidade!$F:$H,0,MATCH(W$3,rastreabilidade!$F$1:$H$1,0)),rastreabilidade!$M:$M,$AE25,rastreabilidade!$N:$N,$AN25),0)) -IF($AF25="",0,IFERROR(SUMIFS(INDEX(rastreabilidade!$F:$H,0,MATCH(W$3,rastreabilidade!$F$1:$H$1,0)),rastreabilidade!$M:$M,$AF25,rastreabilidade!$N:$N,$AN25),0)) -> 0 | X25: =IFERROR(SUMIFS(INDEX(rastreabilidade!$F:$H,0,MATCH(X$3,rastreabilidade!$F$1:$H$1,0)),rastreabilidade!$N:$N,$AN25),0)*IF($AB25="sim",-1,1) +IF($AG25="",0,IFERROR(SUMIFS(INDEX(rastreabilidade!$F:$H,0,MATCH(X$3,rastreabilidade!$F$1:$H$1,0)),rastreabilidade!$M:$M,$AG25),0)) +IF($AH25="",0,IFERROR(SUMIFS(INDEX(rastreabilidade!$F:$H,0,MATCH(X$3,rastreabilidade!$F$1:$H$1,0)),rastreabilidade!$M:$M,$AH25),0)) +IF($AI25="",0,IFERROR(SUMIFS(INDEX(rastreabilidade!$F:$H,0,MATCH(X$3,rastreabilidade!$F$1:$H$1,0)),rastreabilidade!$M:$M,$AI25),0)) +IF($AJ25="",0,IFERROR(SUMIFS(INDEX(rastreabilidade!$F:$H,0,MATCH(X$3,rastreabilidade!$F$1:$H$1,0)),rastreabilidade!$M:$M,$AJ25),0)) -IF($AC25="",0,IFERROR(SUMIFS(INDEX(rastreabilidade!$F:$H,0,MATCH(X$3,rastreabilidade!$F$1:$H$1,0)),rastreabilidade!$M:$M,$AC25,rastreabilidade!$N:$N,$AN25),0)) -IF($AD25="",0,IFERROR(SUMIFS(INDEX(rastreabilidade!$F:$H,0,MATCH(X$3,rastreabilidade!$F$1:$H$1,0)),rastreabilidade!$M:$M,$AD25,rastreabilidade!$N:$N,$AN25),0)) -IF($AE25="",0,IFERROR(SUMIFS(INDEX(rastreabilidade!$F:$H,0,MATCH(X$3,rastreabilidade!$F$1:$H$1,0)),rastreabilidade!$M:$M,$AE25,rastreabilidade!$N:$N,$AN25),0)) -IF($AF25="",0,IFERROR(SUMIFS(INDEX(rastreabilidade!$F:$H,0,MATCH(X$3,rastreabilidade!$F$1:$H$1,0)),rastreabilidade!$M:$M,$AF25,rastreabilidade!$N:$N,$AN25),0)) -> 0 | Y25: =IFERROR(SUMIFS(INDEX(rastreabilidade!$F:$H,0,MATCH(Y$3,rastreabilidade!$F$1:$H$1,0)),rastreabilidade!$N:$N,$AN25),0)*IF($AB25="sim",-1,1) +IF($AG25="",0,IFERROR(SUMIFS(INDEX(rastreabilidade!$F:$H,0,MATCH(Y$3,rastreabilidade!$F$1:$H$1,0)),rastreabilidade!$M:$M,$AG25),0)) +IF($AH25="",0,IFERROR(SUMIFS(INDEX(rastreabilidade!$F:$H,0,MATCH(Y$3,rastreabilidade!$F$1:$H$1,0)),rastreabilidade!$M:$M,$AH25),0)) +IF($AI25="",0,IFERROR(SUMIFS(INDEX(rastreabilidade!$F:$H,0,MATCH(Y$3,rastreabilidade!$F$1:$H$1,0)),rastreabilidade!$M:$M,$AI25),0)) +IF($AJ25="",0,IFERROR(SUMIFS(INDEX(rastreabilidade!$F:$H,0,MATCH(Y$3,rastreabilidade!$F$1:$H$1,0)),rastreabilidade!$M:$M,$AJ25),0)) -IF($AC25="",0,IFERROR(SUMIFS(INDEX(rastreabilidade!$F:$H,0,MATCH(Y$3,rastreabilidade!$F$1:$H$1,0)),rastreabilidade!$M:$M,$AC25,rastreabilidade!$N:$N,$AN25),0)) -IF($AD25="",0,IFERROR(SUMIFS(INDEX(rastreabilidade!$F:$H,0,MATCH(Y$3,rastreabilidade!$F$1:$H$1,0)),rastreabilidade!$M:$M,$AD25,rastreabilidade!$N:$N,$AN25),0)) -IF($AE25="",0,IFERROR(SUMIFS(INDEX(rastreabilidade!$F:$H,0,MATCH(Y$3,rastreabilidade!$F$1:$H$1,0)),rastreabilidade!$M:$M,$AE25,rastreabilidade!$N:$N,$AN25),0)) -IF($AF25="",0,IFERROR(SUMIFS(INDEX(rastreabilidade!$F:$H,0,MATCH(Y$3,rastreabilidade!$F$1:$H$1,0)),rastreabilidade!$M:$M,$AF25,rastreabilidade!$N:$N,$AN25),0)) -> 0 | AA25: {=_xlfn.LET( _xlpm.mem,Z25, _xlpm.retiradas,AC25:AF25, _xlpm.adicoes,AG25:AJ25, _xlpm.memAjustada,_xlfn.REDUCE(_xlpm.mem,_xlpm.retiradas,_xlfn.LAMBDA(_xlpm.x,_xlpm.y,IF(_xlpm.y<>"",SUBSTITUTE(_xlpm.x," + ("&_xlpm.y&")",""),_xlpm.x))), _xlpm.memRemovida,_xlfn.REDUCE(_xlpm.memAjustada,_xlpm.retiradas,_xlfn.LAMBDA(_xlpm.x,_xlpm.y,IF(_xlpm.y<>"",SUBSTITUTE(_xlpm.x,"("&_xlpm.y&")",""),_xlpm.x))), _xlpm.memSemSinal,IF(OR(LEFT(_xlpm.memRemovida,3)=" + ",LEFT(_xlpm.memRemovida,3)=" - "),MID(_xlpm.memRemovida,4,LEN(_xlpm.memRemovida)),_xlpm.memRemovida), _xlpm.memFinal,IF(OR(RIGHT(_xlpm.memSemSinal,3)=" + ",RIGHT(_xlpm.memSemSinal,3)=" - "),LEFT(_xlpm.memSemSinal,LEN(_xlpm.memSemSinal)-3),_xlpm.memSemSinal), _xlpm.adicoesTxt,_xlfn.TEXTJOIN(" + ",TRUE,IF(_xlpm.adicoes<>"","("&_xlpm.adicoes&")","")), IF(_xlpm.memFinal="",_xlpm.adicoesTxt,IF(_xlpm.adicoesTxt="",_xlpm.memFinal,_xlpm.memFinal&" + "&_xlpm.adicoesTxt)) )} | AM25: =_xlfn.TEXTJOIN("|",TRUE,A25,"Ativo","Não Circulante") -> Impostos a recuperar/Crédito tributário|Ativo|Não Circulante | AN25: =_xlfn.CONCAT(S25,"|","DRE","|","DRE",) -> +/- Equivalência Patrimonial|DRE|DRE
A26: Mútuo Financeiro LP | B26: =IFERROR(SUMIFS(INDEX(rastreabilidade!$F:$H,0,MATCH($B$2,rastreabilidade!$F$1:$H$1,0)),rastreabilidade!$K:$K,$A26,rastreabilidade!$D:$D,"Sim"),0) -> 0 | E26: =IFERROR(SUMIFS(INDEX(rastreabilidade!$F:$H,0,MATCH(E$3,rastreabilidade!$F$1:$H$1,0)),rastreabilidade!$N:$N,$AM26),0) +IF($N26="",0,IFERROR(SUMIFS(INDEX(rastreabilidade!$F:$H,0,MATCH(E$3,rastreabilidade!$F$1:$H$1,0)),rastreabilidade!$M:$M,$N26),0)) +IF($O26="",0,IFERROR(SUMIFS(INDEX(rastreabilidade!$F:$H,0,MATCH(E$3,rastreabilidade!$F$1:$H$1,0)),rastreabilidade!$M:$M,$O26),0)) +IF($P26="",0,IFERROR(SUMIFS(INDEX(rastreabilidade!$F:$H,0,MATCH(E$3,rastreabilidade!$F$1:$H$1,0)),rastreabilidade!$M:$M,$P26),0)) +IF($Q26="",0,IFERROR(SUMIFS(INDEX(rastreabilidade!$F:$H,0,MATCH(E$3,rastreabilidade!$F$1:$H$1,0)),rastreabilidade!$M:$M,$Q26),0)) -IF($J26="",0,IFERROR(SUMIFS(INDEX(rastreabilidade!$F:$H,0,MATCH(E$3,rastreabilidade!$F$1:$H$1,0)),rastreabilidade!$M:$M,$J26,rastreabilidade!$N:$N,$AM26),0)) -IF($K26="",0,IFERROR(SUMIFS(INDEX(rastreabilidade!$F:$H,0,MATCH(E$3,rastreabilidade!$F$1:$H$1,0)),rastreabilidade!$M:$M,$K26,rastreabilidade!$N:$N,$AM26),0)) -IF($L26="",0,IFERROR(SUMIFS(INDEX(rastreabilidade!$F:$H,0,MATCH(E$3,rastreabilidade!$F$1:$H$1,0)),rastreabilidade!$M:$M,$L26,rastreabilidade!$N:$N,$AM26),0)) -IF($M26="",0,IFERROR(SUMIFS(INDEX(rastreabilidade!$F:$H,0,MATCH(E$3,rastreabilidade!$F$1:$H$1,0)),rastreabilidade!$M:$M,$M26,rastreabilidade!$N:$N,$AM26),0)) -> 0 | F26: =IFERROR(SUMIFS(INDEX(rastreabilidade!$F:$H,0,MATCH(F$3,rastreabilidade!$F$1:$H$1,0)),rastreabilidade!$N:$N,$AM26),0) +IF($N26="",0,IFERROR(SUMIFS(INDEX(rastreabilidade!$F:$H,0,MATCH(F$3,rastreabilidade!$F$1:$H$1,0)),rastreabilidade!$M:$M,$N26),0)) +IF($O26="",0,IFERROR(SUMIFS(INDEX(rastreabilidade!$F:$H,0,MATCH(F$3,rastreabilidade!$F$1:$H$1,0)),rastreabilidade!$M:$M,$O26),0)) +IF($P26="",0,IFERROR(SUMIFS(INDEX(rastreabilidade!$F:$H,0,MATCH(F$3,rastreabilidade!$F$1:$H$1,0)),rastreabilidade!$M:$M,$P26),0)) +IF($Q26="",0,IFERROR(SUMIFS(INDEX(rastreabilidade!$F:$H,0,MATCH(F$3,rastreabilidade!$F$1:$H$1,0)),rastreabilidade!$M:$M,$Q26),0)) -IF($J26="",0,IFERROR(SUMIFS(INDEX(rastreabilidade!$F:$H,0,MATCH(F$3,rastreabilidade!$F$1:$H$1,0)),rastreabilidade!$M:$M,$J26,rastreabilidade!$N:$N,$AM26),0)) -IF($K26="",0,IFERROR(SUMIFS(INDEX(rastreabilidade!$F:$H,0,MATCH(F$3,rastreabilidade!$F$1:$H$1,0)),rastreabilidade!$M:$M,$K26,rastreabilidade!$N:$N,$AM26),0)) -IF($L26="",0,IFERROR(SUMIFS(INDEX(rastreabilidade!$F:$H,0,MATCH(F$3,rastreabilidade!$F$1:$H$1,0)),rastreabilidade!$M:$M,$L26,rastreabilidade!$N:$N,$AM26),0)) -IF($M26="",0,IFERROR(SUMIFS(INDEX(rastreabilidade!$F:$H,0,MATCH(F$3,rastreabilidade!$F$1:$H$1,0)),rastreabilidade!$M:$M,$M26,rastreabilidade!$N:$N,$AM26),0)) -> 0 | G26: =IFERROR(SUMIFS(INDEX(rastreabilidade!$F:$H,0,MATCH(G$3,rastreabilidade!$F$1:$H$1,0)),rastreabilidade!$N:$N,$AM26),0) +IF($N26="",0,IFERROR(SUMIFS(INDEX(rastreabilidade!$F:$H,0,MATCH(G$3,rastreabilidade!$F$1:$H$1,0)),rastreabilidade!$M:$M,$N26),0)) +IF($O26="",0,IFERROR(SUMIFS(INDEX(rastreabilidade!$F:$H,0,MATCH(G$3,rastreabilidade!$F$1:$H$1,0)),rastreabilidade!$M:$M,$O26),0)) +IF($P26="",0,IFERROR(SUMIFS(INDEX(rastreabilidade!$F:$H,0,MATCH(G$3,rastreabilidade!$F$1:$H$1,0)),rastreabilidade!$M:$M,$P26),0)) +IF($Q26="",0,IFERROR(SUMIFS(INDEX(rastreabilidade!$F:$H,0,MATCH(G$3,rastreabilidade!$F$1:$H$1,0)),rastreabilidade!$M:$M,$Q26),0)) -IF($J26="",0,IFERROR(SUMIFS(INDEX(rastreabilidade!$F:$H,0,MATCH(G$3,rastreabilidade!$F$1:$H$1,0)),rastreabilidade!$M:$M,$J26,rastreabilidade!$N:$N,$AM26),0)) -IF($K26="",0,IFERROR(SUMIFS(INDEX(rastreabilidade!$F:$H,0,MATCH(G$3,rastreabilidade!$F$1:$H$1,0)),rastreabilidade!$M:$M,$K26,rastreabilidade!$N:$N,$AM26),0)) -IF($L26="",0,IFERROR(SUMIFS(INDEX(rastreabilidade!$F:$H,0,MATCH(G$3,rastreabilidade!$F$1:$H$1,0)),rastreabilidade!$M:$M,$L26,rastreabilidade!$N:$N,$AM26),0)) -IF($M26="",0,IFERROR(SUMIFS(INDEX(rastreabilidade!$F:$H,0,MATCH(G$3,rastreabilidade!$F$1:$H$1,0)),rastreabilidade!$M:$M,$M26,rastreabilidade!$N:$N,$AM26),0)) -> 0 | I26: {=_xlfn.LET( _xlpm.mem,H26, _xlpm.retiradas,J26:M26, _xlpm.adicoes,N26:Q26, _xlpm.memAjustada,_xlfn.REDUCE(_xlpm.mem,_xlpm.retiradas,_xlfn.LAMBDA(_xlpm.x,_xlpm.y,IF(_xlpm.y<>"",SUBSTITUTE(_xlpm.x," + ("&_xlpm.y&")",""),_xlpm.x))), _xlpm.memRemovida,_xlfn.REDUCE(_xlpm.memAjustada,_xlpm.retiradas,_xlfn.LAMBDA(_xlpm.x,_xlpm.y,IF(_xlpm.y<>"",SUBSTITUTE(_xlpm.x,"("&_xlpm.y&")",""),_xlpm.x))), _xlpm.memSemSinal,IF(OR(LEFT(_xlpm.memRemovida,3)=" + ",LEFT(_xlpm.memRemovida,3)=" - "),MID(_xlpm.memRemovida,4,LEN(_xlpm.memRemovida)),_xlpm.memRemovida), _xlpm.memFinal,IF(OR(RIGHT(_xlpm.memSemSinal,3)=" + ",RIGHT(_xlpm.memSemSinal,3)=" - "),LEFT(_xlpm.memSemSinal,LEN(_xlpm.memSemSinal)-3),_xlpm.memSemSinal), _xlpm.adicoesTxt,_xlfn.TEXTJOIN(" + ",TRUE,IF(_xlpm.adicoes<>"","("&_xlpm.adicoes&")","")), IF(_xlpm.memFinal="",_xlpm.adicoesTxt,IF(_xlpm.adicoesTxt="",_xlpm.memFinal,_xlpm.memFinal&" + "&_xlpm.adicoesTxt)) )} | S26: Lucro antes de Impostos e Extraordinários | T26: =+T15+T23+T24+T25 -> 0 | W26: =+W15+W23+W24+W25 -> 0 | X26: =+X15+X23+X24+X25 -> 0 | Y26: =+Y15+Y23+Y24+Y25 -> 0 | AM26: =_xlfn.TEXTJOIN("|",TRUE,A26,"Ativo","Não Circulante") -> Mútuo Financeiro LP|Ativo|Não Circulante | AN26: =_xlfn.CONCAT(S26,"|","DRE","|","DRE",) -> Lucro antes de Impostos e Extraordinários|DRE|DRE
A27: Aplicações Financeiras de LP | B27: =IFERROR(SUMIFS(INDEX(rastreabilidade!$F:$H,0,MATCH($B$2,rastreabilidade!$F$1:$H$1,0)),rastreabilidade!$K:$K,$A27,rastreabilidade!$D:$D,"Sim"),0) -> 0 | E27: =IFERROR(SUMIFS(INDEX(rastreabilidade!$F:$H,0,MATCH(E$3,rastreabilidade!$F$1:$H$1,0)),rastreabilidade!$N:$N,$AM27),0) +IF($N27="",0,IFERROR(SUMIFS(INDEX(rastreabilidade!$F:$H,0,MATCH(E$3,rastreabilidade!$F$1:$H$1,0)),rastreabilidade!$M:$M,$N27),0)) +IF($O27="",0,IFERROR(SUMIFS(INDEX(rastreabilidade!$F:$H,0,MATCH(E$3,rastreabilidade!$F$1:$H$1,0)),rastreabilidade!$M:$M,$O27),0)) +IF($P27="",0,IFERROR(SUMIFS(INDEX(rastreabilidade!$F:$H,0,MATCH(E$3,rastreabilidade!$F$1:$H$1,0)),rastreabilidade!$M:$M,$P27),0)) +IF($Q27="",0,IFERROR(SUMIFS(INDEX(rastreabilidade!$F:$H,0,MATCH(E$3,rastreabilidade!$F$1:$H$1,0)),rastreabilidade!$M:$M,$Q27),0)) -IF($J27="",0,IFERROR(SUMIFS(INDEX(rastreabilidade!$F:$H,0,MATCH(E$3,rastreabilidade!$F$1:$H$1,0)),rastreabilidade!$M:$M,$J27,rastreabilidade!$N:$N,$AM27),0)) -IF($K27="",0,IFERROR(SUMIFS(INDEX(rastreabilidade!$F:$H,0,MATCH(E$3,rastreabilidade!$F$1:$H$1,0)),rastreabilidade!$M:$M,$K27,rastreabilidade!$N:$N,$AM27),0)) -IF($L27="",0,IFERROR(SUMIFS(INDEX(rastreabilidade!$F:$H,0,MATCH(E$3,rastreabilidade!$F$1:$H$1,0)),rastreabilidade!$M:$M,$L27,rastreabilidade!$N:$N,$AM27),0)) -IF($M27="",0,IFERROR(SUMIFS(INDEX(rastreabilidade!$F:$H,0,MATCH(E$3,rastreabilidade!$F$1:$H$1,0)),rastreabilidade!$M:$M,$M27,rastreabilidade!$N:$N,$AM27),0)) -> 0 | F27: =IFERROR(SUMIFS(INDEX(rastreabilidade!$F:$H,0,MATCH(F$3,rastreabilidade!$F$1:$H$1,0)),rastreabilidade!$N:$N,$AM27),0) +IF($N27="",0,IFERROR(SUMIFS(INDEX(rastreabilidade!$F:$H,0,MATCH(F$3,rastreabilidade!$F$1:$H$1,0)),rastreabilidade!$M:$M,$N27),0)) +IF($O27="",0,IFERROR(SUMIFS(INDEX(rastreabilidade!$F:$H,0,MATCH(F$3,rastreabilidade!$F$1:$H$1,0)),rastreabilidade!$M:$M,$O27),0)) +IF($P27="",0,IFERROR(SUMIFS(INDEX(rastreabilidade!$F:$H,0,MATCH(F$3,rastreabilidade!$F$1:$H$1,0)),rastreabilidade!$M:$M,$P27),0)) +IF($Q27="",0,IFERROR(SUMIFS(INDEX(rastreabilidade!$F:$H,0,MATCH(F$3,rastreabilidade!$F$1:$H$1,0)),rastreabilidade!$M:$M,$Q27),0)) -IF($J27="",0,IFERROR(SUMIFS(INDEX(rastreabilidade!$F:$H,0,MATCH(F$3,rastreabilidade!$F$1:$H$1,0)),rastreabilidade!$M:$M,$J27,rastreabilidade!$N:$N,$AM27),0)) -IF($K27="",0,IFERROR(SUMIFS(INDEX(rastreabilidade!$F:$H,0,MATCH(F$3,rastreabilidade!$F$1:$H$1,0)),rastreabilidade!$M:$M,$K27,rastreabilidade!$N:$N,$AM27),0)) -IF($L27="",0,IFERROR(SUMIFS(INDEX(rastreabilidade!$F:$H,0,MATCH(F$3,rastreabilidade!$F$1:$H$1,0)),rastreabilidade!$M:$M,$L27,rastreabilidade!$N:$N,$AM27),0)) -IF($M27="",0,IFERROR(SUMIFS(INDEX(rastreabilidade!$F:$H,0,MATCH(F$3,rastreabilidade!$F$1:$H$1,0)),rastreabilidade!$M:$M,$M27,rastreabilidade!$N:$N,$AM27),0)) -> 0 | G27: =IFERROR(SUMIFS(INDEX(rastreabilidade!$F:$H,0,MATCH(G$3,rastreabilidade!$F$1:$H$1,0)),rastreabilidade!$N:$N,$AM27),0) +IF($N27="",0,IFERROR(SUMIFS(INDEX(rastreabilidade!$F:$H,0,MATCH(G$3,rastreabilidade!$F$1:$H$1,0)),rastreabilidade!$M:$M,$N27),0)) +IF($O27="",0,IFERROR(SUMIFS(INDEX(rastreabilidade!$F:$H,0,MATCH(G$3,rastreabilidade!$F$1:$H$1,0)),rastreabilidade!$M:$M,$O27),0)) +IF($P27="",0,IFERROR(SUMIFS(INDEX(rastreabilidade!$F:$H,0,MATCH(G$3,rastreabilidade!$F$1:$H$1,0)),rastreabilidade!$M:$M,$P27),0)) +IF($Q27="",0,IFERROR(SUMIFS(INDEX(rastreabilidade!$F:$H,0,MATCH(G$3,rastreabilidade!$F$1:$H$1,0)),rastreabilidade!$M:$M,$Q27),0)) -IF($J27="",0,IFERROR(SUMIFS(INDEX(rastreabilidade!$F:$H,0,MATCH(G$3,rastreabilidade!$F$1:$H$1,0)),rastreabilidade!$M:$M,$J27,rastreabilidade!$N:$N,$AM27),0)) -IF($K27="",0,IFERROR(SUMIFS(INDEX(rastreabilidade!$F:$H,0,MATCH(G$3,rastreabilidade!$F$1:$H$1,0)),rastreabilidade!$M:$M,$K27,rastreabilidade!$N:$N,$AM27),0)) -IF($L27="",0,IFERROR(SUMIFS(INDEX(rastreabilidade!$F:$H,0,MATCH(G$3,rastreabilidade!$F$1:$H$1,0)),rastreabilidade!$M:$M,$L27,rastreabilidade!$N:$N,$AM27),0)) -IF($M27="",0,IFERROR(SUMIFS(INDEX(rastreabilidade!$F:$H,0,MATCH(G$3,rastreabilidade!$F$1:$H$1,0)),rastreabilidade!$M:$M,$M27,rastreabilidade!$N:$N,$AM27),0)) -> 0 | I27: {=_xlfn.LET( _xlpm.mem,H27, _xlpm.retiradas,J27:M27, _xlpm.adicoes,N27:Q27, _xlpm.memAjustada,_xlfn.REDUCE(_xlpm.mem,_xlpm.retiradas,_xlfn.LAMBDA(_xlpm.x,_xlpm.y,IF(_xlpm.y<>"",SUBSTITUTE(_xlpm.x," + ("&_xlpm.y&")",""),_xlpm.x))), _xlpm.memRemovida,_xlfn.REDUCE(_xlpm.memAjustada,_xlpm.retiradas,_xlfn.LAMBDA(_xlpm.x,_xlpm.y,IF(_xlpm.y<>"",SUBSTITUTE(_xlpm.x,"("&_xlpm.y&")",""),_xlpm.x))), _xlpm.memSemSinal,IF(OR(LEFT(_xlpm.memRemovida,3)=" + ",LEFT(_xlpm.memRemovida,3)=" - "),MID(_xlpm.memRemovida,4,LEN(_xlpm.memRemovida)),_xlpm.memRemovida), _xlpm.memFinal,IF(OR(RIGHT(_xlpm.memSemSinal,3)=" + ",RIGHT(_xlpm.memSemSinal,3)=" - "),LEFT(_xlpm.memSemSinal,LEN(_xlpm.memSemSinal)-3),_xlpm.memSemSinal), _xlpm.adicoesTxt,_xlfn.TEXTJOIN(" + ",TRUE,IF(_xlpm.adicoes<>"","("&_xlpm.adicoes&")","")), IF(_xlpm.memFinal="",_xlpm.adicoesTxt,IF(_xlpm.adicoesTxt="",_xlpm.memFinal,_xlpm.memFinal&" + "&_xlpm.adicoesTxt)) )} | S27: Outros não recorrentes e/ou não operacionais | T27: =IFERROR(SUMIFS(INDEX(rastreabilidade!$F:$H,0,MATCH($T$2,rastreabilidade!$F$1:$H$1,0)),rastreabilidade!$K:$K,$S27,rastreabilidade!$D:$D,"Sim"),0) -> 0 | W27: =IFERROR(SUMIFS(INDEX(rastreabilidade!$F:$H,0,MATCH(W$3,rastreabilidade!$F$1:$H$1,0)),rastreabilidade!$N:$N,$AN27),0)*IF($AB27="sim",-1,1) +IF($AG27="",0,IFERROR(SUMIFS(INDEX(rastreabilidade!$F:$H,0,MATCH(W$3,rastreabilidade!$F$1:$H$1,0)),rastreabilidade!$M:$M,$AG27),0)) +IF($AH27="",0,IFERROR(SUMIFS(INDEX(rastreabilidade!$F:$H,0,MATCH(W$3,rastreabilidade!$F$1:$H$1,0)),rastreabilidade!$M:$M,$AH27),0)) +IF($AI27="",0,IFERROR(SUMIFS(INDEX(rastreabilidade!$F:$H,0,MATCH(W$3,rastreabilidade!$F$1:$H$1,0)),rastreabilidade!$M:$M,$AI27),0)) +IF($AJ27="",0,IFERROR(SUMIFS(INDEX(rastreabilidade!$F:$H,0,MATCH(W$3,rastreabilidade!$F$1:$H$1,0)),rastreabilidade!$M:$M,$AJ27),0)) -IF($AC27="",0,IFERROR(SUMIFS(INDEX(rastreabilidade!$F:$H,0,MATCH(W$3,rastreabilidade!$F$1:$H$1,0)),rastreabilidade!$M:$M,$AC27,rastreabilidade!$N:$N,$AN27),0)) -IF($AD27="",0,IFERROR(SUMIFS(INDEX(rastreabilidade!$F:$H,0,MATCH(W$3,rastreabilidade!$F$1:$H$1,0)),rastreabilidade!$M:$M,$AD27,rastreabilidade!$N:$N,$AN27),0)) -IF($AE27="",0,IFERROR(SUMIFS(INDEX(rastreabilidade!$F:$H,0,MATCH(W$3,rastreabilidade!$F$1:$H$1,0)),rastreabilidade!$M:$M,$AE27,rastreabilidade!$N:$N,$AN27),0)) -IF($AF27="",0,IFERROR(SUMIFS(INDEX(rastreabilidade!$F:$H,0,MATCH(W$3,rastreabilidade!$F$1:$H$1,0)),rastreabilidade!$M:$M,$AF27,rastreabilidade!$N:$N,$AN27),0)) -> 0 | X27: =IFERROR(SUMIFS(INDEX(rastreabilidade!$F:$H,0,MATCH(X$3,rastreabilidade!$F$1:$H$1,0)),rastreabilidade!$N:$N,$AN27),0)*IF($AB27="sim",-1,1) +IF($AG27="",0,IFERROR(SUMIFS(INDEX(rastreabilidade!$F:$H,0,MATCH(X$3,rastreabilidade!$F$1:$H$1,0)),rastreabilidade!$M:$M,$AG27),0)) +IF($AH27="",0,IFERROR(SUMIFS(INDEX(rastreabilidade!$F:$H,0,MATCH(X$3,rastreabilidade!$F$1:$H$1,0)),rastreabilidade!$M:$M,$AH27),0)) +IF($AI27="",0,IFERROR(SUMIFS(INDEX(rastreabilidade!$F:$H,0,MATCH(X$3,rastreabilidade!$F$1:$H$1,0)),rastreabilidade!$M:$M,$AI27),0)) +IF($AJ27="",0,IFERROR(SUMIFS(INDEX(rastreabilidade!$F:$H,0,MATCH(X$3,rastreabilidade!$F$1:$H$1,0)),rastreabilidade!$M:$M,$AJ27),0)) -IF($AC27="",0,IFERROR(SUMIFS(INDEX(rastreabilidade!$F:$H,0,MATCH(X$3,rastreabilidade!$F$1:$H$1,0)),rastreabilidade!$M:$M,$AC27,rastreabilidade!$N:$N,$AN27),0)) -IF($AD27="",0,IFERROR(SUMIFS(INDEX(rastreabilidade!$F:$H,0,MATCH(X$3,rastreabilidade!$F$1:$H$1,0)),rastreabilidade!$M:$M,$AD27,rastreabilidade!$N:$N,$AN27),0)) -IF($AE27="",0,IFERROR(SUMIFS(INDEX(rastreabilidade!$F:$H,0,MATCH(X$3,rastreabilidade!$F$1:$H$1,0)),rastreabilidade!$M:$M,$AE27,rastreabilidade!$N:$N,$AN27),0)) -IF($AF27="",0,IFERROR(SUMIFS(INDEX(rastreabilidade!$F:$H,0,MATCH(X$3,rastreabilidade!$F$1:$H$1,0)),rastreabilidade!$M:$M,$AF27,rastreabilidade!$N:$N,$AN27),0)) -> 0 | Y27: =IFERROR(SUMIFS(INDEX(rastreabilidade!$F:$H,0,MATCH(Y$3,rastreabilidade!$F$1:$H$1,0)),rastreabilidade!$N:$N,$AN27),0)*IF($AB27="sim",-1,1) +IF($AG27="",0,IFERROR(SUMIFS(INDEX(rastreabilidade!$F:$H,0,MATCH(Y$3,rastreabilidade!$F$1:$H$1,0)),rastreabilidade!$M:$M,$AG27),0)) +IF($AH27="",0,IFERROR(SUMIFS(INDEX(rastreabilidade!$F:$H,0,MATCH(Y$3,rastreabilidade!$F$1:$H$1,0)),rastreabilidade!$M:$M,$AH27),0)) +IF($AI27="",0,IFERROR(SUMIFS(INDEX(rastreabilidade!$F:$H,0,MATCH(Y$3,rastreabilidade!$F$1:$H$1,0)),rastreabilidade!$M:$M,$AI27),0)) +IF($AJ27="",0,IFERROR(SUMIFS(INDEX(rastreabilidade!$F:$H,0,MATCH(Y$3,rastreabilidade!$F$1:$H$1,0)),rastreabilidade!$M:$M,$AJ27),0)) -IF($AC27="",0,IFERROR(SUMIFS(INDEX(rastreabilidade!$F:$H,0,MATCH(Y$3,rastreabilidade!$F$1:$H$1,0)),rastreabilidade!$M:$M,$AC27,rastreabilidade!$N:$N,$AN27),0)) -IF($AD27="",0,IFERROR(SUMIFS(INDEX(rastreabilidade!$F:$H,0,MATCH(Y$3,rastreabilidade!$F$1:$H$1,0)),rastreabilidade!$M:$M,$AD27,rastreabilidade!$N:$N,$AN27),0)) -IF($AE27="",0,IFERROR(SUMIFS(INDEX(rastreabilidade!$F:$H,0,MATCH(Y$3,rastreabilidade!$F$1:$H$1,0)),rastreabilidade!$M:$M,$AE27,rastreabilidade!$N:$N,$AN27),0)) -IF($AF27="",0,IFERROR(SUMIFS(INDEX(rastreabilidade!$F:$H,0,MATCH(Y$3,rastreabilidade!$F$1:$H$1,0)),rastreabilidade!$M:$M,$AF27,rastreabilidade!$N:$N,$AN27),0)) -> 0 | AA27: {=_xlfn.LET( _xlpm.mem,Z27, _xlpm.retiradas,AC27:AF27, _xlpm.adicoes,AG27:AJ27, _xlpm.memAjustada,_xlfn.REDUCE(_xlpm.mem,_xlpm.retiradas,_xlfn.LAMBDA(_xlpm.x,_xlpm.y,IF(_xlpm.y<>"",SUBSTITUTE(_xlpm.x," + ("&_xlpm.y&")",""),_xlpm.x))), _xlpm.memRemovida,_xlfn.REDUCE(_xlpm.memAjustada,_xlpm.retiradas,_xlfn.LAMBDA(_xlpm.x,_xlpm.y,IF(_xlpm.y<>"",SUBSTITUTE(_xlpm.x,"("&_xlpm.y&")",""),_xlpm.x))), _xlpm.memSemSinal,IF(OR(LEFT(_xlpm.memRemovida,3)=" + ",LEFT(_xlpm.memRemovida,3)=" - "),MID(_xlpm.memRemovida,4,LEN(_xlpm.memRemovida)),_xlpm.memRemovida), _xlpm.memFinal,IF(OR(RIGHT(_xlpm.memSemSinal,3)=" + ",RIGHT(_xlpm.memSemSinal,3)=" - "),LEFT(_xlpm.memSemSinal,LEN(_xlpm.memSemSinal)-3),_xlpm.memSemSinal), _xlpm.adicoesTxt,_xlfn.TEXTJOIN(" + ",TRUE,IF(_xlpm.adicoes<>"","("&_xlpm.adicoes&")","")), IF(_xlpm.memFinal="",_xlpm.adicoesTxt,IF(_xlpm.adicoesTxt="",_xlpm.memFinal,_xlpm.memFinal&" + "&_xlpm.adicoesTxt)) )} | AM27: =_xlfn.TEXTJOIN("|",TRUE,A27,"Ativo","Não Circulante") -> Aplicações Financeiras de LP|Ativo|Não Circulante | AN27: =_xlfn.CONCAT(S27,"|","DRE","|","DRE",) -> Outros não recorrentes e/ou não operacionais|DRE|DRE
A28: Outros Operacionais (ANC) | B28: =IFERROR(SUMIFS(INDEX(rastreabilidade!$F:$H,0,MATCH($B$2,rastreabilidade!$F$1:$H$1,0)),rastreabilidade!$K:$K,$A28,rastreabilidade!$D:$D,"Sim"),0) -> 0 | E28: =IFERROR(SUMIFS(INDEX(rastreabilidade!$F:$H,0,MATCH(E$3,rastreabilidade!$F$1:$H$1,0)),rastreabilidade!$N:$N,$AM28),0) +IF($N28="",0,IFERROR(SUMIFS(INDEX(rastreabilidade!$F:$H,0,MATCH(E$3,rastreabilidade!$F$1:$H$1,0)),rastreabilidade!$M:$M,$N28),0)) +IF($O28="",0,IFERROR(SUMIFS(INDEX(rastreabilidade!$F:$H,0,MATCH(E$3,rastreabilidade!$F$1:$H$1,0)),rastreabilidade!$M:$M,$O28),0)) +IF($P28="",0,IFERROR(SUMIFS(INDEX(rastreabilidade!$F:$H,0,MATCH(E$3,rastreabilidade!$F$1:$H$1,0)),rastreabilidade!$M:$M,$P28),0)) +IF($Q28="",0,IFERROR(SUMIFS(INDEX(rastreabilidade!$F:$H,0,MATCH(E$3,rastreabilidade!$F$1:$H$1,0)),rastreabilidade!$M:$M,$Q28),0)) -IF($J28="",0,IFERROR(SUMIFS(INDEX(rastreabilidade!$F:$H,0,MATCH(E$3,rastreabilidade!$F$1:$H$1,0)),rastreabilidade!$M:$M,$J28,rastreabilidade!$N:$N,$AM28),0)) -IF($K28="",0,IFERROR(SUMIFS(INDEX(rastreabilidade!$F:$H,0,MATCH(E$3,rastreabilidade!$F$1:$H$1,0)),rastreabilidade!$M:$M,$K28,rastreabilidade!$N:$N,$AM28),0)) -IF($L28="",0,IFERROR(SUMIFS(INDEX(rastreabilidade!$F:$H,0,MATCH(E$3,rastreabilidade!$F$1:$H$1,0)),rastreabilidade!$M:$M,$L28,rastreabilidade!$N:$N,$AM28),0)) -IF($M28="",0,IFERROR(SUMIFS(INDEX(rastreabilidade!$F:$H,0,MATCH(E$3,rastreabilidade!$F$1:$H$1,0)),rastreabilidade!$M:$M,$M28,rastreabilidade!$N:$N,$AM28),0)) -> 0 | F28: =IFERROR(SUMIFS(INDEX(rastreabilidade!$F:$H,0,MATCH(F$3,rastreabilidade!$F$1:$H$1,0)),rastreabilidade!$N:$N,$AM28),0) +IF($N28="",0,IFERROR(SUMIFS(INDEX(rastreabilidade!$F:$H,0,MATCH(F$3,rastreabilidade!$F$1:$H$1,0)),rastreabilidade!$M:$M,$N28),0)) +IF($O28="",0,IFERROR(SUMIFS(INDEX(rastreabilidade!$F:$H,0,MATCH(F$3,rastreabilidade!$F$1:$H$1,0)),rastreabilidade!$M:$M,$O28),0)) +IF($P28="",0,IFERROR(SUMIFS(INDEX(rastreabilidade!$F:$H,0,MATCH(F$3,rastreabilidade!$F$1:$H$1,0)),rastreabilidade!$M:$M,$P28),0)) +IF($Q28="",0,IFERROR(SUMIFS(INDEX(rastreabilidade!$F:$H,0,MATCH(F$3,rastreabilidade!$F$1:$H$1,0)),rastreabilidade!$M:$M,$Q28),0)) -IF($J28="",0,IFERROR(SUMIFS(INDEX(rastreabilidade!$F:$H,0,MATCH(F$3,rastreabilidade!$F$1:$H$1,0)),rastreabilidade!$M:$M,$J28,rastreabilidade!$N:$N,$AM28),0)) -IF($K28="",0,IFERROR(SUMIFS(INDEX(rastreabilidade!$F:$H,0,MATCH(F$3,rastreabilidade!$F$1:$H$1,0)),rastreabilidade!$M:$M,$K28,rastreabilidade!$N:$N,$AM28),0)) -IF($L28="",0,IFERROR(SUMIFS(INDEX(rastreabilidade!$F:$H,0,MATCH(F$3,rastreabilidade!$F$1:$H$1,0)),rastreabilidade!$M:$M,$L28,rastreabilidade!$N:$N,$AM28),0)) -IF($M28="",0,IFERROR(SUMIFS(INDEX(rastreabilidade!$F:$H,0,MATCH(F$3,rastreabilidade!$F$1:$H$1,0)),rastreabilidade!$M:$M,$M28,rastreabilidade!$N:$N,$AM28),0)) -> 0 | G28: =IFERROR(SUMIFS(INDEX(rastreabilidade!$F:$H,0,MATCH(G$3,rastreabilidade!$F$1:$H$1,0)),rastreabilidade!$N:$N,$AM28),0) +IF($N28="",0,IFERROR(SUMIFS(INDEX(rastreabilidade!$F:$H,0,MATCH(G$3,rastreabilidade!$F$1:$H$1,0)),rastreabilidade!$M:$M,$N28),0)) +IF($O28="",0,IFERROR(SUMIFS(INDEX(rastreabilidade!$F:$H,0,MATCH(G$3,rastreabilidade!$F$1:$H$1,0)),rastreabilidade!$M:$M,$O28),0)) +IF($P28="",0,IFERROR(SUMIFS(INDEX(rastreabilidade!$F:$H,0,MATCH(G$3,rastreabilidade!$F$1:$H$1,0)),rastreabilidade!$M:$M,$P28),0)) +IF($Q28="",0,IFERROR(SUMIFS(INDEX(rastreabilidade!$F:$H,0,MATCH(G$3,rastreabilidade!$F$1:$H$1,0)),rastreabilidade!$M:$M,$Q28),0)) -IF($J28="",0,IFERROR(SUMIFS(INDEX(rastreabilidade!$F:$H,0,MATCH(G$3,rastreabilidade!$F$1:$H$1,0)),rastreabilidade!$M:$M,$J28,rastreabilidade!$N:$N,$AM28),0)) -IF($K28="",0,IFERROR(SUMIFS(INDEX(rastreabilidade!$F:$H,0,MATCH(G$3,rastreabilidade!$F$1:$H$1,0)),rastreabilidade!$M:$M,$K28,rastreabilidade!$N:$N,$AM28),0)) -IF($L28="",0,IFERROR(SUMIFS(INDEX(rastreabilidade!$F:$H,0,MATCH(G$3,rastreabilidade!$F$1:$H$1,0)),rastreabilidade!$M:$M,$L28,rastreabilidade!$N:$N,$AM28),0)) -IF($M28="",0,IFERROR(SUMIFS(INDEX(rastreabilidade!$F:$H,0,MATCH(G$3,rastreabilidade!$F$1:$H$1,0)),rastreabilidade!$M:$M,$M28,rastreabilidade!$N:$N,$AM28),0)) -> 0 | I28: {=_xlfn.LET( _xlpm.mem,H28, _xlpm.retiradas,J28:M28, _xlpm.adicoes,N28:Q28, _xlpm.memAjustada,_xlfn.REDUCE(_xlpm.mem,_xlpm.retiradas,_xlfn.LAMBDA(_xlpm.x,_xlpm.y,IF(_xlpm.y<>"",SUBSTITUTE(_xlpm.x," + ("&_xlpm.y&")",""),_xlpm.x))), _xlpm.memRemovida,_xlfn.REDUCE(_xlpm.memAjustada,_xlpm.retiradas,_xlfn.LAMBDA(_xlpm.x,_xlpm.y,IF(_xlpm.y<>"",SUBSTITUTE(_xlpm.x,"("&_xlpm.y&")",""),_xlpm.x))), _xlpm.memSemSinal,IF(OR(LEFT(_xlpm.memRemovida,3)=" + ",LEFT(_xlpm.memRemovida,3)=" - "),MID(_xlpm.memRemovida,4,LEN(_xlpm.memRemovida)),_xlpm.memRemovida), _xlpm.memFinal,IF(OR(RIGHT(_xlpm.memSemSinal,3)=" + ",RIGHT(_xlpm.memSemSinal,3)=" - "),LEFT(_xlpm.memSemSinal,LEN(_xlpm.memSemSinal)-3),_xlpm.memSemSinal), _xlpm.adicoesTxt,_xlfn.TEXTJOIN(" + ",TRUE,IF(_xlpm.adicoes<>"","("&_xlpm.adicoes&")","")), IF(_xlpm.memFinal="",_xlpm.adicoesTxt,IF(_xlpm.adicoesTxt="",_xlpm.memFinal,_xlpm.memFinal&" + "&_xlpm.adicoesTxt)) )} | S28: +/- Créditos Tributários | T28: =IFERROR(SUMIFS(INDEX(rastreabilidade!$F:$H,0,MATCH($T$2,rastreabilidade!$F$1:$H$1,0)),rastreabilidade!$K:$K,$S28,rastreabilidade!$D:$D,"Sim"),0) -> 0 | W28: =IFERROR(SUMIFS(INDEX(rastreabilidade!$F:$H,0,MATCH(W$3,rastreabilidade!$F$1:$H$1,0)),rastreabilidade!$N:$N,$AN28),0)*IF($AB28="sim",-1,1) +IF($AG28="",0,IFERROR(SUMIFS(INDEX(rastreabilidade!$F:$H,0,MATCH(W$3,rastreabilidade!$F$1:$H$1,0)),rastreabilidade!$M:$M,$AG28),0)) +IF($AH28="",0,IFERROR(SUMIFS(INDEX(rastreabilidade!$F:$H,0,MATCH(W$3,rastreabilidade!$F$1:$H$1,0)),rastreabilidade!$M:$M,$AH28),0)) +IF($AI28="",0,IFERROR(SUMIFS(INDEX(rastreabilidade!$F:$H,0,MATCH(W$3,rastreabilidade!$F$1:$H$1,0)),rastreabilidade!$M:$M,$AI28),0)) +IF($AJ28="",0,IFERROR(SUMIFS(INDEX(rastreabilidade!$F:$H,0,MATCH(W$3,rastreabilidade!$F$1:$H$1,0)),rastreabilidade!$M:$M,$AJ28),0)) -IF($AC28="",0,IFERROR(SUMIFS(INDEX(rastreabilidade!$F:$H,0,MATCH(W$3,rastreabilidade!$F$1:$H$1,0)),rastreabilidade!$M:$M,$AC28,rastreabilidade!$N:$N,$AN28),0)) -IF($AD28="",0,IFERROR(SUMIFS(INDEX(rastreabilidade!$F:$H,0,MATCH(W$3,rastreabilidade!$F$1:$H$1,0)),rastreabilidade!$M:$M,$AD28,rastreabilidade!$N:$N,$AN28),0)) -IF($AE28="",0,IFERROR(SUMIFS(INDEX(rastreabilidade!$F:$H,0,MATCH(W$3,rastreabilidade!$F$1:$H$1,0)),rastreabilidade!$M:$M,$AE28,rastreabilidade!$N:$N,$AN28),0)) -IF($AF28="",0,IFERROR(SUMIFS(INDEX(rastreabilidade!$F:$H,0,MATCH(W$3,rastreabilidade!$F$1:$H$1,0)),rastreabilidade!$M:$M,$AF28,rastreabilidade!$N:$N,$AN28),0)) -> 0 | X28: =IFERROR(SUMIFS(INDEX(rastreabilidade!$F:$H,0,MATCH(X$3,rastreabilidade!$F$1:$H$1,0)),rastreabilidade!$N:$N,$AN28),0)*IF($AB28="sim",-1,1) +IF($AG28="",0,IFERROR(SUMIFS(INDEX(rastreabilidade!$F:$H,0,MATCH(X$3,rastreabilidade!$F$1:$H$1,0)),rastreabilidade!$M:$M,$AG28),0)) +IF($AH28="",0,IFERROR(SUMIFS(INDEX(rastreabilidade!$F:$H,0,MATCH(X$3,rastreabilidade!$F$1:$H$1,0)),rastreabilidade!$M:$M,$AH28),0)) +IF($AI28="",0,IFERROR(SUMIFS(INDEX(rastreabilidade!$F:$H,0,MATCH(X$3,rastreabilidade!$F$1:$H$1,0)),rastreabilidade!$M:$M,$AI28),0)) +IF($AJ28="",0,IFERROR(SUMIFS(INDEX(rastreabilidade!$F:$H,0,MATCH(X$3,rastreabilidade!$F$1:$H$1,0)),rastreabilidade!$M:$M,$AJ28),0)) -IF($AC28="",0,IFERROR(SUMIFS(INDEX(rastreabilidade!$F:$H,0,MATCH(X$3,rastreabilidade!$F$1:$H$1,0)),rastreabilidade!$M:$M,$AC28,rastreabilidade!$N:$N,$AN28),0)) -IF($AD28="",0,IFERROR(SUMIFS(INDEX(rastreabilidade!$F:$H,0,MATCH(X$3,rastreabilidade!$F$1:$H$1,0)),rastreabilidade!$M:$M,$AD28,rastreabilidade!$N:$N,$AN28),0)) -IF($AE28="",0,IFERROR(SUMIFS(INDEX(rastreabilidade!$F:$H,0,MATCH(X$3,rastreabilidade!$F$1:$H$1,0)),rastreabilidade!$M:$M,$AE28,rastreabilidade!$N:$N,$AN28),0)) -IF($AF28="",0,IFERROR(SUMIFS(INDEX(rastreabilidade!$F:$H,0,MATCH(X$3,rastreabilidade!$F$1:$H$1,0)),rastreabilidade!$M:$M,$AF28,rastreabilidade!$N:$N,$AN28),0)) -> 0 | Y28: =IFERROR(SUMIFS(INDEX(rastreabilidade!$F:$H,0,MATCH(Y$3,rastreabilidade!$F$1:$H$1,0)),rastreabilidade!$N:$N,$AN28),0)*IF($AB28="sim",-1,1) +IF($AG28="",0,IFERROR(SUMIFS(INDEX(rastreabilidade!$F:$H,0,MATCH(Y$3,rastreabilidade!$F$1:$H$1,0)),rastreabilidade!$M:$M,$AG28),0)) +IF($AH28="",0,IFERROR(SUMIFS(INDEX(rastreabilidade!$F:$H,0,MATCH(Y$3,rastreabilidade!$F$1:$H$1,0)),rastreabilidade!$M:$M,$AH28),0)) +IF($AI28="",0,IFERROR(SUMIFS(INDEX(rastreabilidade!$F:$H,0,MATCH(Y$3,rastreabilidade!$F$1:$H$1,0)),rastreabilidade!$M:$M,$AI28),0)) +IF($AJ28="",0,IFERROR(SUMIFS(INDEX(rastreabilidade!$F:$H,0,MATCH(Y$3,rastreabilidade!$F$1:$H$1,0)),rastreabilidade!$M:$M,$AJ28),0)) -IF($AC28="",0,IFERROR(SUMIFS(INDEX(rastreabilidade!$F:$H,0,MATCH(Y$3,rastreabilidade!$F$1:$H$1,0)),rastreabilidade!$M:$M,$AC28,rastreabilidade!$N:$N,$AN28),0)) -IF($AD28="",0,IFERROR(SUMIFS(INDEX(rastreabilidade!$F:$H,0,MATCH(Y$3,rastreabilidade!$F$1:$H$1,0)),rastreabilidade!$M:$M,$AD28,rastreabilidade!$N:$N,$AN28),0)) -IF($AE28="",0,IFERROR(SUMIFS(INDEX(rastreabilidade!$F:$H,0,MATCH(Y$3,rastreabilidade!$F$1:$H$1,0)),rastreabilidade!$M:$M,$AE28,rastreabilidade!$N:$N,$AN28),0)) -IF($AF28="",0,IFERROR(SUMIFS(INDEX(rastreabilidade!$F:$H,0,MATCH(Y$3,rastreabilidade!$F$1:$H$1,0)),rastreabilidade!$M:$M,$AF28,rastreabilidade!$N:$N,$AN28),0)) -> 0 | AA28: {=_xlfn.LET( _xlpm.mem,Z28, _xlpm.retiradas,AC28:AF28, _xlpm.adicoes,AG28:AJ28, _xlpm.memAjustada,_xlfn.REDUCE(_xlpm.mem,_xlpm.retiradas,_xlfn.LAMBDA(_xlpm.x,_xlpm.y,IF(_xlpm.y<>"",SUBSTITUTE(_xlpm.x," + ("&_xlpm.y&")",""),_xlpm.x))), _xlpm.memRemovida,_xlfn.REDUCE(_xlpm.memAjustada,_xlpm.retiradas,_xlfn.LAMBDA(_xlpm.x,_xlpm.y,IF(_xlpm.y<>"",SUBSTITUTE(_xlpm.x,"("&_xlpm.y&")",""),_xlpm.x))), _xlpm.memSemSinal,IF(OR(LEFT(_xlpm.memRemovida,3)=" + ",LEFT(_xlpm.memRemovida,3)=" - "),MID(_xlpm.memRemovida,4,LEN(_xlpm.memRemovida)),_xlpm.memRemovida), _xlpm.memFinal,IF(OR(RIGHT(_xlpm.memSemSinal,3)=" + ",RIGHT(_xlpm.memSemSinal,3)=" - "),LEFT(_xlpm.memSemSinal,LEN(_xlpm.memSemSinal)-3),_xlpm.memSemSinal), _xlpm.adicoesTxt,_xlfn.TEXTJOIN(" + ",TRUE,IF(_xlpm.adicoes<>"","("&_xlpm.adicoes&")","")), IF(_xlpm.memFinal="",_xlpm.adicoesTxt,IF(_xlpm.adicoesTxt="",_xlpm.memFinal,_xlpm.memFinal&" + "&_xlpm.adicoesTxt)) )} | AM28: =_xlfn.TEXTJOIN("|",TRUE,A28,"Ativo","Não Circulante") -> Outros Operacionais (ANC)|Ativo|Não Circulante | AN28: =_xlfn.CONCAT(S28,"|","DRE","|","DRE",) -> +/- Créditos Tributários|DRE|DRE
A29: Outros Não Operacionais LP (ANC) | B29: =IFERROR(SUMIFS(INDEX(rastreabilidade!$F:$H,0,MATCH($B$2,rastreabilidade!$F$1:$H$1,0)),rastreabilidade!$K:$K,$A29,rastreabilidade!$D:$D,"Sim"),0) -> 0 | E29: =IFERROR(SUMIFS(INDEX(rastreabilidade!$F:$H,0,MATCH(E$3,rastreabilidade!$F$1:$H$1,0)),rastreabilidade!$N:$N,$AM29),0) +IF($N29="",0,IFERROR(SUMIFS(INDEX(rastreabilidade!$F:$H,0,MATCH(E$3,rastreabilidade!$F$1:$H$1,0)),rastreabilidade!$M:$M,$N29),0)) +IF($O29="",0,IFERROR(SUMIFS(INDEX(rastreabilidade!$F:$H,0,MATCH(E$3,rastreabilidade!$F$1:$H$1,0)),rastreabilidade!$M:$M,$O29),0)) +IF($P29="",0,IFERROR(SUMIFS(INDEX(rastreabilidade!$F:$H,0,MATCH(E$3,rastreabilidade!$F$1:$H$1,0)),rastreabilidade!$M:$M,$P29),0)) +IF($Q29="",0,IFERROR(SUMIFS(INDEX(rastreabilidade!$F:$H,0,MATCH(E$3,rastreabilidade!$F$1:$H$1,0)),rastreabilidade!$M:$M,$Q29),0)) -IF($J29="",0,IFERROR(SUMIFS(INDEX(rastreabilidade!$F:$H,0,MATCH(E$3,rastreabilidade!$F$1:$H$1,0)),rastreabilidade!$M:$M,$J29,rastreabilidade!$N:$N,$AM29),0)) -IF($K29="",0,IFERROR(SUMIFS(INDEX(rastreabilidade!$F:$H,0,MATCH(E$3,rastreabilidade!$F$1:$H$1,0)),rastreabilidade!$M:$M,$K29,rastreabilidade!$N:$N,$AM29),0)) -IF($L29="",0,IFERROR(SUMIFS(INDEX(rastreabilidade!$F:$H,0,MATCH(E$3,rastreabilidade!$F$1:$H$1,0)),rastreabilidade!$M:$M,$L29,rastreabilidade!$N:$N,$AM29),0)) -IF($M29="",0,IFERROR(SUMIFS(INDEX(rastreabilidade!$F:$H,0,MATCH(E$3,rastreabilidade!$F$1:$H$1,0)),rastreabilidade!$M:$M,$M29,rastreabilidade!$N:$N,$AM29),0)) -> 0 | F29: =IFERROR(SUMIFS(INDEX(rastreabilidade!$F:$H,0,MATCH(F$3,rastreabilidade!$F$1:$H$1,0)),rastreabilidade!$N:$N,$AM29),0) +IF($N29="",0,IFERROR(SUMIFS(INDEX(rastreabilidade!$F:$H,0,MATCH(F$3,rastreabilidade!$F$1:$H$1,0)),rastreabilidade!$M:$M,$N29),0)) +IF($O29="",0,IFERROR(SUMIFS(INDEX(rastreabilidade!$F:$H,0,MATCH(F$3,rastreabilidade!$F$1:$H$1,0)),rastreabilidade!$M:$M,$O29),0)) +IF($P29="",0,IFERROR(SUMIFS(INDEX(rastreabilidade!$F:$H,0,MATCH(F$3,rastreabilidade!$F$1:$H$1,0)),rastreabilidade!$M:$M,$P29),0)) +IF($Q29="",0,IFERROR(SUMIFS(INDEX(rastreabilidade!$F:$H,0,MATCH(F$3,rastreabilidade!$F$1:$H$1,0)),rastreabilidade!$M:$M,$Q29),0)) -IF($J29="",0,IFERROR(SUMIFS(INDEX(rastreabilidade!$F:$H,0,MATCH(F$3,rastreabilidade!$F$1:$H$1,0)),rastreabilidade!$M:$M,$J29,rastreabilidade!$N:$N,$AM29),0)) -IF($K29="",0,IFERROR(SUMIFS(INDEX(rastreabilidade!$F:$H,0,MATCH(F$3,rastreabilidade!$F$1:$H$1,0)),rastreabilidade!$M:$M,$K29,rastreabilidade!$N:$N,$AM29),0)) -IF($L29="",0,IFERROR(SUMIFS(INDEX(rastreabilidade!$F:$H,0,MATCH(F$3,rastreabilidade!$F$1:$H$1,0)),rastreabilidade!$M:$M,$L29,rastreabilidade!$N:$N,$AM29),0)) -IF($M29="",0,IFERROR(SUMIFS(INDEX(rastreabilidade!$F:$H,0,MATCH(F$3,rastreabilidade!$F$1:$H$1,0)),rastreabilidade!$M:$M,$M29,rastreabilidade!$N:$N,$AM29),0)) -> 0 | G29: =IFERROR(SUMIFS(INDEX(rastreabilidade!$F:$H,0,MATCH(G$3,rastreabilidade!$F$1:$H$1,0)),rastreabilidade!$N:$N,$AM29),0) +IF($N29="",0,IFERROR(SUMIFS(INDEX(rastreabilidade!$F:$H,0,MATCH(G$3,rastreabilidade!$F$1:$H$1,0)),rastreabilidade!$M:$M,$N29),0)) +IF($O29="",0,IFERROR(SUMIFS(INDEX(rastreabilidade!$F:$H,0,MATCH(G$3,rastreabilidade!$F$1:$H$1,0)),rastreabilidade!$M:$M,$O29),0)) +IF($P29="",0,IFERROR(SUMIFS(INDEX(rastreabilidade!$F:$H,0,MATCH(G$3,rastreabilidade!$F$1:$H$1,0)),rastreabilidade!$M:$M,$P29),0)) +IF($Q29="",0,IFERROR(SUMIFS(INDEX(rastreabilidade!$F:$H,0,MATCH(G$3,rastreabilidade!$F$1:$H$1,0)),rastreabilidade!$M:$M,$Q29),0)) -IF($J29="",0,IFERROR(SUMIFS(INDEX(rastreabilidade!$F:$H,0,MATCH(G$3,rastreabilidade!$F$1:$H$1,0)),rastreabilidade!$M:$M,$J29,rastreabilidade!$N:$N,$AM29),0)) -IF($K29="",0,IFERROR(SUMIFS(INDEX(rastreabilidade!$F:$H,0,MATCH(G$3,rastreabilidade!$F$1:$H$1,0)),rastreabilidade!$M:$M,$K29,rastreabilidade!$N:$N,$AM29),0)) -IF($L29="",0,IFERROR(SUMIFS(INDEX(rastreabilidade!$F:$H,0,MATCH(G$3,rastreabilidade!$F$1:$H$1,0)),rastreabilidade!$M:$M,$L29,rastreabilidade!$N:$N,$AM29),0)) -IF($M29="",0,IFERROR(SUMIFS(INDEX(rastreabilidade!$F:$H,0,MATCH(G$3,rastreabilidade!$F$1:$H$1,0)),rastreabilidade!$M:$M,$M29,rastreabilidade!$N:$N,$AM29),0)) -> 0 | I29: {=_xlfn.LET( _xlpm.mem,H29, _xlpm.retiradas,J29:M29, _xlpm.adicoes,N29:Q29, _xlpm.memAjustada,_xlfn.REDUCE(_xlpm.mem,_xlpm.retiradas,_xlfn.LAMBDA(_xlpm.x,_xlpm.y,IF(_xlpm.y<>"",SUBSTITUTE(_xlpm.x," + ("&_xlpm.y&")",""),_xlpm.x))), _xlpm.memRemovida,_xlfn.REDUCE(_xlpm.memAjustada,_xlpm.retiradas,_xlfn.LAMBDA(_xlpm.x,_xlpm.y,IF(_xlpm.y<>"",SUBSTITUTE(_xlpm.x,"("&_xlpm.y&")",""),_xlpm.x))), _xlpm.memSemSinal,IF(OR(LEFT(_xlpm.memRemovida,3)=" + ",LEFT(_xlpm.memRemovida,3)=" - "),MID(_xlpm.memRemovida,4,LEN(_xlpm.memRemovida)),_xlpm.memRemovida), _xlpm.memFinal,IF(OR(RIGHT(_xlpm.memSemSinal,3)=" + ",RIGHT(_xlpm.memSemSinal,3)=" - "),LEFT(_xlpm.memSemSinal,LEN(_xlpm.memSemSinal)-3),_xlpm.memSemSinal), _xlpm.adicoesTxt,_xlfn.TEXTJOIN(" + ",TRUE,IF(_xlpm.adicoes<>"","("&_xlpm.adicoes&")","")), IF(_xlpm.memFinal="",_xlpm.adicoesTxt,IF(_xlpm.adicoesTxt="",_xlpm.memFinal,_xlpm.memFinal&" + "&_xlpm.adicoesTxt)) )} | S29: +/- Resultado de alienação do Imobilizado | T29: =IFERROR(SUMIFS(INDEX(rastreabilidade!$F:$H,0,MATCH($T$2,rastreabilidade!$F$1:$H$1,0)),rastreabilidade!$K:$K,$S29,rastreabilidade!$D:$D,"Sim"),0) -> 0 | W29: =IFERROR(SUMIFS(INDEX(rastreabilidade!$F:$H,0,MATCH(W$3,rastreabilidade!$F$1:$H$1,0)),rastreabilidade!$N:$N,$AN29),0)*IF($AB29="sim",-1,1) +IF($AG29="",0,IFERROR(SUMIFS(INDEX(rastreabilidade!$F:$H,0,MATCH(W$3,rastreabilidade!$F$1:$H$1,0)),rastreabilidade!$M:$M,$AG29),0)) +IF($AH29="",0,IFERROR(SUMIFS(INDEX(rastreabilidade!$F:$H,0,MATCH(W$3,rastreabilidade!$F$1:$H$1,0)),rastreabilidade!$M:$M,$AH29),0)) +IF($AI29="",0,IFERROR(SUMIFS(INDEX(rastreabilidade!$F:$H,0,MATCH(W$3,rastreabilidade!$F$1:$H$1,0)),rastreabilidade!$M:$M,$AI29),0)) +IF($AJ29="",0,IFERROR(SUMIFS(INDEX(rastreabilidade!$F:$H,0,MATCH(W$3,rastreabilidade!$F$1:$H$1,0)),rastreabilidade!$M:$M,$AJ29),0)) -IF($AC29="",0,IFERROR(SUMIFS(INDEX(rastreabilidade!$F:$H,0,MATCH(W$3,rastreabilidade!$F$1:$H$1,0)),rastreabilidade!$M:$M,$AC29,rastreabilidade!$N:$N,$AN29),0)) -IF($AD29="",0,IFERROR(SUMIFS(INDEX(rastreabilidade!$F:$H,0,MATCH(W$3,rastreabilidade!$F$1:$H$1,0)),rastreabilidade!$M:$M,$AD29,rastreabilidade!$N:$N,$AN29),0)) -IF($AE29="",0,IFERROR(SUMIFS(INDEX(rastreabilidade!$F:$H,0,MATCH(W$3,rastreabilidade!$F$1:$H$1,0)),rastreabilidade!$M:$M,$AE29,rastreabilidade!$N:$N,$AN29),0)) -IF($AF29="",0,IFERROR(SUMIFS(INDEX(rastreabilidade!$F:$H,0,MATCH(W$3,rastreabilidade!$F$1:$H$1,0)),rastreabilidade!$M:$M,$AF29,rastreabilidade!$N:$N,$AN29),0)) -> 0 | X29: =IFERROR(SUMIFS(INDEX(rastreabilidade!$F:$H,0,MATCH(X$3,rastreabilidade!$F$1:$H$1,0)),rastreabilidade!$N:$N,$AN29),0)*IF($AB29="sim",-1,1) +IF($AG29="",0,IFERROR(SUMIFS(INDEX(rastreabilidade!$F:$H,0,MATCH(X$3,rastreabilidade!$F$1:$H$1,0)),rastreabilidade!$M:$M,$AG29),0)) +IF($AH29="",0,IFERROR(SUMIFS(INDEX(rastreabilidade!$F:$H,0,MATCH(X$3,rastreabilidade!$F$1:$H$1,0)),rastreabilidade!$M:$M,$AH29),0)) +IF($AI29="",0,IFERROR(SUMIFS(INDEX(rastreabilidade!$F:$H,0,MATCH(X$3,rastreabilidade!$F$1:$H$1,0)),rastreabilidade!$M:$M,$AI29),0)) +IF($AJ29="",0,IFERROR(SUMIFS(INDEX(rastreabilidade!$F:$H,0,MATCH(X$3,rastreabilidade!$F$1:$H$1,0)),rastreabilidade!$M:$M,$AJ29),0)) -IF($AC29="",0,IFERROR(SUMIFS(INDEX(rastreabilidade!$F:$H,0,MATCH(X$3,rastreabilidade!$F$1:$H$1,0)),rastreabilidade!$M:$M,$AC29,rastreabilidade!$N:$N,$AN29),0)) -IF($AD29="",0,IFERROR(SUMIFS(INDEX(rastreabilidade!$F:$H,0,MATCH(X$3,rastreabilidade!$F$1:$H$1,0)),rastreabilidade!$M:$M,$AD29,rastreabilidade!$N:$N,$AN29),0)) -IF($AE29="",0,IFERROR(SUMIFS(INDEX(rastreabilidade!$F:$H,0,MATCH(X$3,rastreabilidade!$F$1:$H$1,0)),rastreabilidade!$M:$M,$AE29,rastreabilidade!$N:$N,$AN29),0)) -IF($AF29="",0,IFERROR(SUMIFS(INDEX(rastreabilidade!$F:$H,0,MATCH(X$3,rastreabilidade!$F$1:$H$1,0)),rastreabilidade!$M:$M,$AF29,rastreabilidade!$N:$N,$AN29),0)) -> 0 | Y29: =IFERROR(SUMIFS(INDEX(rastreabilidade!$F:$H,0,MATCH(Y$3,rastreabilidade!$F$1:$H$1,0)),rastreabilidade!$N:$N,$AN29),0)*IF($AB29="sim",-1,1) +IF($AG29="",0,IFERROR(SUMIFS(INDEX(rastreabilidade!$F:$H,0,MATCH(Y$3,rastreabilidade!$F$1:$H$1,0)),rastreabilidade!$M:$M,$AG29),0)) +IF($AH29="",0,IFERROR(SUMIFS(INDEX(rastreabilidade!$F:$H,0,MATCH(Y$3,rastreabilidade!$F$1:$H$1,0)),rastreabilidade!$M:$M,$AH29),0)) +IF($AI29="",0,IFERROR(SUMIFS(INDEX(rastreabilidade!$F:$H,0,MATCH(Y$3,rastreabilidade!$F$1:$H$1,0)),rastreabilidade!$M:$M,$AI29),0)) +IF($AJ29="",0,IFERROR(SUMIFS(INDEX(rastreabilidade!$F:$H,0,MATCH(Y$3,rastreabilidade!$F$1:$H$1,0)),rastreabilidade!$M:$M,$AJ29),0)) -IF($AC29="",0,IFERROR(SUMIFS(INDEX(rastreabilidade!$F:$H,0,MATCH(Y$3,rastreabilidade!$F$1:$H$1,0)),rastreabilidade!$M:$M,$AC29,rastreabilidade!$N:$N,$AN29),0)) -IF($AD29="",0,IFERROR(SUMIFS(INDEX(rastreabilidade!$F:$H,0,MATCH(Y$3,rastreabilidade!$F$1:$H$1,0)),rastreabilidade!$M:$M,$AD29,rastreabilidade!$N:$N,$AN29),0)) -IF($AE29="",0,IFERROR(SUMIFS(INDEX(rastreabilidade!$F:$H,0,MATCH(Y$3,rastreabilidade!$F$1:$H$1,0)),rastreabilidade!$M:$M,$AE29,rastreabilidade!$N:$N,$AN29),0)) -IF($AF29="",0,IFERROR(SUMIFS(INDEX(rastreabilidade!$F:$H,0,MATCH(Y$3,rastreabilidade!$F$1:$H$1,0)),rastreabilidade!$M:$M,$AF29,rastreabilidade!$N:$N,$AN29),0)) -> 0 | AA29: {=_xlfn.LET( _xlpm.mem,Z29, _xlpm.retiradas,AC29:AF29, _xlpm.adicoes,AG29:AJ29, _xlpm.memAjustada,_xlfn.REDUCE(_xlpm.mem,_xlpm.retiradas,_xlfn.LAMBDA(_xlpm.x,_xlpm.y,IF(_xlpm.y<>"",SUBSTITUTE(_xlpm.x," + ("&_xlpm.y&")",""),_xlpm.x))), _xlpm.memRemovida,_xlfn.REDUCE(_xlpm.memAjustada,_xlpm.retiradas,_xlfn.LAMBDA(_xlpm.x,_xlpm.y,IF(_xlpm.y<>"",SUBSTITUTE(_xlpm.x,"("&_xlpm.y&")",""),_xlpm.x))), _xlpm.memSemSinal,IF(OR(LEFT(_xlpm.memRemovida,3)=" + ",LEFT(_xlpm.memRemovida,3)=" - "),MID(_xlpm.memRemovida,4,LEN(_xlpm.memRemovida)),_xlpm.memRemovida), _xlpm.memFinal,IF(OR(RIGHT(_xlpm.memSemSinal,3)=" + ",RIGHT(_xlpm.memSemSinal,3)=" - "),LEFT(_xlpm.memSemSinal,LEN(_xlpm.memSemSinal)-3),_xlpm.memSemSinal), _xlpm.adicoesTxt,_xlfn.TEXTJOIN(" + ",TRUE,IF(_xlpm.adicoes<>"","("&_xlpm.adicoes&")","")), IF(_xlpm.memFinal="",_xlpm.adicoesTxt,IF(_xlpm.adicoesTxt="",_xlpm.memFinal,_xlpm.memFinal&" + "&_xlpm.adicoesTxt)) )} | AM29: =_xlfn.TEXTJOIN("|",TRUE,A29,"Ativo","Não Circulante") -> Outros Não Operacionais LP (ANC)|Ativo|Não Circulante | AN29: =_xlfn.CONCAT(S29,"|","DRE","|","DRE",) -> +/- Resultado de alienação do Imobilizado|DRE|DRE
